Workbook
Name _FilterDatabase_0: 'Přehled dne'!$A$3:$AJ$3
Name _FilterDatabase_0_0: 'Přehled dne'!$A$3:$AJ$3
Name _FilterDatabase_0_0_0: 'Přehled dne'!$A$3:$AJ$3
Name _FilterDatabase_0_0_0_0: 'Přehled dne'!$A$3:$AJ$3
Name _FilterDatabase_0_0_0_0_0: 'Přehled dne'!$A$3:$AJ$3
Name _FilterDatabase_0: 'Fiskalizované doklady'!$A$3:$AK$3
Name _FilterDatabase_0_0: 'Fiskalizované doklady'!$A$3:$AK$3
Name _FilterDatabase_0_0_0: 'Fiskalizované doklady'!$A$3:$AK$3
Name _FilterDatabase_0_0_0_0: 'Fiskalizované doklady'!$A$3:$AK$3
Name _FilterDatabase_0_0_0_0_0: 'Fiskalizované doklady'!$A$3:$AK$3
Name _FilterDatabase_0: 'Položky dokladů'!$A$3:$AC$3
Name _FilterDatabase_0_0: 'Položky dokladů'!$A$3:$AC$3
Name _FilterDatabase_0_0_0: 'Položky dokladů'!$A$3:$AC$3
Name _FilterDatabase_0_0_0_0: 'Položky dokladů'!$A$3:$AC$3
Name _FilterDatabase_0_0_0_0_0: 'Položky dokladů'!$A$3:$AC$3
Name _FilterDatabase_0: 'Zrušené položky'!$A$3:$Y$3
Name _FilterDatabase_0_0: 'Zrušené položky'!$A$3:$Y$3
Name _FilterDatabase_0_0_0: 'Zrušené položky'!$A$3:$Y$3
Name _FilterDatabase_0_0_0_0: 'Zrušené položky'!$A$3:$Y$3
Name _FilterDatabase_0_0_0_0_0: 'Zrušené položky'!$A$3:$Y$3

Sheet SOUHRN
A1: OBDOBÍ OD: | B1: 46132
A2: OBDOBÍ DO: | B2: 46132
A3: FIRMA: | B3: RAPO BRNO, s.r.o.
A4: DIČ: | B4: CZ60738677
A5: PROVOZOVNA: | B5: BALADA - Březinky
A6: ID PROVOZOVNY: | B6: 96
A7: ID POKLADNY: | B7: Více pokladen
A8: UŽIVATEL: | B8: Více uživatelů
A11: TRŽBY | B11: FISKALIZOVANÉ | C11: NEFISKALIZOVANÉ | D11: CELKEM | F11: STAV POKLADNY
A12: zdroj dat: | B12: záložka Fiskalizované doklady | C12: záložka Nefiskalizované doklady | D12: součet | F12: zdroj dat: | G12: záložka Přehled dne
B13: =IF(COUNTA('Fiskalizované doklady'!G4:G999932)=SUBTOTAL(103,'Fiskalizované doklady'!G4:G999932),"","Na datech záložky je nastaven filtr") | C13: =IF(COUNTA('Nefiskalizované doklady'!G1:G999994)=SUBTOTAL(103,'Nefiskalizované doklady'!G1:G999994),"","Na datech záložky je nastaven filtr") | G13: =IF(COUNTA('Přehled dne'!A4:A999990)=SUBTOTAL(103,'Přehled dne'!A4:A999990),"","Na datech záložky je nastaven filtr")
A14: TRŽBY CELKEM | B14: ='Fiskalizované doklady'!J2 -> 0 | C14: ='Nefiskalizované doklady'!J2 -> 92316.38 | D14: =B14+C14 -> 92316.38 | F14: POČÁTEČNÍ STAV K DATU | G14: 46132.015
A15: Poskytnuté slevy | B15: ='Fiskalizované doklady'!AL2 -> 0 | C15: ='Nefiskalizované doklady'!AF2 -> 1083.0861 | D15: =B15+C15 -> 1083.0861 | F15: Hotovost | G15: 0
A16: Zaokrouhlení | B16: ='Fiskalizované doklady'!M2 -> 0 | C16: ='Nefiskalizované doklady'!M2 -> 21.23 | D16: =B16+C16 -> 21.23 | F16: Stravenky | G16: 0
F17: Počáteční stav celkem | G17: =G15+G16 -> 0
A18: OBRATY
A19: Zboží bez DPH prodané | B19: ='Fiskalizované doklady'!S2 -> 0 | C19: ='Nefiskalizované doklady'!S2 -> 80438.671 | D19: =B19+C19 -> 80438.671 | F19: ÚHRADY
A20: Zboží bez DPH vrácené | B20: ='Fiskalizované doklady'!U2 -> 0 | C20: ='Nefiskalizované doklady'!U2 -> 0 | D20: =B20+C20 -> 0 | F20: Hotovost | G20: =D40 -> 38903
A21: Saldo prodeje bez DPH | B21: =B19+B20 -> 0 | C21: =C19+C20 -> 80438.671 | D21: =B21+C21 -> 80438.671 | F21: Stravenky | G21: =D41 -> 0
A22: Zboží s DPH prodané | B22: ='Fiskalizované doklady'!T2 -> 0 | C22: ='Nefiskalizované doklady'!T2 -> 92289.15 | D22: =B22+C22 -> 92289.15 | F22: Platby celkem | G22: =G20+G21 -> 38903
A23: Zboží s DPH vrácené | B23: ='Fiskalizované doklady'!V2 -> 0 | C23: ='Nefiskalizované doklady'!V2 -> 0 | D23: =B23+C23 -> 0
A24: Saldo prodeje s DPH | B24: =B22+B23 -> 0 | C24: =C22+C23 -> 92289.15 | D24: =B24+C24 -> 92289.15 | F24: CASHBACK
A25: Obaly prodané | B25: ='Fiskalizované doklady'!W2 -> 0 | C25: ='Nefiskalizované doklady'!W2 -> 75 | D25: =B25+C25 -> 75 | F25: Cashback | G25: ='Přehled dne'!AB2 -> 0
A26: Obaly vykoupené | B26: ='Fiskalizované doklady'!X2 -> 0 | C26: ='Nefiskalizované doklady'!X2 -> -69 | D26: =B26+C26 -> -69 | F26: CASHBACK celkem | G26: =G25 -> 0
A27: Saldo obalů | B27: =B25+B26 -> 0 | C27: =C25+C26 -> 6 | D27: =B27+C27 -> 6
A28: Zaokrouhlení | B28: ='Fiskalizované doklady'!Y2 -> 0 | C28: ='Nefiskalizované doklady'!Y2 -> 21.23 | D28: =B28+C28 -> 21.23 | F28: DOTACE A ODVODY
A29: kontrolní součet | B29: =B24+B27+B28 -> 0 | C29: =C24+C27+C28 -> 92316.38 | D29: =B29+C29 -> 92316.38 | F29: Dotace - hotovost | G29: ='Přehled dne'!AC2 -> 0
A30: DPH | F30: Dotace - stravenky | G30: ='Přehled dne'!AD2 -> 0
A31: Základ 21% | B31: ='Fiskalizované doklady'!N2 -> 0 | C31: ='Nefiskalizované doklady'!N2 -> 24403.425 | D31: =B31+C31 -> 24403.425 | F31: Odvody - hotovost | G31: ='Přehled dne'!AE2 -> 0
A32: Základ 12% | B32: ='Fiskalizované doklady'!O2 -> 0 | C32: ='Nefiskalizované doklady'!O2 -> 56035.246 | D32: =B32+C32 -> 56035.246 | F32: Odvody - stravenky | G32: ='Přehled dne'!AF2 -> 0
A33: Základ 0% | B33: ='Fiskalizované doklady'!P2 -> 0 | C33: ='Nefiskalizované doklady'!P2 -> 6 | D33: =B33+C33 -> 6 | F33: Dotace a odvody celkem | G33: =G29+G30+G31+G32 -> 0
A34: Základ celkem | B34: =SUM(B31:B33) -> 0 | C34: =SUM(C31:C33) -> 80444.671 | D34: =B34+C34 -> 80444.671
A35: DPH 21% | B35: ='Fiskalizované doklady'!Q2 -> 0 | C35: ='Nefiskalizované doklady'!Q2 -> 5125.0054 | D35: =B35+C35 -> 5125.0054 | F35: KONEČNÝ STAV K DATU | G35: 46132.836
A36: DPH 12% | B36: ='Fiskalizované doklady'!R2 -> 0 | C36: ='Nefiskalizované doklady'!R2 -> 6725.4739 | D36: =B36+C36 -> 6725.4739 | F36: Hotovost | G36: ='Přehled dne'!AH2 -> #VALUE!
A37: DPH celkem | B37: =SUM(B35:B36) -> 0 | C37: =SUM(C35:C36) -> 11850.479 | D37: =B37+C37 -> 11850.479 | F37: Stravenky | G37: ='Přehled dne'!AI2 -> #VALUE!
A38: kontrolní součet | B38: =B34+B37+B16 -> 0 | C38: =C34+C37+C16 -> 92316.38 | D38: =B38+C38 -> 92316.38 | F38: Konečný stav celkem | G38: =G36+G37 -> #VALUE!
A39: ÚHRADY | F39: kontrolní součet | G39: =G17+G22+G26+G33 -> 38903
A40: Hotovost | B40: ='Fiskalizované doklady'!Z2+'Fiskalizované doklady'!AE2 -> 0 | C40: ='Nefiskalizované doklady'!Z2+'Nefiskalizované doklady'!AE2 -> 38903 | D40: =B40+C40 -> 38903
A41: Stravenky | B41: ='Fiskalizované doklady'!AA2 -> 0 | C41: ='Nefiskalizované doklady'!AA2 -> 0 | D41: =B41+C41 -> 0
A42: Platební karta | B42: ='Fiskalizované doklady'!AB2+'Fiskalizované doklady'!AD2 -> 0 | C42: ='Nefiskalizované doklady'!AB2+'Nefiskalizované doklady'!AD2 -> 53413.38 | D42: =B42+C42 -> 53413.38
A43: Platby celkem | B43: =SUM(B40:B42) -> 0 | C43: =SUM(C40:C42) -> 92316.38 | D43: =B43+C43 -> 92316.38

Sheet Přehled dne
A1: Datum a čas | B1: Akce | C1: Uživatel | D1: DIČ | E1: ID provozovny | F1: ID pokladny | G1: Číslo dokladu | H1: Tržba | L1: Dle sazeb DPH | Q1: Dle věcného rozlišení | X1: Finanční transakce | AG1: Konečný zůstatek pokladny | AK1: Poskytnuté slevy
H2: =SUBTOTAL(109,H4:H999856) -> 92316.38 | I2: =SUBTOTAL(109,I4:I999856) -> 80444.671 | J2: =SUBTOTAL(109,J4:J999856) -> 11850.479 | K2: =SUBTOTAL(109,K4:K999856) -> 21.23 | L2: =SUBTOTAL(109,L4:L999856) -> 24403.425 | M2: =SUBTOTAL(109,M4:M999856) -> 56035.246 | N2: =SUBTOTAL(109,N4:N999856) -> 6 | O2: =SUBTOTAL(109,O4:O999856) -> 5125.0054 | P2: =SUBTOTAL(109,P4:P999856) -> 6725.4739 | Q2: =SUBTOTAL(109,Q4:Q999938) -> 80438.671 | R2: =SUBTOTAL(109,R4:R999938) -> 92289.15 | S2: =SUBTOTAL(109,S4:S999938) -> 0 | T2: =SUBTOTAL(109,T4:T999938) -> 0 | U2: =SUBTOTAL(109,U4:U999938) -> 75 | V2: =SUBTOTAL(109,V4:V999938) -> -69 | W2: =SUBTOTAL(109,W4:W999938) -> 21.23 | X2: =SUBTOTAL(109,X4:X999938) -> 87217 | ... Z2: =SUBTOTAL(109,Z4:Z999938) -> 53413.38 | AB2: =SUBTOTAL(109,AB4:AB999938) -> 0 | AC2: =SUBTOTAL(109,AC4:AC999853) -> 0 | AD2: =SUBTOTAL(109,AD4:AD999853) -> 0 | AE2: =SUBTOTAL(109,AE4:AE999853) -> 0 | AF2: =SUBTOTAL(109,AF4:AF999853) -> 0 | AG2: =IF(SUBTOTAL(104,AG4:AG999853)=0,"Datum není k dispozici",SUBTOTAL(104,AG4:AG999853)) -> 46132.836 | AH2: =IFERROR(VLOOKUP(AG2,AG4:AH999990,2),"0 Kč") -> #VALUE! | AI2: =IFERROR(VLOOKUP(AH2,AH4:AI999990,2),"0 Kč") -> #VALUE! | AJ2: =AH2+AI2 -> #VALUE! | AK2: =SUBTOTAL(109,AK4:AK999853) -> 1083.0861
H3: Tržba celkem | I3: Základ DPH celkem | J3: DPH Celkem | K3: Zaokrouhlení | L3: Základ DPH 21% | M3: Základ DPH 12% | N3: Základ DPH 0% | O3: DPH 21% | P3: DPH 12% | Q3: Prodané zboží bez DPH | R3: Prodané zboží s DPH | S3: Vrácené zboží bez DPH | T3: Vrácené zboží s DPH | U3: Prodané obaly | V3: Vykoupené obaly | W3: Zaokrouhlení | X3: Úhrada hotovost | Y3: Úhrada stravenky | Z3: Platba platební kartou | AA3: Gastro konto | AB3: Cashback | AC3: Dotace hotovost | AD3: Dotace stravenky | AE3: Odvody hotovost | AF3: Odvody stravenky | AG3: K času | AH3: Hotovost | AI3: Stravenky | AJ3: Celkem | AK3: Sleva na pokladně
A4: 46132.015 | B4: Přihlášení | C4: profikasa | D4: CZ60738677 | E4: 96 | F4: Pokladna SCO2 | H4: 0 | I4: ==L4+M4+N4 -> FALSE | J4: ==O4+P4 -> FALSE | K4: ==IF(H4=I4+J4,0,W4) -> FALSE | L4: 0 | M4: 0 | N4: 0 | O4: 0 | P4: 0 | Q4: 0 | R4: 0 | S4: 0 | T4: 0 | U4: 0 | V4: 0 | W4: 0 | Y4: 0 | Z4: 0 | AA4: 0 | AB4: 0 | AC4: 0 | AD4: 0 | AE4: 0 | AF4: 0 | AG4: 46132.015 | AH4: 0 | AI4: 0 | AJ4: ==AH4+AI4 -> FALSE
A5: 46132.015 | B5: Převod | C5: převod z 19.04.2026 | E5: -1 | H5: 0 | I5: =L5+M5+N5 -> 0 | J5: =O5+P5 -> 0 | K5: =IF(H5=I5+J5,0,W5) -> 0 | L5: 0 | M5: 0 | N5: 0 | O5: 0 | P5: 0 | Q5: 0 | R5: 0 | S5: 0 | T5: 0 | U5: 0 | V5: 0 | W5: 0 | X5: 0 | Y5: 0 | Z5: 0 | AA5: 0 | AB5: 0 | AC5: 0 | AD5: 0 | AE5: 0 | AF5: 0 | AG5: 46132.015 | AH5: 0 | AI5: 0 | AJ5: =AH5+AI5 -> 0
A6: 46132.015 | B6: Přihlášení | C6: profikasa | D6: CZ60738677 | E6: 96 | F6: Pokladna SCO1 | H6: 0 | I6: =L6+M6+N6 -> 0 | J6: =O6+P6 -> 0 | K6: =IF(H6=I6+J6,0,W6) -> 0 | L6: 0 | M6: 0 | N6: 0 | O6: 0 | P6: 0 | Q6: 0 | R6: 0 | S6: 0 | T6: 0 | U6: 0 | V6: 0 | W6: 0 | Y6: 0 | Z6: 0 | AA6: 0 | AB6: 0 | AC6: 0 | AD6: 0 | AE6: 0 | AF6: 0 | AG6: 46132.015 | AH6: 0 | AI6: 0 | AJ6: =AH6+AI6 -> 0
A7: 46132.292 | B7: Převod | C7: převod z 19.04.2026 | E7: -1 | H7: 0 | I7: =L7+M7+N7 -> 0 | J7: =O7+P7 -> 0 | K7: =IF(H7=I7+J7,0,W7) -> 0 | L7: 0 | M7: 0 | N7: 0 | O7: 0 | P7: 0 | Q7: 0 | R7: 0 | S7: 0 | T7: 0 | U7: 0 | V7: 0 | W7: 0 | X7: 0 | Y7: 0 | Z7: 0 | AA7: 0 | AB7: 0 | AC7: 0 | AD7: 0 | AE7: 0 | AF7: 0 | AG7: 46132.292 | AH7: 26214 | AI7: 0 | AJ7: =AH7+AI7 -> 26214
A8: 46132.292 | B8: Přihlášení | C8: Teclová | D8: CZ60738677 | E8: 96 | F8: Pokladna 1 | H8: 0 | I8: =L8+M8+N8 -> 0 | J8: =O8+P8 -> 0 | K8: =IF(H8=I8+J8,0,W8) -> 0 | L8: 0 | M8: 0 | N8: 0 | O8: 0 | P8: 0 | Q8: 0 | R8: 0 | S8: 0 | T8: 0 | U8: 0 | V8: 0 | W8: 0 | Y8: 0 | Z8: 0 | AA8: 0 | AB8: 0 | AC8: 0 | AD8: 0 | AE8: 0 | AF8: 0 | AG8: 46132.292 | AH8: 26214 | AI8: 0 | AJ8: =AH8+AI8 -> 26214
A9: 46132.293 | B9: Prodej | C9: Teclová | D9: CZ60738677 | E9: 96 | F9: Pokladna 1 | G9: 166004504 | H9: 69.7 | I9: =L9+M9+N9 -> 59.848 | J9: =O9+P9 -> 9.852 | K9: =IF(H9=I9+J9,0,W9) -> 0 | L9: 29.6694 | M9: 30.1786 | N9: 0 | O9: 6.2306 | P9: 3.6214 | Q9: 59.848 | R9: 69.7 | S9: 0 | T9: 0 | U9: 0 | V9: 0 | W9: 0 | X9: 0 | Y9: 0 | Z9: 69.7 | AA9: 0 | AB9: 0 | AC9: 0 | AD9: 0 | AE9: 0 | AF9: 0 | AG9: 46132.293 | AH9: 26214 | AI9: 0 | AJ9: =AH9+AI9 -> 26214 | AK9: 0
A10: 46132.294 | B10: Prodej | C10: Teclová | D10: CZ60738677 | E10: 96 | F10: Pokladna 1 | G10: 166004505 | H10: 51.4 | I10: =L10+M10+N10 -> 42.4793 | J10: =O10+P10 -> 8.9207 | K10: =IF(H10=I10+J10,0,W10) -> 0 | L10: 42.4793 | M10: 0 | N10: 0 | O10: 8.9207 | P10: 0 | Q10: 42.4793 | R10: 51.4 | S10: 0 | T10: 0 | U10: 0 | V10: 0 | W10: 0 | X10: 0 | Y10: 0 | Z10: 51.4 | AA10: 0 | AB10: 0 | AC10: 0 | AD10: 0 | AE10: 0 | AF10: 0 | AG10: 46132.294 | AH10: 26214 | AI10: 0 | AJ10: =AH10+AI10 -> 26214 | AK10: 0
A11: 46132.295 | B11: Prodej | C11: Teclová | D11: CZ60738677 | E11: 96 | F11: Pokladna 1 | G11: 166004506 | H11: 38 | I11: =L11+M11+N11 -> 31.2396 | J11: =O11+P11 -> 6.5604 | K11: =IF(H11=I11+J11,0,W11) -> 0.2 | L11: 31.2396 | M11: 0 | N11: 0 | O11: 6.5604 | P11: 0 | Q11: 31.2396 | R11: 37.8 | S11: 0 | T11: 0 | U11: 0 | V11: 0 | W11: 0.2 | X11: 50 | Y11: 0 | Z11: 0 | AA11: 0 | AB11: 0 | AC11: 0 | AD11: 0 | AE11: 0 | AF11: 0 | AG11: 46132.295 | AH11: 26252 | AI11: 0 | AJ11: =AH11+AI11 -> 26252 | AK11: 0
A12: 46132.295 | B12: Prodej | C12: Teclová | D12: CZ60738677 | E12: 96 | F12: Pokladna 1 | G12: 166004507 | H12: 70 | I12: =L12+M12+N12 -> 62.8572 | J12: =O12+P12 -> 7.5428 | K12: =IF(H12=I12+J12,0,W12) -> -0.4 | L12: 0 | M12: 62.8572 | N12: 0 | O12: 0 | P12: 7.5428 | Q12: 62.8572 | R12: 70.4 | S12: 0 | T12: 0 | U12: 0 | V12: 0 | W12: -0.4 | X12: 100 | Y12: 0 | Z12: 0 | AA12: 0 | AB12: 0 | AC12: 0 | AD12: 0 | AE12: 0 | AF12: 0 | AG12: 46132.295 | AH12: 26322 | AI12: 0 | AJ12: =AH12+AI12 -> 26322 | AK12: 0
A13: 46132.297 | B13: Prodej | C13: Teclová | D13: CZ60738677 | E13: 96 | F13: Pokladna 1 | G13: 166004508 | H13: 253 | I13: =L13+M13+N13 -> 219.2109 | J13: =O13+P13 -> 33.6391 | K13: =IF(H13=I13+J13,0,W13) -> 0.15 | L13: 81.4875 | M13: 137.7234 | N13: 0 | O13: 17.1125 | P13: 16.5266 | Q13: 219.2109 | R13: 252.85 | S13: 0 | T13: 0 | U13: 0 | V13: 0 | W13: 0.15 | X13: 500 | Y13: 0 | Z13: 0 | AA13: 0 | AB13: 0 | AC13: 0 | AD13: 0 | AE13: 0 | AF13: 0 | AG13: 46132.297 | AH13: 26575 | AI13: 0 | AJ13: =AH13+AI13 -> 26575 | AK13: 0
A14: 46132.298 | B14: Prodej | C14: Teclová | D14: CZ60738677 | E14: 96 | F14: Pokladna 1 | G14: 166004509 | H14: 32 | I14: =L14+M14+N14 -> 26.281 | J14: =O14+P14 -> 5.519 | K14: =IF(H14=I14+J14,0,W14) -> 0.2 | L14: 26.281 | M14: 0 | N14: 0 | O14: 5.519 | P14: 0 | Q14: 26.281 | R14: 31.8 | S14: 0 | T14: 0 | U14: 0 | V14: 0 | W14: 0.2 | X14: 32 | Y14: 0 | Z14: 0 | AA14: 0 | AB14: 0 | AC14: 0 | AD14: 0 | AE14: 0 | AF14: 0 | AG14: 46132.298 | AH14: 26607 | AI14: 0 | AJ14: =AH14+AI14 -> 26607 | AK14: 0
A15: 46132.299 | B15: Prodej | C15: Teclová | D15: CZ60738677 | E15: 96 | F15: Pokladna 1 | G15: 166004510 | H15: 164 | I15: =L15+M15+N15 -> 141.3984 | J15: =O15+P15 -> 22.5316 | K15: =IF(H15=I15+J15,0,W15) -> 0.07 | L15: 61.8182 | M15: 79.5802 | N15: 0 | O15: 12.9818 | P15: 9.5498 | Q15: 141.3984 | R15: 163.93 | S15: 0 | T15: 0 | U15: 0 | V15: 0 | W15: 0.07 | X15: 500 | Y15: 0 | Z15: 0 | AA15: 0 | AB15: 0 | AC15: 0 | AD15: 0 | AE15: 0 | AF15: 0 | AG15: 46132.299 | AH15: 26771 | AI15: 0 | AJ15: =AH15+AI15 -> 26771 | AK15: 0
A16: 46132.3 | B16: Prodej | C16: Teclová | D16: CZ60738677 | E16: 96 | F16: Pokladna 1 | G16: 166004511 | H16: 198.41 | I16: =L16+M16+N16 -> 175.8304 | J16: =O16+P16 -> 22.5796 | K16: =IF(H16=I16+J16,0,W16) -> 0 | L16: 16.4463 | M16: 159.3841 | N16: 0 | O16: 3.4537 | P16: 19.1259 | Q16: 175.8304 | R16: 198.41 | S16: 0 | T16: 0 | U16: 0 | V16: 0 | W16: 0 | X16: 0 | Y16: 0 | Z16: 198.41 | AA16: 0 | AB16: 0 | AC16: 0 | AD16: 0 | AE16: 0 | AF16: 0 | AG16: 46132.3 | AH16: 26771 | AI16: 0 | AJ16: =AH16+AI16 -> 26771 | AK16: 0
A17: 46132.302 | B17: Prodej | C17: Teclová | D17: CZ60738677 | E17: 96 | F17: Pokladna 1 | G17: 166004512 | H17: 200 | I17: =L17+M17+N17 -> 165.2893 | J17: =O17+P17 -> 34.7107 | K17: =IF(H17=I17+J17,0,W17) -> 0 | L17: 165.2893 | M17: 0 | N17: 0 | O17: 34.7107 | P17: 0 | Q17: 165.2893 | R17: 200 | S17: 0 | T17: 0 | U17: 0 | V17: 0 | W17: 0 | X17: 200 | Y17: 0 | Z17: 0 | AA17: 0 | AB17: 0 | AC17: 0 | AD17: 0 | AE17: 0 | AF17: 0 | AG17: 46132.302 | AH17: 26971 | AI17: 0 | AJ17: =AH17+AI17 -> 26971 | AK17: 0
A18: 46132.304 | B18: Prodej | C18: Teclová | D18: CZ60738677 | E18: 96 | F18: Pokladna 1 | G18: 166004513 | H18: 67.42 | I18: =L18+M18+N18 -> 60.1964 | J18: =O18+P18 -> 7.2236 | K18: =IF(H18=I18+J18,0,W18) -> 0 | L18: 0 | M18: 60.1964 | N18: 0 | O18: 0 | P18: 7.2236 | Q18: 60.1964 | R18: 67.42 | S18: 0 | T18: 0 | U18: 0 | V18: 0 | W18: 0 | X18: 0 | Y18: 0 | Z18: 67.42 | AA18: 0 | AB18: 0 | AC18: 0 | AD18: 0 | AE18: 0 | AF18: 0 | AG18: 46132.304 | AH18: 26971 | AI18: 0 | AJ18: =AH18+AI18 -> 26971 | AK18: 0
A19: 46132.304 | B19: Prodej | C19: Teclová | D19: CZ60738677 | E19: 96 | F19: Pokladna 1 | G19: 166004514 | H19: 104 | I19: =L19+M19+N19 -> 88.1936 | J19: =O19+P19 -> 16.2064 | K19: =IF(H19=I19+J19,0,W19) -> -0.4 | L19: 62.4794 | M19: 25.7142 | N19: 0 | O19: 13.1206 | P19: 3.0858 | Q19: 88.1936 | R19: 104.4 | S19: 0 | T19: 0 | U19: 0 | V19: 0 | W19: -0.4 | X19: 150 | Y19: 0 | Z19: 0 | AA19: 0 | AB19: 0 | AC19: 0 | AD19: 0 | AE19: 0 | AF19: 0 | AG19: 46132.304 | AH19: 27075 | AI19: 0 | AJ19: =AH19+AI19 -> 27075 | AK19: 0
A20: 46132.307 | B20: Prodej | C20: Teclová | D20: CZ60738677 | E20: 96 | F20: Pokladna 1 | G20: 166004515 | H20: 209.2 | I20: =L20+M20+N20 -> 186.7857 | J20: =O20+P20 -> 22.4143 | K20: =IF(H20=I20+J20,0,W20) -> 0 | L20: 0 | M20: 186.7857 | N20: 0 | O20: 0 | P20: 22.4143 | Q20: 186.7857 | R20: 209.2 | S20: 0 | T20: 0 | U20: 0 | V20: 0 | W20: 0 | X20: 0 | Y20: 0 | Z20: 209.2 | AA20: 0 | AB20: 0 | AC20: 0 | AD20: 0 | AE20: 0 | AF20: 0 | AG20: 46132.307 | AH20: 27075 | AI20: 0 | AJ20: =AH20+AI20 -> 27075 | AK20: 0
... A187: 46132.464 | B187: Prodej | C187: Teclová | D187: CZ60738677 | E187: 96 | F187: Pokladna 1 | G187: 166004664 | H187: 222 | I187: =L187+M187+N187 -> 195.484 | J187: =O187+P187 -> 27.006 | K187: =IF(H187=I187+J187,0,W187) -> -0.49 | L187: 39.4215 | M187: 156.0625 | N187: 0 | O187: 8.2785 | P187: 18.7275 | Q187: 195.484 | R187: 222.49 | S187: 0 | T187: 0 | U187: 0 | V187: 0 | W187: -0.49 | X187: 502 | Y187: 0 | Z187: 0 | AA187: 0 | AB187: 0 | AC187: 0 | AD187: 0 | AE187: 0 | AF187: 0 | AG187: 46132.464 | AH187: 38130 | AI187: 0 | AJ187: =AH187+AI187 -> 38130 | AK187: 0
A188: 46132.465 | B188: Převod | C188: převod z 19.04.2026 | E188: -1 | H188: 0 | I188: =L188+M188+N188 -> 0 | J188: =O188+P188 -> 0 | K188: =IF(H188=I188+J188,0,W188) -> 0 | L188: 0 | M188: 0 | N188: 0 | O188: 0 | P188: 0 | Q188: 0 | R188: 0 | S188: 0 | T188: 0 | U188: 0 | V188: 0 | W188: 0 | X188: 0 | Y188: 0 | Z188: 0 | AA188: 0 | AB188: 0 | AC188: 0 | AD188: 0 | AE188: 0 | AF188: 0 | AG188: 46132.465 | AH188: 23360 | AI188: 0 | AJ188: =AH188+AI188 -> 23360
A189: 46132.465 | B189: Přihlášení | C189: profikasa | D189: CZ60738677 | E189: 96 | F189: Pokladna 2 | H189: 0 | I189: =L189+M189+N189 -> 0 | J189: =O189+P189 -> 0 | K189: =IF(H189=I189+J189,0,W189) -> 0 | L189: 0 | M189: 0 | N189: 0 | O189: 0 | P189: 0 | Q189: 0 | R189: 0 | S189: 0 | T189: 0 | U189: 0 | V189: 0 | W189: 0 | Y189: 0 | Z189: 0 | AA189: 0 | AB189: 0 | AC189: 0 | AD189: 0 | AE189: 0 | AF189: 0 | AG189: 46132.465 | AH189: 23360 | AI189: 0 | AJ189: =AH189+AI189 -> 23360
A190: 46132.466 | B190: Odhášení | C190: profikasa | D190: CZ60738677 | E190: 96 | F190: Pokladna 2 | H190: 0 | I190: =L190+M190+N190 -> 0 | J190: =O190+P190 -> 0 | K190: =IF(H190=I190+J190,0,W190) -> 0 | L190: 0 | M190: 0 | N190: 0 | O190: 0 | P190: 0 | Q190: 0 | R190: 0 | S190: 0 | T190: 0 | U190: 0 | V190: 0 | W190: 0 | Y190: 0 | Z190: 0 | AA190: 0 | AB190: 0 | AC190: 0 | AD190: 0 | AE190: 0 | AF190: 0 | AG190: 46132.466 | AH190: 23360 | AI190: 0 | AJ190: =AH190+AI190 -> 23360
A191: 46132.466 | B191: Přihlášení | C191: profikasa | D191: CZ60738677 | E191: 96 | F191: Pokladna 1 | H191: 0 | I191: =L191+M191+N191 -> 0 | J191: =O191+P191 -> 0 | K191: =IF(H191=I191+J191,0,W191) -> 0 | L191: 0 | M191: 0 | N191: 0 | O191: 0 | P191: 0 | Q191: 0 | R191: 0 | S191: 0 | T191: 0 | U191: 0 | V191: 0 | W191: 0 | Y191: 0 | Z191: 0 | AA191: 0 | AB191: 0 | AC191: 0 | AD191: 0 | AE191: 0 | AF191: 0 | AG191: 46132.466 | AH191: 38130 | AI191: 0 | AJ191: =AH191+AI191 -> 38130
A192: 46132.466 | B192: Odhášení | C192: profikasa | D192: CZ60738677 | E192: 96 | F192: Pokladna 1 | H192: 0 | I192: =L192+M192+N192 -> 0 | J192: =O192+P192 -> 0 | K192: =IF(H192=I192+J192,0,W192) -> 0 | L192: 0 | M192: 0 | N192: 0 | O192: 0 | P192: 0 | Q192: 0 | R192: 0 | S192: 0 | T192: 0 | U192: 0 | V192: 0 | W192: 0 | Y192: 0 | Z192: 0 | AA192: 0 | AB192: 0 | AC192: 0 | AD192: 0 | AE192: 0 | AF192: 0 | AG192: 46132.466 | AH192: 38130 | AI192: 0 | AJ192: =AH192+AI192 -> 38130
A193: 46132.466 | B193: Přihlášení | C193: Teclová | D193: CZ60738677 | E193: 96 | F193: Pokladna 1 | H193: 0 | I193: =L193+M193+N193 -> 0 | J193: =O193+P193 -> 0 | K193: =IF(H193=I193+J193,0,W193) -> 0 | L193: 0 | M193: 0 | N193: 0 | O193: 0 | P193: 0 | Q193: 0 | R193: 0 | S193: 0 | T193: 0 | U193: 0 | V193: 0 | W193: 0 | Y193: 0 | Z193: 0 | AA193: 0 | AB193: 0 | AC193: 0 | AD193: 0 | AE193: 0 | AF193: 0 | AG193: 46132.466 | AH193: 38130 | AI193: 0 | AJ193: =AH193+AI193 -> 38130
A194: 46132.467 | B194: Prodej | C194: Teclová | D194: CZ60738677 | E194: 96 | F194: Pokladna 1 | G194: 166004665 | H194: 51 | I194: =L194+M194+N194 -> 45.3392 | J194: =O194+P194 -> 5.4408 | K194: =IF(H194=I194+J194,0,W194) -> 0.22 | L194: 0 | M194: 45.3392 | N194: 0 | O194: 0 | P194: 5.4408 | Q194: 45.3392 | R194: 50.78 | S194: 0 | T194: 0 | U194: 0 | V194: 0 | W194: 0.22 | X194: 51 | Y194: 0 | Z194: 0 | AA194: 0 | AB194: 0 | AC194: 0 | AD194: 0 | AE194: 0 | AF194: 0 | AG194: 46132.467 | AH194: 38181 | AI194: 0 | AJ194: =AH194+AI194 -> 38181 | AK194: 0
A195: 46132.468 | B195: Prodej | C195: Teclová | D195: CZ60738677 | E195: 96 | F195: Pokladna 1 | G195: 166004666 | H195: 50 | I195: =L195+M195+N195 -> 41.2397 | J195: =O195+P195 -> 8.6603 | K195: =IF(H195=I195+J195,0,W195) -> 0.1 | L195: 41.2397 | M195: 0 | N195: 0 | O195: 8.6603 | P195: 0 | Q195: 41.2397 | R195: 49.9 | S195: 0 | T195: 0 | U195: 0 | V195: 0 | W195: 0.1 | X195: 50 | Y195: 0 | Z195: 0 | AA195: 0 | AB195: 0 | AC195: 0 | AD195: 0 | AE195: 0 | AF195: 0 | AG195: 46132.468 | AH195: 38231 | AI195: 0 | AJ195: =AH195+AI195 -> 38231 | AK195: 0
A196: 46132.469 | B196: Prodej | C196: Teclová | D196: CZ60738677 | E196: 96 | F196: Pokladna 1 | G196: 166004667 | H196: 653 | I196: =L196+M196+N196 -> 561.4099 | J196: =O196+P196 -> 91.8401 | K196: =IF(H196=I196+J196,0,W196) -> -0.25 | L196: 271.9008 | M196: 289.5091 | N196: 0 | O196: 57.0992 | P196: 34.7409 | Q196: 561.4099 | R196: 653.25 | S196: 0 | T196: 0 | U196: 0 | V196: 0 | W196: -0.25 | X196: 1000 | Y196: 0 | Z196: 0 | AA196: 0 | AB196: 0 | AC196: 0 | AD196: 0 | AE196: 0 | AF196: 0 | AG196: 46132.469 | AH196: 38884 | AI196: 0 | AJ196: =AH196+AI196 -> 38884 | AK196: 10.4805
A197: 46132.469 | B197: Prodej | C197: Teclová | D197: CZ60738677 | E197: 96 | F197: Pokladna 1 | G197: 166004668 | H197: 15 | I197: =L197+M197+N197 -> 12.314 | J197: =O197+P197 -> 2.586 | K197: =IF(H197=I197+J197,0,W197) -> 0.1 | L197: 12.314 | M197: 0 | N197: 0 | O197: 2.586 | P197: 0 | Q197: 12.314 | R197: 14.9 | S197: 0 | T197: 0 | U197: 0 | V197: 0 | W197: 0.1 | X197: 20 | Y197: 0 | Z197: 0 | AA197: 0 | AB197: 0 | AC197: 0 | AD197: 0 | AE197: 0 | AF197: 0 | AG197: 46132.469 | AH197: 38899 | AI197: 0 | AJ197: =AH197+AI197 -> 38899 | AK197: 0
A198: 46132.47 | B198: Prodej | C198: Teclová | D198: CZ60738677 | E198: 96 | F198: Pokladna 1 | G198: 166004669 | H198: 148.6 | I198: =L198+M198+N198 -> 131.0249 | J198: =O198+P198 -> 17.5751 | K198: =IF(H198=I198+J198,0,W198) -> 0 | L198: 20.5785 | M198: 110.4464 | N198: 0 | O198: 4.3215 | P198: 13.2536 | Q198: 131.0249 | R198: 148.6 | S198: 0 | T198: 0 | U198: 0 | V198: 0 | W198: 0 | X198: 0 | Y198: 0 | Z198: 148.6 | AA198: 0 | AB198: 0 | AC198: 0 | AD198: 0 | AE198: 0 | AF198: 0 | AG198: 46132.47 | AH198: 38899 | AI198: 0 | AJ198: =AH198+AI198 -> 38899 | AK198: 0
A199: 46132.47 | B199: Prodej | C199: Teclová | D199: CZ60738677 | E199: 96 | F199: Pokladna 1 | G199: 166004670 | H199: 481 | I199: =L199+M199+N199 -> 415.4146 | J199: =O199+P199 -> 65.6854 | K199: =IF(H199=I199+J199,0,W199) -> -0.1 | L199: 175.9504 | M199: 239.4642 | N199: 0 | O199: 36.9496 | P199: 28.7358 | Q199: 415.4146 | R199: 481.1 | S199: 0 | T199: 0 | U199: 0 | V199: 0 | W199: -0.1 | X199: 2000 | Y199: 0 | Z199: 0 | AA199: 0 | AB199: 0 | AC199: 0 | AD199: 0 | AE199: 0 | AF199: 0 | AG199: 46132.47 | AH199: 39380 | AI199: 0 | AJ199: =AH199+AI199 -> 39380 | AK199: 0
A200: 46132.471 | B200: Prodej | C200: Teclová | D200: CZ60738677 | E200: 96 | F200: Pokladna 1 | G200: 166004671 | H200: 94 | I200: =L200+M200+N200 -> 83.5714 | J200: =O200+P200 -> 10.0286 | K200: =IF(H200=I200+J200,0,W200) -> 0.4 | L200: 0 | M200: 83.5714 | N200: 0 | O200: 0 | P200: 10.0286 | Q200: 83.5714 | R200: 93.6 | S200: 0 | T200: 0 | U200: 0 | V200: 0 | W200: 0.4 | X200: 94 | Y200: 0 | Z200: 0 | AA200: 0 | AB200: 0 | AC200: 0 | AD200: 0 | AE200: 0 | AF200: 0 | AG200: 46132.471 | AH200: 39474 | AI200: 0 | AJ200: =AH200+AI200 -> 39474 | AK200: 0
A201: 46132.471 | B201: Prodej | C201: Teclová | D201: CZ60738677 | E201: 96 | F201: Pokladna 1 | G201: 166004672 | H201: 123 | I201: =L201+M201+N201 -> 109.5536 | J201: =O201+P201 -> 13.1464 | K201: =IF(H201=I201+J201,0,W201) -> 0.3 | L201: 0 | M201: 109.5536 | N201: 0 | O201: 0 | P201: 13.1464 | Q201: 109.5536 | R201: 122.7 | S201: 0 | T201: 0 | U201: 0 | V201: 0 | W201: 0.3 | X201: 200 | Y201: 0 | Z201: 0 | AA201: 0 | AB201: 0 | AC201: 0 | AD201: 0 | AE201: 0 | AF201: 0 | AG201: 46132.471 | AH201: 39597 | AI201: 0 | AJ201: =AH201+AI201 -> 39597 | AK201: 0
A202: 46132.471 | B202: Prodej | C202: Teclová | D202: CZ60738677 | E202: 96 | F202: Pokladna 1 | G202: 166004673 | H202: 30 | I202: =L202+M202+N202 -> 26.9274 | J202: =O202+P202 -> 3.3726 | K202: =IF(H202=I202+J202,0,W202) -> -0.3 | L202: 1.5702 | M202: 25.3572 | N202: 0 | O202: 0.3298 | P202: 3.0428 | Q202: 26.9274 | R202: 30.3 | S202: 0 | T202: 0 | U202: 0 | V202: 0 | W202: -0.3 | X202: 30 | Y202: 0 | Z202: 0 | AA202: 0 | AB202: 0 | AC202: 0 | AD202: 0 | AE202: 0 | AF202: 0 | AG202: 46132.471 | AH202: 39627 | AI202: 0 | AJ202: =AH202+AI202 -> 39627 | AK202: 0
A203: 46132.472 | B203: Prodej | C203: Teclová | D203: CZ60738677 | E203: 96 | F203: Pokladna 1 | G203: 166004674 | H203: 5.77 | I203: =L203+M203+N203 -> 5.1518 | J203: =O203+P203 -> 0.6182 | K203: =IF(H203=I203+J203,0,W203) -> 0 | L203: 0 | M203: 5.1518 | N203: 0 | O203: 0 | P203: 0.6182 | Q203: 5.1518 | R203: 5.77 | S203: 0 | T203: 0 | U203: 0 | V203: 0 | W203: 0 | X203: 0 | Y203: 0 | Z203: 5.77 | AA203: 0 | AB203: 0 | AC203: 0 | AD203: 0 | AE203: 0 | AF203: 0 | AG203: 46132.472 | AH203: 39627 | AI203: 0 | AJ203: =AH203+AI203 -> 39627 | AK203: 0
A204: 46132.472 | B204: Prodej | C204: Teclová | D204: CZ60738677 | E204: 96 | F204: Pokladna 1 | G204: 166004675 | H204: 15.9 | I204: =L204+M204+N204 -> 14.1964 | J204: =O204+P204 -> 1.7036 | K204: =IF(H204=I204+J204,0,W204) -> 0 | L204: 0 | M204: 14.1964 | N204: 0 | O204: 0 | P204: 1.7036 | Q204: 14.1964 | R204: 15.9 | S204: 0 | T204: 0 | U204: 0 | V204: 0 | W204: 0 | X204: 0 | Y204: 0 | Z204: 15.9 | AA204: 0 | AB204: 0 | AC204: 0 | AD204: 0 | AE204: 0 | AF204: 0 | AG204: 46132.472 | AH204: 39627 | AI204: 0 | AJ204: =AH204+AI204 -> 39627 | AK204: 0
A205: 46132.474 | B205: Prodej | C205: Teclová | D205: CZ60738677 | E205: 96 | F205: Pokladna 1 | G205: 166004676 | H205: 137 | I205: =L205+M205+N205 -> 117.6446 | J205: =O205+P205 -> 19.7554 | K205: =IF(H205=I205+J205,0,W205) -> -0.4 | L205: 62.6446 | M205: 55 | N205: 0 | O205: 13.1554 | P205: 6.6 | Q205: 117.6446 | R205: 137.4 | S205: 0 | T205: 0 | U205: 0 | V205: 0 | W205: -0.4 | X205: 237 | Y205: 0 | Z205: 0 | AA205: 0 | AB205: 0 | AC205: 0 | AD205: 0 | AE205: 0 | AF205: 0 | AG205: 46132.474 | AH205: 39764 | AI205: 0 | AJ205: =AH205+AI205 -> 39764 | AK205: 0
... A231: 46132.498 | B231: Prodej | C231: Teclová | D231: CZ60738677 | E231: 96 | F231: Pokladna 1 | G231: 166004701 | H231: 19.9 | I231: =L231+M231+N231 -> 17.7679 | J231: =O231+P231 -> 2.1321 | K231: =IF(H231=I231+J231,0,W231) -> 0 | L231: 0 | M231: 17.7679 | N231: 0 | O231: 0 | P231: 2.1321 | Q231: 17.7679 | R231: 19.9 | S231: 0 | T231: 0 | U231: 0 | V231: 0 | W231: 0 | X231: 0 | Y231: 0 | Z231: 19.9 | AA231: 0 | AB231: 0 | AC231: 0 | AD231: 0 | AE231: 0 | AF231: 0 | AG231: 46132.498 | AH231: 41177 | AI231: 0 | AJ231: =AH231+AI231 -> 41177 | AK231: 0
A232: 46132.498 | B232: Přihlášení | C232: Šímová | D232: CZ60738677 | E232: 96 | F232: Pokladna 2 | H232: 0 | I232: =L232+M232+N232 -> 0 | J232: =O232+P232 -> 0 | K232: =IF(H232=I232+J232,0,W232) -> 0 | L232: 0 | M232: 0 | N232: 0 | O232: 0 | P232: 0 | Q232: 0 | R232: 0 | S232: 0 | T232: 0 | U232: 0 | V232: 0 | W232: 0 | Y232: 0 | Z232: 0 | AA232: 0 | AB232: 0 | AC232: 0 | AD232: 0 | AE232: 0 | AF232: 0 | AG232: 46132.498 | AH232: 23360 | AI232: 0 | AJ232: =AH232+AI232 -> 23360
A233: 46132.499 | B233: Prodej | C233: Teclová | D233: CZ60738677 | E233: 96 | F233: Pokladna 1 | G233: 166004702 | H233: 639.82 | I233: =L233+M233+N233 -> 571.0155 | J233: =O233+P233 -> 68.8045 | K233: =IF(H233=I233+J233,0,W233) -> 0 | L233: 3.1404 | M233: 567.8751 | N233: 0 | O233: 0.6596 | P233: 68.1449 | Q233: 571.0155 | R233: 639.82 | S233: 0 | T233: 0 | U233: 0 | V233: 0 | W233: 0 | X233: 0 | Y233: 0 | Z233: 639.82 | AA233: 0 | AB233: 0 | AC233: 0 | AD233: 0 | AE233: 0 | AF233: 0 | AG233: 46132.499 | AH233: 41177 | AI233: 0 | AJ233: =AH233+AI233 -> 41177 | AK233: 142.08
A234: 46132.499 | B234: Prodej | C234: Teclová | D234: CZ60738677 | E234: 96 | F234: Pokladna 1 | G234: 166004703 | H234: 91 | I234: =L234+M234+N234 -> 80.8036 | J234: =O234+P234 -> 9.6964 | K234: =IF(H234=I234+J234,0,W234) -> 0.5 | L234: 0 | M234: 80.8036 | N234: 0 | O234: 0 | P234: 9.6964 | Q234: 80.8036 | R234: 90.5 | S234: 0 | T234: 0 | U234: 0 | V234: 0 | W234: 0.5 | X234: 91 | Y234: 0 | Z234: 0 | AA234: 0 | AB234: 0 | AC234: 0 | AD234: 0 | AE234: 0 | AF234: 0 | AG234: 46132.499 | AH234: 41268 | AI234: 0 | AJ234: =AH234+AI234 -> 41268 | AK234: 0
A235: 46132.499 | B235: Prodej | C235: Šímová | D235: CZ60738677 | E235: 96 | F235: Pokladna 2 | G235: 169002596 | H235: 227.1 | I235: =L235+M235+N235 -> 200.9151 | J235: =O235+P235 -> 26.1849 | K235: =IF(H235=I235+J235,0,W235) -> 0 | L235: 23.0579 | M235: 177.8572 | N235: 0 | O235: 4.8421 | P235: 21.3428 | Q235: 200.9151 | R235: 227.1 | S235: 0 | T235: 0 | U235: 0 | V235: 0 | W235: 0 | X235: 0 | Y235: 0 | Z235: 227.1 | AA235: 0 | AB235: 0 | AC235: 0 | AD235: 0 | AE235: 0 | AF235: 0 | AG235: 46132.499 | AH235: 23360 | AI235: 0 | AJ235: =AH235+AI235 -> 23360 | AK235: 0
A236: 46132.499 | B236: Prodej | C236: Šímová | D236: CZ60738677 | E236: 96 | F236: Pokladna 2 | G236: 169002597 | H236: 42.9 | I236: =L236+M236+N236 -> 38.3036 | J236: =O236+P236 -> 4.5964 | K236: =IF(H236=I236+J236,0,W236) -> 0 | L236: 0 | M236: 38.3036 | N236: 0 | O236: 0 | P236: 4.5964 | Q236: 38.3036 | R236: 42.9 | S236: 0 | T236: 0 | U236: 0 | V236: 0 | W236: 0 | X236: 0 | Y236: 0 | Z236: 42.9 | AA236: 0 | AB236: 0 | AC236: 0 | AD236: 0 | AE236: 0 | AF236: 0 | AG236: 46132.499 | AH236: 23360 | AI236: 0 | AJ236: =AH236+AI236 -> 23360 | AK236: 0
A237: 46132.5 | B237: Prodej | C237: profikasa | D237: CZ60738677 | E237: 96 | F237: Pokladna SCO1 | G237: 161000347 | H237: 67.8 | I237: =L237+M237+N237 -> 60.53 | J237: =O237+P237 -> 7.27 | K237: =IF(H237=I237+J237,0,W237) -> 0 | L237: 0 | M237: 60.53 | N237: 0 | O237: 0 | P237: 7.27 | Q237: 60.53 | R237: 67.8 | S237: 0 | T237: 0 | U237: 0 | V237: 0 | W237: 0 | X237: 0 | Y237: 0 | Z237: 67.8 | AA237: 0 | AB237: 0 | AC237: 0 | AD237: 0 | AE237: 0 | AF237: 0 | AG237: 46132.5 | AH237: 0 | AI237: 0 | AJ237: =AH237+AI237 -> 0 | AK237: 0
A238: 46132.5 | B238: Prodej | C238: Šímová | D238: CZ60738677 | E238: 96 | F238: Pokladna 2 | G238: 169002598 | H238: 250 | I238: =L238+M238+N238 -> 223.5714 | J238: =O238+P238 -> 26.8286 | K238: =IF(H238=I238+J238,0,W238) -> -0.4 | L238: 0 | M238: 223.5714 | N238: 0 | O238: 0 | P238: 26.8286 | Q238: 223.5714 | R238: 250.4 | S238: 0 | T238: 0 | U238: 0 | V238: 0 | W238: -0.4 | X238: 500 | Y238: 0 | Z238: 0 | AA238: 0 | AB238: 0 | AC238: 0 | AD238: 0 | AE238: 0 | AF238: 0 | AG238: 46132.5 | AH238: 23610 | AI238: 0 | AJ238: =AH238+AI238 -> 23610 | AK238: 0
A239: 46132.5 | B239: Prodej | C239: Teclová | D239: CZ60738677 | E239: 96 | F239: Pokladna 1 | G239: 166004704 | H239: 101.83 | I239: =L239+M239+N239 -> 90.9197 | J239: =O239+P239 -> 10.9103 | K239: =IF(H239=I239+J239,0,W239) -> 0 | L239: 0 | M239: 90.9197 | N239: 0 | O239: 0 | P239: 10.9103 | Q239: 90.9197 | R239: 101.83 | S239: 0 | T239: 0 | U239: 0 | V239: 0 | W239: 0 | X239: 0 | Y239: 0 | Z239: 101.83 | AA239: 0 | AB239: 0 | AC239: 0 | AD239: 0 | AE239: 0 | AF239: 0 | AG239: 46132.5 | AH239: 41268 | AI239: 0 | AJ239: =AH239+AI239 -> 41268 | AK239: 0
A240: 46132.501 | B240: Prodej | C240: Šímová | D240: CZ60738677 | E240: 96 | F240: Pokladna 2 | G240: 169002599 | H240: 158.4 | I240: =L240+M240+N240 -> 141.4286 | J240: =O240+P240 -> 16.9714 | K240: =IF(H240=I240+J240,0,W240) -> 0 | L240: 0 | M240: 141.4286 | N240: 0 | O240: 0 | P240: 16.9714 | Q240: 141.4286 | R240: 158.4 | S240: 0 | T240: 0 | U240: 0 | V240: 0 | W240: 0 | X240: 0 | Y240: 0 | Z240: 158.4 | AA240: 0 | AB240: 0 | AC240: 0 | AD240: 0 | AE240: 0 | AF240: 0 | AG240: 46132.501 | AH240: 23610 | AI240: 0 | AJ240: =AH240+AI240 -> 23610 | AK240: 0
A241: 46132.501 | B241: Prodej | C241: Teclová | D241: CZ60738677 | E241: 96 | F241: Pokladna 1 | G241: 166004705 | H241: 108.71 | I241: =L241+M241+N241 -> 97.0625 | J241: =O241+P241 -> 11.6475 | K241: =IF(H241=I241+J241,0,W241) -> 0 | L241: 0 | M241: 97.0625 | N241: 0 | O241: 0 | P241: 11.6475 | Q241: 97.0625 | R241: 108.71 | S241: 0 | T241: 0 | U241: 0 | V241: 0 | W241: 0 | X241: 0 | Y241: 0 | Z241: 108.71 | AA241: 0 | AB241: 0 | AC241: 0 | AD241: 0 | AE241: 0 | AF241: 0 | AG241: 46132.501 | AH241: 41268 | AI241: 0 | AJ241: =AH241+AI241 -> 41268 | AK241: 0
A242: 46132.502 | B242: Prodej | C242: profikasa | D242: CZ60738677 | E242: 96 | F242: Pokladna SCO1 | G242: 161000348 | H242: 43.8 | I242: =L242+M242+N242 -> 36.18 | J242: =O242+P242 -> 7.62 | K242: =IF(H242=I242+J242,0,W242) -> 0 | L242: 36.18 | M242: 0 | N242: 0 | O242: 7.62 | P242: 0 | Q242: 36.18 | R242: 43.8 | S242: 0 | T242: 0 | U242: 0 | V242: 0 | W242: 0 | X242: 0 | Y242: 0 | Z242: 43.8 | AA242: 0 | AB242: 0 | AC242: 0 | AD242: 0 | AE242: 0 | AF242: 0 | AG242: 46132.502 | AH242: 0 | AI242: 0 | AJ242: =AH242+AI242 -> 0 | AK242: 0
A243: 46132.503 | B243: Prodej | C243: Teclová | D243: CZ60738677 | E243: 96 | F243: Pokladna 1 | G243: 166004706 | H243: 34.8 | I243: =L243+M243+N243 -> 29.7499 | J243: =O243+P243 -> 5.0501 | K243: =IF(H243=I243+J243,0,W243) -> 0 | L243: 16.4463 | M243: 13.3036 | N243: 0 | O243: 3.4537 | P243: 1.5964 | Q243: 29.7499 | R243: 34.8 | S243: 0 | T243: 0 | U243: 0 | V243: 0 | W243: 0 | X243: 0 | Y243: 0 | Z243: 34.8 | AA243: 0 | AB243: 0 | AC243: 0 | AD243: 0 | AE243: 0 | AF243: 0 | AG243: 46132.503 | AH243: 41268 | AI243: 0 | AJ243: =AH243+AI243 -> 41268 | AK243: 0
A244: 46132.503 | B244: Prodej | C244: Teclová | D244: CZ60738677 | E244: 96 | F244: Pokladna 1 | G244: 166004707 | H244: 17 | I244: =L244+M244+N244 -> 15.0893 | J244: =O244+P244 -> 1.8107 | K244: =IF(H244=I244+J244,0,W244) -> 0.1 | L244: 0 | M244: 15.0893 | N244: 0 | O244: 0 | P244: 1.8107 | Q244: 15.0893 | R244: 16.9 | S244: 0 | T244: 0 | U244: 0 | V244: 0 | W244: 0.1 | X244: 17 | Y244: 0 | Z244: 0 | AA244: 0 | AB244: 0 | AC244: 0 | AD244: 0 | AE244: 0 | AF244: 0 | AG244: 46132.503 | AH244: 41285 | AI244: 0 | AJ244: =AH244+AI244 -> 41285 | AK244: 0
... A253: 46132.512 | B253: Prodej | C253: profikasa | D253: CZ60738677 | E253: 96 | F253: Pokladna SCO1 | G253: 161000349 | H253: 42.8 | I253: =L253+M253+N253 -> 36.35 | J253: =O253+P253 -> 6.45 | K253: =IF(H253=I253+J253,0,W253) -> 0 | L253: 23.05 | M253: 13.3 | N253: 0 | O253: 4.85 | P253: 1.6 | Q253: 36.35 | R253: 42.8 | S253: 0 | T253: 0 | U253: 0 | V253: 0 | W253: 0 | X253: 0 | Y253: 0 | Z253: 42.8 | AA253: 0 | AB253: 0 | AC253: 0 | AD253: 0 | AE253: 0 | AF253: 0 | AG253: 46132.512 | AH253: 0 | AI253: 0 | AJ253: =AH253+AI253 -> 0 | AK253: 0
A254: 46132.514 | B254: Přihlášení | C254: Šímová | D254: CZ60738677 | E254: 96 | F254: Pokladna 2 | H254: 0 | I254: =L254+M254+N254 -> 0 | J254: =O254+P254 -> 0 | K254: =IF(H254=I254+J254,0,W254) -> 0 | L254: 0 | M254: 0 | N254: 0 | O254: 0 | P254: 0 | Q254: 0 | R254: 0 | S254: 0 | T254: 0 | U254: 0 | V254: 0 | W254: 0 | Y254: 0 | Z254: 0 | AA254: 0 | AB254: 0 | AC254: 0 | AD254: 0 | AE254: 0 | AF254: 0 | AG254: 46132.514 | AH254: 23912 | AI254: 0 | AJ254: =AH254+AI254 -> 23912
A255: 46132.514 | B255: Prodej | C255: Šímová | D255: CZ60738677 | E255: 96 | F255: Pokladna 2 | G255: 169002604 | H255: 23 | I255: =L255+M255+N255 -> 20.6696 | J255: =O255+P255 -> 2.4804 | K255: =IF(H255=I255+J255,0,W255) -> -0.15 | L255: 0 | M255: 20.6696 | N255: 0 | O255: 0 | P255: 2.4804 | Q255: 20.6696 | R255: 23.15 | S255: 0 | T255: 0 | U255: 0 | V255: 0 | W255: -0.15 | X255: 25 | Y255: 0 | Z255: 0 | AA255: 0 | AB255: 0 | AC255: 0 | AD255: 0 | AE255: 0 | AF255: 0 | AG255: 46132.514 | AH255: 23935 | AI255: 0 | AJ255: =AH255+AI255 -> 23935 | AK255: 0
A256: 46132.514 | B256: Prodej | C256: Šímová | D256: CZ60738677 | E256: 96 | F256: Pokladna 2 | G256: 169002605 | H256: 54 | I256: =L256+M256+N256 -> 46.4485 | J256: =O256+P256 -> 7.3515 | K256: =IF(H256=I256+J256,0,W256) -> 0.2 | L256: 19.7521 | M256: 26.6964 | N256: 0 | O256: 4.1479 | P256: 3.2036 | Q256: 46.4485 | R256: 53.8 | S256: 0 | T256: 0 | U256: 0 | V256: 0 | W256: 0.2 | X256: 100 | Y256: 0 | Z256: 0 | AA256: 0 | AB256: 0 | AC256: 0 | AD256: 0 | AE256: 0 | AF256: 0 | AG256: 46132.514 | AH256: 23989 | AI256: 0 | AJ256: =AH256+AI256 -> 23989 | AK256: 0
A257: 46132.515 | B257: Prodej | C257: Šímová | D257: CZ60738677 | E257: 96 | F257: Pokladna 2 | G257: 169002606 | H257: 10 | I257: =L257+M257+N257 -> 8.8393 | J257: =O257+P257 -> 1.0607 | K257: =IF(H257=I257+J257,0,W257) -> 0.1 | L257: 0 | M257: 8.8393 | N257: 0 | O257: 0 | P257: 1.0607 | Q257: 8.8393 | R257: 9.9 | S257: 0 | T257: 0 | U257: 0 | V257: 0 | W257: 0.1 | X257: 10 | Y257: 0 | Z257: 0 | AA257: 0 | AB257: 0 | AC257: 0 | AD257: 0 | AE257: 0 | AF257: 0 | AG257: 46132.515 | AH257: 23999 | AI257: 0 | AJ257: =AH257+AI257 -> 23999 | AK257: 0
A258: 46132.515 | B258: Prodej | C258: Šímová | D258: CZ60738677 | E258: 96 | F258: Pokladna 2 | G258: 169002607 | H258: 36 | I258: =L258+M258+N258 -> 32.2946 | J258: =O258+P258 -> 3.8754 | K258: =IF(H258=I258+J258,0,W258) -> -0.17 | L258: 0 | M258: 32.2946 | N258: 0 | O258: 0 | P258: 3.8754 | Q258: 32.2946 | R258: 36.17 | S258: 0 | T258: 0 | U258: 0 | V258: 0 | W258: -0.17 | X258: 36 | Y258: 0 | Z258: 0 | AA258: 0 | AB258: 0 | AC258: 0 | AD258: 0 | AE258: 0 | AF258: 0 | AG258: 46132.515 | AH258: 24035 | AI258: 0 | AJ258: =AH258+AI258 -> 24035 | AK258: 6.8002
A259: 46132.516 | B259: Prodej | C259: Šímová | D259: CZ60738677 | E259: 96 | F259: Pokladna 2 | G259: 169002608 | H259: 70 | I259: =L259+M259+N259 -> 62.2322 | J259: =O259+P259 -> 7.4678 | K259: =IF(H259=I259+J259,0,W259) -> 0.3 | L259: 0 | M259: 62.2322 | N259: 0 | O259: 0 | P259: 7.4678 | Q259: 62.2322 | R259: 69.7 | S259: 0 | T259: 0 | U259: 0 | V259: 0 | W259: 0.3 | X259: 70 | Y259: 0 | Z259: 0 | AA259: 0 | AB259: 0 | AC259: 0 | AD259: 0 | AE259: 0 | AF259: 0 | AG259: 46132.516 | AH259: 24105 | AI259: 0 | AJ259: =AH259+AI259 -> 24105 | AK259: 0
A260: 46132.517 | B260: Prodej | C260: Šímová | D260: CZ60738677 | E260: 96 | F260: Pokladna 2 | G260: 169002609 | H260: 391.3 | I260: =L260+M260+N260 -> 349.249 | J260: =O260+P260 -> 42.051 | K260: =IF(H260=I260+J260,0,W260) -> 0 | L260: 1.5702 | M260: 347.6788 | N260: 0 | O260: 0.3298 | P260: 41.7212 | Q260: 349.249 | R260: 391.3 | S260: 0 | T260: 0 | U260: 0 | V260: 0 | W260: 0 | X260: 0 | Y260: 0 | Z260: 391.3 | AA260: 0 | AB260: 0 | AC260: 0 | AD260: 0 | AE260: 0 | AF260: 0 | AG260: 46132.517 | AH260: 24105 | AI260: 0 | AJ260: =AH260+AI260 -> 24105 | AK260: 0
A261: 46132.518 | B261: Prodej | C261: Šímová | D261: CZ60738677 | E261: 96 | F261: Pokladna 2 | G261: 169002610 | H261: 49.64 | I261: =L261+M261+N261 -> 44.3214 | J261: =O261+P261 -> 5.3186 | K261: =IF(H261=I261+J261,0,W261) -> 0 | L261: 0 | M261: 44.3214 | N261: 0 | O261: 0 | P261: 5.3186 | Q261: 44.3214 | R261: 49.64 | S261: 0 | T261: 0 | U261: 0 | V261: 0 | W261: 0 | X261: 0 | Y261: 0 | Z261: 49.64 | AA261: 0 | AB261: 0 | AC261: 0 | AD261: 0 | AE261: 0 | AF261: 0 | AG261: 46132.518 | AH261: 24105 | AI261: 0 | AJ261: =AH261+AI261 -> 24105 | AK261: 0
A262: 46132.518 | B262: Prodej | C262: Šímová | D262: CZ60738677 | E262: 96 | F262: Pokladna 2 | G262: 169002611 | H262: 33 | I262: =L262+M262+N262 -> 29.375 | J262: =O262+P262 -> 3.525 | K262: =IF(H262=I262+J262,0,W262) -> 0.1 | L262: 0 | M262: 29.375 | N262: 0 | O262: 0 | P262: 3.525 | Q262: 29.375 | R262: 32.9 | S262: 0 | T262: 0 | U262: 0 | V262: 0 | W262: 0.1 | X262: 100 | Y262: 0 | Z262: 0 | AA262: 0 | AB262: 0 | AC262: 0 | AD262: 0 | AE262: 0 | AF262: 0 | AG262: 46132.518 | AH262: 24138 | AI262: 0 | AJ262: =AH262+AI262 -> 24138 | AK262: 0
A263: 46132.519 | B263: Prodej | C263: profikasa | D263: CZ60738677 | E263: 96 | F263: Pokladna SCO1 | G263: 161000350 | H263: 15.9 | I263: =L263+M263+N263 -> 13.43 | J263: =O263+P263 -> 2.47 | K263: =IF(H263=I263+J263,0,W263) -> 0 | L263: 9.42 | M263: 4.01 | N263: 0 | O263: 1.98 | P263: 0.49 | Q263: 13.43 | R263: 15.9 | S263: 0 | T263: 0 | U263: 0 | V263: 0 | W263: 0 | X263: 0 | Y263: 0 | Z263: 15.9 | AA263: 0 | AB263: 0 | AC263: 0 | AD263: 0 | AE263: 0 | AF263: 0 | AG263: 46132.519 | AH263: 0 | AI263: 0 | AJ263: =AH263+AI263 -> 0 | AK263: 0
A264: 46132.519 | B264: Prodej | C264: Šímová | D264: CZ60738677 | E264: 96 | F264: Pokladna 2 | G264: 169002612 | H264: 82.5 | I264: =L264+M264+N264 -> 73.6608 | J264: =O264+P264 -> 8.8392 | K264: =IF(H264=I264+J264,0,W264) -> 0 | L264: 0 | M264: 73.6608 | N264: 0 | O264: 0 | P264: 8.8392 | Q264: 73.6608 | R264: 82.5 | S264: 0 | T264: 0 | U264: 0 | V264: 0 | W264: 0 | X264: 0 | Y264: 0 | Z264: 82.5 | AA264: 0 | AB264: 0 | AC264: 0 | AD264: 0 | AE264: 0 | AF264: 0 | AG264: 46132.519 | AH264: 24138 | AI264: 0 | AJ264: =AH264+AI264 -> 24138 | AK264: 0
A265: 46132.519 | B265: Prodej | C265: Šímová | D265: CZ60738677 | E265: 96 | F265: Pokladna 2 | G265: 169002613 | H265: 11 | I265: =L265+M265+N265 -> 9.4215 | J265: =O265+P265 -> 1.9785 | K265: =IF(H265=I265+J265,0,W265) -> -0.4 | L265: 9.4215 | M265: 0 | N265: 0 | O265: 1.9785 | P265: 0 | Q265: 9.4215 | R265: 11.4 | S265: 0 | T265: 0 | U265: 0 | V265: 0 | W265: -0.4 | X265: 20 | Y265: 0 | Z265: 0 | AA265: 0 | AB265: 0 | AC265: 0 | AD265: 0 | AE265: 0 | AF265: 0 | AG265: 46132.519 | AH265: 24149 | AI265: 0 | AJ265: =AH265+AI265 -> 24149 | AK265: 0
A266: 46132.52 | B266: Prodej | C266: Šímová | D266: CZ60738677 | E266: 96 | F266: Pokladna 2 | G266: 169002614 | H266: 37.8 | I266: =L266+M266+N266 -> 33.75 | J266: =O266+P266 -> 4.05 | K266: =IF(H266=I266+J266,0,W266) -> 0 | L266: 0 | M266: 33.75 | N266: 0 | O266: 0 | P266: 4.05 | Q266: 33.75 | R266: 37.8 | S266: 0 | T266: 0 | U266: 0 | V266: 0 | W266: 0 | X266: 0 | Y266: 0 | Z266: 37.8 | AA266: 0 | AB266: 0 | AC266: 0 | AD266: 0 | AE266: 0 | AF266: 0 | AG266: 46132.52 | AH266: 24149 | AI266: 0 | AJ266: =AH266+AI266 -> 24149 | AK266: 0
... A318: 46132.561 | B318: Prodej | C318: Teclová | D318: CZ60738677 | E318: 96 | F318: Pokladna 1 | G318: 166004743 | H318: 20 | I318: =L318+M318+N318 -> 17.7679 | J318: =O318+P318 -> 2.1321 | K318: =IF(H318=I318+J318,0,W318) -> 0.1 | L318: 0 | M318: 17.7679 | N318: 0 | O318: 0 | P318: 2.1321 | Q318: 17.7679 | R318: 19.9 | S318: 0 | T318: 0 | U318: 0 | V318: 0 | W318: 0.1 | X318: 20 | Y318: 0 | Z318: 0 | AA318: 0 | AB318: 0 | AC318: 0 | AD318: 0 | AE318: 0 | AF318: 0 | AG318: 46132.561 | AH318: 42859 | AI318: 0 | AJ318: =AH318+AI318 -> 42859 | AK318: 0
A319: 46132.561 | B319: Přihlášení | C319: Klímová | D319: CZ60738677 | E319: 96 | F319: Pokladna 2 | H319: 0 | I319: =L319+M319+N319 -> 0 | J319: =O319+P319 -> 0 | K319: =IF(H319=I319+J319,0,W319) -> 0 | L319: 0 | M319: 0 | N319: 0 | O319: 0 | P319: 0 | Q319: 0 | R319: 0 | S319: 0 | T319: 0 | U319: 0 | V319: 0 | W319: 0 | Y319: 0 | Z319: 0 | AA319: 0 | AB319: 0 | AC319: 0 | AD319: 0 | AE319: 0 | AF319: 0 | AG319: 46132.561 | AH319: 25082 | AI319: 0 | AJ319: =AH319+AI319 -> 25082
A320: 46132.561 | B320: Přihlášení | C320: Teclová | D320: CZ60738677 | E320: 96 | F320: Pokladna 1 | H320: 0 | I320: =L320+M320+N320 -> 0 | J320: =O320+P320 -> 0 | K320: =IF(H320=I320+J320,0,W320) -> 0 | L320: 0 | M320: 0 | N320: 0 | O320: 0 | P320: 0 | Q320: 0 | R320: 0 | S320: 0 | T320: 0 | U320: 0 | V320: 0 | W320: 0 | Y320: 0 | Z320: 0 | AA320: 0 | AB320: 0 | AC320: 0 | AD320: 0 | AE320: 0 | AF320: 0 | AG320: 46132.561 | AH320: 42859 | AI320: 0 | AJ320: =AH320+AI320 -> 42859
A321: 46132.561 | B321: Prodej | C321: Teclová | D321: CZ60738677 | E321: 96 | F321: Pokladna 1 | G321: 166004744 | H321: 28 | I321: =L321+M321+N321 -> 24.9107 | J321: =O321+P321 -> 2.9893 | K321: =IF(H321=I321+J321,0,W321) -> 0.1 | L321: 0 | M321: 24.9107 | N321: 0 | O321: 0 | P321: 2.9893 | Q321: 24.9107 | R321: 27.9 | S321: 0 | T321: 0 | U321: 0 | V321: 0 | W321: 0.1 | X321: 28 | Y321: 0 | Z321: 0 | AA321: 0 | AB321: 0 | AC321: 0 | AD321: 0 | AE321: 0 | AF321: 0 | AG321: 46132.561 | AH321: 42887 | AI321: 0 | AJ321: =AH321+AI321 -> 42887 | AK321: 0
A322: 46132.561 | B322: Prodej | C322: profikasa | D322: CZ60738677 | E322: 96 | F322: Pokladna SCO1 | G322: 161000354 | H322: 41.9 | I322: =L322+M322+N322 -> 34.62 | J322: =O322+P322 -> 7.28 | K322: =IF(H322=I322+J322,0,W322) -> 0 | L322: 34.62 | M322: 0 | N322: 0 | O322: 7.28 | P322: 0 | Q322: 34.62 | R322: 41.9 | S322: 0 | T322: 0 | U322: 0 | V322: 0 | W322: 0 | X322: 0 | Y322: 0 | Z322: 41.9 | AA322: 0 | AB322: 0 | AC322: 0 | AD322: 0 | AE322: 0 | AF322: 0 | AG322: 46132.561 | AH322: 0 | AI322: 0 | AJ322: =AH322+AI322 -> 0 | AK322: 0
A323: 46132.561 | B323: Přihlášení | C323: Klímová | D323: CZ60738677 | E323: 96 | F323: Pokladna 1 | H323: 0 | I323: =L323+M323+N323 -> 0 | J323: =O323+P323 -> 0 | K323: =IF(H323=I323+J323,0,W323) -> 0 | L323: 0 | M323: 0 | N323: 0 | O323: 0 | P323: 0 | Q323: 0 | R323: 0 | S323: 0 | T323: 0 | U323: 0 | V323: 0 | W323: 0 | Y323: 0 | Z323: 0 | AA323: 0 | AB323: 0 | AC323: 0 | AD323: 0 | AE323: 0 | AF323: 0 | AG323: 46132.561 | AH323: 42887 | AI323: 0 | AJ323: =AH323+AI323 -> 42887
A324: 46132.562 | B324: Přihlášení | C324: Teclová | D324: CZ60738677 | E324: 96 | F324: Pokladna 1 | H324: 0 | I324: =L324+M324+N324 -> 0 | J324: =O324+P324 -> 0 | K324: =IF(H324=I324+J324,0,W324) -> 0 | L324: 0 | M324: 0 | N324: 0 | O324: 0 | P324: 0 | Q324: 0 | R324: 0 | S324: 0 | T324: 0 | U324: 0 | V324: 0 | W324: 0 | Y324: 0 | Z324: 0 | AA324: 0 | AB324: 0 | AC324: 0 | AD324: 0 | AE324: 0 | AF324: 0 | AG324: 46132.562 | AH324: 42887 | AI324: 0 | AJ324: =AH324+AI324 -> 42887
A325: 46132.563 | B325: Prodej | C325: profikasa | D325: CZ60738677 | E325: 96 | F325: Pokladna SCO1 | G325: 161000355 | H325: 103.5 | I325: =L325+M325+N325 -> 90.62 | J325: =O325+P325 -> 12.88 | K325: =IF(H325=I325+J325,0,W325) -> 0 | L325: 22.23 | M325: 68.39 | N325: 0 | O325: 4.67 | P325: 8.21 | Q325: 90.62 | R325: 103.5 | S325: 0 | T325: 0 | U325: 0 | V325: 0 | W325: 0 | X325: 0 | Y325: 0 | Z325: 103.5 | AA325: 0 | AB325: 0 | AC325: 0 | AD325: 0 | AE325: 0 | AF325: 0 | AG325: 46132.563 | AH325: 0 | AI325: 0 | AJ325: =AH325+AI325 -> 0 | AK325: 0
A326: 46132.563 | B326: Prodej | C326: Teclová | D326: CZ60738677 | E326: 96 | F326: Pokladna 1 | G326: 166004745 | H326: 59.8 | I326: =L326+M326+N326 -> 53.3929 | J326: =O326+P326 -> 6.4071 | K326: =IF(H326=I326+J326,0,W326) -> 0 | L326: 0 | M326: 53.3929 | N326: 0 | O326: 0 | P326: 6.4071 | Q326: 53.3929 | R326: 59.8 | S326: 0 | T326: 0 | U326: 0 | V326: 0 | W326: 0 | X326: 0 | Y326: 0 | Z326: 59.8 | AA326: 0 | AB326: 0 | AC326: 0 | AD326: 0 | AE326: 0 | AF326: 0 | AG326: 46132.563 | AH326: 42887 | AI326: 0 | AJ326: =AH326+AI326 -> 42887 | AK326: 0
A327: 46132.565 | B327: Prodej | C327: Teclová | D327: CZ60738677 | E327: 96 | F327: Pokladna 1 | G327: 166004746 | H327: 206.8 | I327: =L327+M327+N327 -> 178.3073 | J327: =O327+P327 -> 28.4927 | K327: =IF(H327=I327+J327,0,W327) -> 0 | L327: 78.843 | M327: 99.4643 | N327: 0 | O327: 16.557 | P327: 11.9357 | Q327: 178.3073 | R327: 206.8 | S327: 0 | T327: 0 | U327: 0 | V327: 0 | W327: 0 | X327: 0 | Y327: 0 | Z327: 206.8 | AA327: 0 | AB327: 0 | AC327: 0 | AD327: 0 | AE327: 0 | AF327: 0 | AG327: 46132.565 | AH327: 42887 | AI327: 0 | AJ327: =AH327+AI327 -> 42887 | AK327: 0
A328: 46132.565 | B328: Prodej | C328: Teclová | D328: CZ60738677 | E328: 96 | F328: Pokladna 1 | G328: 166004747 | H328: 32 | I328: =L328+M328+N328 -> 28.8304 | J328: =O328+P328 -> 3.4596 | K328: =IF(H328=I328+J328,0,W328) -> -0.29 | L328: 0 | M328: 28.8304 | N328: 0 | O328: 0 | P328: 3.4596 | Q328: 28.8304 | R328: 32.29 | S328: 0 | T328: 0 | U328: 0 | V328: 0 | W328: -0.29 | X328: 52 | Y328: 0 | Z328: 0 | AA328: 0 | AB328: 0 | AC328: 0 | AD328: 0 | AE328: 0 | AF328: 0 | AG328: 46132.565 | AH328: 42919 | AI328: 0 | AJ328: =AH328+AI328 -> 42919 | AK328: 0
A329: 46132.566 | B329: Prodej | C329: profikasa | D329: CZ60738677 | E329: 96 | F329: Pokladna SCO2 | G329: 163000334 | H329: 12.4 | I329: =L329+M329+N329 -> 11.07 | J329: =O329+P329 -> 1.33 | K329: =IF(H329=I329+J329,0,W329) -> 0 | L329: 0 | M329: 11.07 | N329: 0 | O329: 0 | P329: 1.33 | Q329: 11.07 | R329: 12.4 | S329: 0 | T329: 0 | U329: 0 | V329: 0 | W329: 0 | X329: 0 | Y329: 0 | Z329: 12.4 | AA329: 0 | AB329: 0 | AC329: 0 | AD329: 0 | AE329: 0 | AF329: 0 | AG329: 46132.566 | AH329: 0 | AI329: 0 | AJ329: =AH329+AI329 -> 0 | AK329: 0
A330: 46132.566 | B330: Prodej | C330: profikasa | D330: CZ60738677 | E330: 96 | F330: Pokladna SCO1 | G330: 161000356 | H330: 12.4 | I330: =L330+M330+N330 -> 11.07 | J330: =O330+P330 -> 1.33 | K330: =IF(H330=I330+J330,0,W330) -> 0 | L330: 0 | M330: 11.07 | N330: 0 | O330: 0 | P330: 1.33 | Q330: 11.07 | R330: 12.4 | S330: 0 | T330: 0 | U330: 0 | V330: 0 | W330: 0 | X330: 0 | Y330: 0 | Z330: 12.4 | AA330: 0 | AB330: 0 | AC330: 0 | AD330: 0 | AE330: 0 | AF330: 0 | AG330: 46132.566 | AH330: 0 | AI330: 0 | AJ330: =AH330+AI330 -> 0 | AK330: 0
A331: 46132.567 | B331: Prodej | C331: Teclová | D331: CZ60738677 | E331: 96 | F331: Pokladna 1 | G331: 166004748 | H331: 52 | I331: =L331+M331+N331 -> 46.2054 | J331: =O331+P331 -> 5.5446 | K331: =IF(H331=I331+J331,0,W331) -> 0.25 | L331: 0 | M331: 46.2054 | N331: 0 | O331: 0 | P331: 5.5446 | Q331: 46.2054 | R331: 51.75 | S331: 0 | T331: 0 | U331: 0 | V331: 0 | W331: 0.25 | X331: 52 | Y331: 0 | Z331: 0 | AA331: 0 | AB331: 0 | AC331: 0 | AD331: 0 | AE331: 0 | AF331: 0 | AG331: 46132.567 | AH331: 42971 | AI331: 0 | AJ331: =AH331+AI331 -> 42971 | AK331: 0
A332: 46132.568 | B332: Prodej | C332: Teclová | D332: CZ60738677 | E332: 96 | F332: Pokladna 1 | G332: 166004749 | H332: 510 | I332: =L332+M332+N332 -> 442.2227 | J332: =O332+P332 -> 67.4073 | K332: =IF(H332=I332+J332,0,W332) -> 0.37 | L332: 159.3388 | M332: 282.8839 | N332: 0 | O332: 33.4612 | P332: 33.9461 | Q332: 442.2227 | R332: 509.63 | S332: 0 | T332: 0 | U332: 0 | V332: 0 | W332: 0.37 | X332: 700 | Y332: 0 | Z332: 0 | AA332: 0 | AB332: 0 | AC332: 0 | AD332: 0 | AE332: 0 | AF332: 0 | AG332: 46132.568 | AH332: 43481 | AI332: 0 | AJ332: =AH332+AI332 -> 43481 | AK332: 0
A333: 46132.568 | B333: Prodej | C333: Teclová | D333: CZ60738677 | E333: 96 | F333: Pokladna 1 | G333: 166004750 | H333: 47.8 | I333: =L333+M333+N333 -> 39.5042 | J333: =O333+P333 -> 8.2958 | K333: =IF(H333=I333+J333,0,W333) -> 0 | L333: 39.5042 | M333: 0 | N333: 0 | O333: 8.2958 | P333: 0 | Q333: 39.5042 | R333: 47.8 | S333: 0 | T333: 0 | U333: 0 | V333: 0 | W333: 0 | X333: 0 | Y333: 0 | Z333: 47.8 | AA333: 0 | AB333: 0 | AC333: 0 | AD333: 0 | AE333: 0 | AF333: 0 | AG333: 46132.568 | AH333: 43481 | AI333: 0 | AJ333: =AH333+AI333 -> 43481 | AK333: 0
A334: 46132.57 | B334: Prodej | C334: Teclová | D334: CZ60738677 | E334: 96 | F334: Pokladna 1 | G334: 166004751 | H334: 424 | I334: =L334+M334+N334 -> 366.2848 | J334: =O334+P334 -> 57.6252 | K334: =IF(H334=I334+J334,0,W334) -> 0.09 | L334: 151.9009 | M334: 214.3839 | N334: 0 | O334: 31.8991 | P334: 25.7261 | Q334: 366.2848 | R334: 423.91 | S334: 0 | T334: 0 | U334: 0 | V334: 0 | W334: 0.09 | X334: 500 | Y334: 0 | Z334: 0 | AA334: 0 | AB334: 0 | AC334: 0 | AD334: 0 | AE334: 0 | AF334: 0 | AG334: 46132.57 | AH334: 43905 | AI334: 0 | AJ334: =AH334+AI334 -> 43905 | AK334: 0
A335: 46132.57 | B335: Prodej | C335: profikasa | D335: CZ60738677 | E335: 96 | F335: Pokladna SCO1 | G335: 161000357 | H335: 19.9 | I335: =L335+M335+N335 -> 17.76 | J335: =O335+P335 -> 2.14 | K335: =IF(H335=I335+J335,0,W335) -> 0 | L335: 0 | M335: 17.76 | N335: 0 | O335: 0 | P335: 2.14 | Q335: 17.76 | R335: 19.9 | S335: 0 | T335: 0 | U335: 0 | V335: 0 | W335: 0 | X335: 0 | Y335: 0 | Z335: 19.9 | AA335: 0 | AB335: 0 | AC335: 0 | AD335: 0 | AE335: 0 | AF335: 0 | AG335: 46132.57 | AH335: 0 | AI335: 0 | AJ335: =AH335+AI335 -> 0 | AK335: 0
A336: 46132.57 | B336: Prodej | C336: Teclová | D336: CZ60738677 | E336: 96 | F336: Pokladna 1 | G336: 166004752 | H336: 82.6 | I336: =L336+M336+N336 -> 71.1733 | J336: =O336+P336 -> 11.4267 | K336: =IF(H336=I336+J336,0,W336) -> 0 | L336: 32.0661 | M336: 39.1072 | N336: 0 | O336: 6.7339 | P336: 4.6928 | Q336: 71.1733 | R336: 82.6 | S336: 0 | T336: 0 | U336: 0 | V336: 0 | W336: 0 | X336: 0 | Y336: 0 | Z336: 82.6 | AA336: 0 | AB336: 0 | AC336: 0 | AD336: 0 | AE336: 0 | AF336: 0 | AG336: 46132.57 | AH336: 43905 | AI336: 0 | AJ336: =AH336+AI336 -> 43905 | AK336: 0
A337: 46132.57 | B337: Prodej | C337: Teclová | D337: CZ60738677 | E337: 96 | F337: Pokladna 1 | G337: 166004753 | H337: 118 | I337: =L337+M337+N337 -> 99.3588 | J337: =O337+P337 -> 18.1412 | K337: =IF(H337=I337+J337,0,W337) -> 0.5 | L337: 69.0909 | M337: 30.2679 | N337: 0 | O337: 14.5091 | P337: 3.6321 | Q337: 99.3588 | R337: 117.5 | S337: 0 | T337: 0 | U337: 0 | V337: 0 | W337: 0.5 | X337: 150 | Y337: 0 | Z337: 0 | AA337: 0 | AB337: 0 | AC337: 0 | AD337: 0 | AE337: 0 | AF337: 0 | AG337: 46132.57 | AH337: 44023 | AI337: 0 | AJ337: =AH337+AI337 -> 44023 | AK337: 0
A338: 46132.572 | B338: Přihlášení | C338: Klímová | D338: CZ60738677 | E338: 96 | F338: Pokladna 2 | H338: 0 | I338: =L338+M338+N338 -> 0 | J338: =O338+P338 -> 0 | K338: =IF(H338=I338+J338,0,W338) -> 0 | L338: 0 | M338: 0 | N338: 0 | O338: 0 | P338: 0 | Q338: 0 | R338: 0 | S338: 0 | T338: 0 | U338: 0 | V338: 0 | W338: 0 | Y338: 0 | Z338: 0 | AA338: 0 | AB338: 0 | AC338: 0 | AD338: 0 | AE338: 0 | AF338: 0 | AG338: 46132.572 | AH338: 25082 | AI338: 0 | AJ338: =AH338+AI338 -> 25082
A339: 46132.572 | B339: Prodej | C339: Teclová | D339: CZ60738677 | E339: 96 | F339: Pokladna 1 | G339: 166004754 | H339: 30 | I339: =L339+M339+N339 -> 26.6964 | J339: =O339+P339 -> 3.2036 | K339: =IF(H339=I339+J339,0,W339) -> 0.1 | L339: 0 | M339: 26.6964 | N339: 0 | O339: 0 | P339: 3.2036 | Q339: 26.6964 | R339: 29.9 | S339: 0 | T339: 0 | U339: 0 | V339: 0 | W339: 0.1 | X339: 30 | Y339: 0 | Z339: 0 | AA339: 0 | AB339: 0 | AC339: 0 | AD339: 0 | AE339: 0 | AF339: 0 | AG339: 46132.572 | AH339: 44053 | AI339: 0 | AJ339: =AH339+AI339 -> 44053 | AK339: 0
A340: 46132.573 | B340: Prodej | C340: Teclová | D340: CZ60738677 | E340: 96 | F340: Pokladna 1 | G340: 166004755 | H340: 14 | I340: =L340+M340+N340 -> 12.0537 | J340: =O340+P340 -> 1.4463 | K340: =IF(H340=I340+J340,0,W340) -> 0.5 | L340: 0 | M340: 12.0537 | N340: 0 | O340: 0 | P340: 1.4463 | Q340: 12.0537 | R340: 13.5 | S340: 0 | T340: 0 | U340: 0 | V340: 0 | W340: 0.5 | X340: 14 | Y340: 0 | Z340: 0 | AA340: 0 | AB340: 0 | AC340: 0 | AD340: 0 | AE340: 0 | AF340: 0 | AG340: 46132.573 | AH340: 44067 | AI340: 0 | AJ340: =AH340+AI340 -> 44067 | AK340: 0
A341: 46132.573 | B341: Přihlášení | C341: Klímová | D341: CZ60738677 | E341: 96 | F341: Pokladna 1 | H341: 0 | I341: =L341+M341+N341 -> 0 | J341: =O341+P341 -> 0 | K341: =IF(H341=I341+J341,0,W341) -> 0 | L341: 0 | M341: 0 | N341: 0 | O341: 0 | P341: 0 | Q341: 0 | R341: 0 | S341: 0 | T341: 0 | U341: 0 | V341: 0 | W341: 0 | Y341: 0 | Z341: 0 | AA341: 0 | AB341: 0 | AC341: 0 | AD341: 0 | AE341: 0 | AF341: 0 | AG341: 46132.573 | AH341: 44067 | AI341: 0 | AJ341: =AH341+AI341 -> 44067
A342: 46132.573 | B342: Přihlášení | C342: Teclová | D342: CZ60738677 | E342: 96 | F342: Pokladna 1 | H342: 0 | I342: =L342+M342+N342 -> 0 | J342: =O342+P342 -> 0 | K342: =IF(H342=I342+J342,0,W342) -> 0 | L342: 0 | M342: 0 | N342: 0 | O342: 0 | P342: 0 | Q342: 0 | R342: 0 | S342: 0 | T342: 0 | U342: 0 | V342: 0 | W342: 0 | Y342: 0 | Z342: 0 | AA342: 0 | AB342: 0 | AC342: 0 | AD342: 0 | AE342: 0 | AF342: 0 | AG342: 46132.573 | AH342: 44067 | AI342: 0 | AJ342: =AH342+AI342 -> 44067
A343: 46132.575 | B343: Prodej | C343: profikasa | D343: CZ60738677 | E343: 96 | F343: Pokladna SCO1 | G343: 161000358 | H343: 19.9 | I343: =L343+M343+N343 -> 16.44 | J343: =O343+P343 -> 3.46 | K343: =IF(H343=I343+J343,0,W343) -> 0 | L343: 16.44 | M343: 0 | N343: 0 | O343: 3.46 | P343: 0 | Q343: 16.44 | R343: 19.9 | S343: 0 | T343: 0 | U343: 0 | V343: 0 | W343: 0 | X343: 0 | Y343: 0 | Z343: 19.9 | AA343: 0 | AB343: 0 | AC343: 0 | AD343: 0 | AE343: 0 | AF343: 0 | AG343: 46132.575 | AH343: 0 | AI343: 0 | AJ343: =AH343+AI343 -> 0 | AK343: 0
A344: 46132.575 | B344: Prodej | C344: Teclová | D344: CZ60738677 | E344: 96 | F344: Pokladna 1 | G344: 166004756 | H344: 327 | I344: =L344+M344+N344 -> 281.5328 | J344: =O344+P344 -> 45.7072 | K344: =IF(H344=I344+J344,0,W344) -> -0.24 | L344: 132.4794 | M344: 149.0534 | N344: 0 | O344: 27.8206 | P344: 17.8866 | Q344: 281.5328 | R344: 327.24 | S344: 0 | T344: 0 | U344: 0 | V344: 0 | W344: -0.24 | X344: 500 | Y344: 0 | Z344: 0 | AA344: 0 | AB344: 0 | AC344: 0 | AD344: 0 | AE344: 0 | AF344: 0 | AG344: 46132.575 | AH344: 44394 | AI344: 0 | AJ344: =AH344+AI344 -> 44394 | AK344: 0
A345: 46132.576 | B345: Prodej | C345: Teclová | D345: CZ60738677 | E345: 96 | F345: Pokladna 1 | G345: 166004757 | H345: 90.3 | I345: =L345+M345+N345 -> 80.6251 | J345: =O345+P345 -> 9.6749 | K345: =IF(H345=I345+J345,0,W345) -> 0 | L345: 0 | M345: 80.6251 | N345: 0 | O345: 0 | P345: 9.6749 | Q345: 80.6251 | R345: 90.3 | S345: 0 | T345: 0 | U345: 0 | V345: 0 | W345: 0 | X345: 0 | Y345: 0 | Z345: 90.3 | AA345: 0 | AB345: 0 | AC345: 0 | AD345: 0 | AE345: 0 | AF345: 0 | AG345: 46132.576 | AH345: 44394 | AI345: 0 | AJ345: =AH345+AI345 -> 44394 | AK345: 0
A346: 46132.576 | B346: Prodej | C346: Teclová | D346: CZ60738677 | E346: 96 | F346: Pokladna 1 | G346: 166004758 | H346: 11 | I346: =L346+M346+N346 -> 9.7321 | J346: =O346+P346 -> 1.1679 | K346: =IF(H346=I346+J346,0,W346) -> 0.1 | L346: 0 | M346: 9.7321 | N346: 0 | O346: 0 | P346: 1.1679 | Q346: 9.7321 | R346: 10.9 | S346: 0 | T346: 0 | U346: 0 | V346: 0 | W346: 0.1 | X346: 20 | Y346: 0 | Z346: 0 | AA346: 0 | AB346: 0 | AC346: 0 | AD346: 0 | AE346: 0 | AF346: 0 | AG346: 46132.576 | AH346: 44405 | AI346: 0 | AJ346: =AH346+AI346 -> 44405 | AK346: 0
A347: 46132.577 | B347: Prodej | C347: Teclová | D347: CZ60738677 | E347: 96 | F347: Pokladna 1 | G347: 166004759 | H347: 65 | I347: =L347+M347+N347 -> 58.3929 | J347: =O347+P347 -> 7.0071 | K347: =IF(H347=I347+J347,0,W347) -> -0.4 | L347: 0 | M347: 58.3929 | N347: 0 | O347: 0 | P347: 7.0071 | Q347: 58.3929 | R347: 65.4 | S347: 0 | T347: 0 | U347: 0 | V347: 0 | W347: -0.4 | X347: 65 | Y347: 0 | Z347: 0 | AA347: 0 | AB347: 0 | AC347: 0 | AD347: 0 | AE347: 0 | AF347: 0 | AG347: 46132.577 | AH347: 44470 | AI347: 0 | AJ347: =AH347+AI347 -> 44470 | AK347: 0
A348: 46132.578 | B348: Prodej | C348: Teclová | D348: CZ60738677 | E348: 96 | F348: Pokladna 1 | G348: 166004760 | H348: 354.3 | I348: =L348+M348+N348 -> 316.3391 | J348: =O348+P348 -> 37.9609 | K348: =IF(H348=I348+J348,0,W348) -> 0 | L348: 0 | M348: 316.3391 | N348: 0 | O348: 0 | P348: 37.9609 | Q348: 316.3391 | R348: 354.3 | S348: 0 | T348: 0 | U348: 0 | V348: 0 | W348: 0 | X348: 0 | Y348: 0 | Z348: 354.3 | AA348: 0 | AB348: 0 | AC348: 0 | AD348: 0 | AE348: 0 | AF348: 0 | AG348: 46132.578 | AH348: 44470 | AI348: 0 | AJ348: =AH348+AI348 -> 44470 | AK348: 0
A349: 46132.578 | B349: Prodej | C349: Teclová | D349: CZ60738677 | E349: 96 | F349: Pokladna 1 | G349: 166004761 | H349: 141.55 | I349: =L349+M349+N349 -> 125.6274 | J349: =O349+P349 -> 15.9226 | K349: =IF(H349=I349+J349,0,W349) -> 0 | L349: 9.4215 | M349: 116.2059 | N349: 0 | O349: 1.9785 | P349: 13.9441 | Q349: 125.6274 | R349: 141.55 | S349: 0 | T349: 0 | U349: 0 | V349: 0 | W349: 0 | X349: 0 | Y349: 0 | Z349: 141.55 | AA349: 0 | AB349: 0 | AC349: 0 | AD349: 0 | AE349: 0 | AF349: 0 | AG349: 46132.578 | AH349: 44470 | AI349: 0 | AJ349: =AH349+AI349 -> 44470 | AK349: 0
A350: 46132.579 | B350: Prodej | C350: Teclová | D350: CZ60738677 | E350: 96 | F350: Pokladna 1 | G350: 166004762 | H350: 95.4 | I350: =L350+M350+N350 -> 78.843 | J350: =O350+P350 -> 16.557 | K350: =IF(H350=I350+J350,0,W350) -> 0 | L350: 78.843 | M350: 0 | N350: 0 | O350: 16.557 | P350: 0 | Q350: 78.843 | R350: 95.4 | S350: 0 | T350: 0 | U350: 0 | V350: 0 | W350: 0 | X350: 0 | Y350: 0 | Z350: 95.4 | AA350: 0 | AB350: 0 | AC350: 0 | AD350: 0 | AE350: 0 | AF350: 0 | AG350: 46132.579 | AH350: 44470 | AI350: 0 | AJ350: =AH350+AI350 -> 44470 | AK350: 0
...

Sheet Fiskalizované doklady
A1: Identifikace | G1: Datum a doklad | J1: Tržba | N1: Dle sazeb DPH | S1: Dle věcného rozlišení | Z1: Platby | AF1: Hlášení EET | AL1: Poskytnuté slevy
J2: =SUBTOTAL(109,J4:J999880) -> 0 | K2: =SUBTOTAL(109,K4:K999880) -> 0 | L2: =SUBTOTAL(109,L4:L999880) -> 0 | M2: =SUBTOTAL(109,M4:M999880) -> 0 | N2: =SUBTOTAL(109,N4:N999880) -> 0 | O2: =SUBTOTAL(109,O4:O999880) -> 0 | P2: =SUBTOTAL(109,P4:P999880) -> 0 | Q2: =SUBTOTAL(109,Q4:Q999880) -> 0 | ... AB2: =SUBTOTAL(109,AB4:AB999880) -> 0 | AD2: =SUBTOTAL(109,AD4:AD999880) -> 0 | AE2: =SUBTOTAL(109,AE4:AE999880) -> 0 | AL2: =SUBTOTAL(109,AL4:AL999853) -> 0
A3: DIČ | B3: Název firmy | C3: ID provozovny | D3: Název provozovny | E3: ID pokladny | F3: Uživatel | G3: Datum | H3: Čas | I3: Číslo dokladu | J3: Tržba celkem | K3: Základ DPH celkem | L3: DPH Celkem | M3: Zaokrouhlení | N3: Základ DPH 21% | O3: Základ DPH 12% | P3: Základ DPH 0% | Q3: DPH 21% | R3: DPH 12% | S3: Prodané zboží bez DPH | T3: Prodané zboží s DPH | U3: Vrácené zboží bez DPH | V3: Vrácené zboží s DPH | W3: Prodané obaly | X3: Vykoupené obaly | Y3: Zaokrouhlení | Z3: Hotovost | AA3: Stravenky | AB3: Platební karta | AC3: Gastro konto | AD3: Cashback | AE3: Vráceno | AF3: Hlášení odesláno | AG3: Hlášení přijato | AH3: BKP | AI3: FIK | AJ3: PKP | AK3: UUID | AL3: Sleva na pokladně

Sheet Nefiskalizované doklady
A1: Identifikace | G1: Datum a doklad | J1: Tržba | N1: Dle sazeb DPH | S1: Dle věcného rozlišení | Z1: Platby | AF1: Poskytnuté slevy
J2: =SUBTOTAL(109,J4:J999948) -> 92316.38 | K2: =SUBTOTAL(109,K4:K999948) -> 79957.291 | L2: =SUBTOTAL(109,L4:L999948) -> 11784.839 | M2: =SUBTOTAL(109,M4:M999948) -> 21.23 | N2: =SUBTOTAL(109,N4:N999948) -> 24403.425 | O2: =SUBTOTAL(109,O4:O999948) -> 56035.246 | P2: =SUBTOTAL(109,P4:P999948) -> 6 | Q2: =SUBTOTAL(109,Q4:Q999948) -> 5125.0054 | ... AB2: =SUBTOTAL(109,AB4:AB999948) -> 53413.38 | AD2: =SUBTOTAL(109,AD4:AD999948) -> 0 | AE2: =SUBTOTAL(109,AE4:AE999948) -> -48314 | AF2: =SUBTOTAL(109,AF4:AF999853) -> 1083.0861
A3: DIČ | B3: Název firmy | C3: ID provozovny | D3: Název provozovny | E3: ID pokladny | F3: Uživatel | G3: Datum | H3: Čas | I3: Číslo dokladu | J3: Tržba celkem | K3: Základ DPH celkem | L3: DPH Celkem | M3: Zaokrouhlení | N3: Základ DPH 21% | O3: Základ DPH 12% | P3: Základ DPH 0% | Q3: DPH 21% | R3: DPH 12% | S3: Prodané zboží bez DPH | T3: Prodané zboží s DPH | U3: Vrácené zboží bez DPH | V3: Vrácené zboží s DPH | W3: Prodané obaly | X3: Vykoupené obaly | Y3: Zaokrouhlení | Z3: Hotovost | AA3: Stravenky | AB3: Platební karta | AC3: Gastro konto | AD3: Cashback | AE3: Vráceno | AF3: Sleva na pokladně
A4: CZ60738677 | B4: RAPO BRNO, s.r.o. | C4: 96 | D4: BALADA - Březinky | E4: Pokladna SCO2 | F4: profikasa | G4: 46132 | H4: 0.37474537 | I4: 163000332 | J4: 553.02 | K4: ==N4+O4+P4 -> FALSE | L4: ==Q4+R4 -> FALSE | M4: ==IF(J4=K4+L4,0,Y4) -> FALSE | N4: 78.84 | O4: 408.54 | P4: 0 | Q4: 16.56 | R4: 49.08 | S4: 487.38 | T4: 553.02 | U4: 0 | V4: 0 | W4: 0 | X4: 0 | Y4: 0 | Z4: 0 | AA4: 0 | AB4: 553.02 | AD4: 0 | AE4: 0 | AF4: 0
A5: CZ60738677 | B5: RAPO BRNO, s.r.o. | C5: 96 | D5: BALADA - Březinky | E5: Pokladna SCO2 | F5: profikasa | G5: 46132 | H5: 0.37981481 | I5: 163000333 | J5: 37.19 | K5: =N5+O5+P5 -> 33.2 | L5: =Q5+R5 -> 3.99 | M5: =IF(J5=K5+L5,0,Y5) -> 0 | N5: 0 | O5: 33.2 | P5: 0 | Q5: 0 | R5: 3.99 | S5: 33.2 | T5: 37.19 | U5: 0 | V5: 0 | W5: 0 | X5: 0 | Y5: 0 | Z5: 0 | AA5: 0 | AB5: 37.19 | AD5: 0 | AE5: 0 | AF5: 0
A6: CZ60738677 | B6: RAPO BRNO, s.r.o. | C6: 96 | D6: BALADA - Březinky | E6: Pokladna SCO2 | F6: profikasa | G6: 46132 | H6: 0.56572917 | I6: 163000334 | J6: 12.4 | K6: =N6+O6+P6 -> 11.07 | L6: =Q6+R6 -> 1.33 | M6: =IF(J6=K6+L6,0,Y6) -> 0 | N6: 0 | O6: 11.07 | P6: 0 | Q6: 0 | R6: 1.33 | S6: 11.07 | T6: 12.4 | U6: 0 | V6: 0 | W6: 0 | X6: 0 | Y6: 0 | Z6: 0 | AA6: 0 | AB6: 12.4 | AD6: 0 | AE6: 0 | AF6: 0
A7: CZ60738677 | B7: RAPO BRNO, s.r.o. | C7: 96 | D7: BALADA - Březinky | E7: Pokladna SCO2 | F7: profikasa | G7: 46132 | H7: 0.59159722 | I7: 163000335 | J7: 22.9 | K7: =N7+O7+P7 -> 20.44 | L7: =Q7+R7 -> 2.46 | M7: =IF(J7=K7+L7,0,Y7) -> 0 | N7: 0 | O7: 20.44 | P7: 0 | Q7: 0 | R7: 2.46 | S7: 20.44 | T7: 22.9 | U7: 0 | V7: 0 | W7: 0 | X7: 0 | Y7: 0 | Z7: 0 | AA7: 0 | AB7: 22.9 | AD7: 0 | AE7: 0 | AF7: 0
A8: CZ60738677 | B8: RAPO BRNO, s.r.o. | C8: 96 | D8: BALADA - Březinky | E8: Pokladna SCO2 | F8: profikasa | G8: 46132 | H8: 0.59576389 | I8: 163000336 | J8: 24.9 | K8: =N8+O8+P8 -> 22.23 | L8: =Q8+R8 -> 2.67 | M8: =IF(J8=K8+L8,0,Y8) -> 0 | N8: 0 | O8: 22.23 | P8: 0 | Q8: 0 | R8: 2.67 | S8: 22.23 | T8: 24.9 | U8: 0 | V8: 0 | W8: 0 | X8: 0 | Y8: 0 | Z8: 0 | AA8: 0 | AB8: 24.9 | AD8: 0 | AE8: 0 | AF8: 0
A9: CZ60738677 | B9: RAPO BRNO, s.r.o. | C9: 96 | D9: BALADA - Březinky | E9: Pokladna SCO2 | F9: profikasa | G9: 46132 | H9: 0.59795139 | I9: 163000337 | J9: 162 | K9: =N9+O9+P9 -> 133.88 | L9: =Q9+R9 -> 28.12 | M9: =IF(J9=K9+L9,0,Y9) -> 0 | N9: 133.88 | O9: 0 | P9: 0 | Q9: 28.12 | R9: 0 | S9: 133.88 | T9: 162 | U9: 0 | V9: 0 | W9: 0 | X9: 0 | Y9: 0 | Z9: 0 | AA9: 0 | AB9: 162 | AD9: 0 | AE9: 0 | AF9: 0
A10: CZ60738677 | B10: RAPO BRNO, s.r.o. | C10: 96 | D10: BALADA - Březinky | E10: Pokladna SCO2 | F10: profikasa | G10: 46132 | H10: 0.60578704 | I10: 163000338 | J10: 27.9 | K10: =N10+O10+P10 -> 23.05 | L10: =Q10+R10 -> 4.85 | M10: =IF(J10=K10+L10,0,Y10) -> 0 | N10: 23.05 | O10: 0 | P10: 0 | Q10: 4.85 | R10: 0 | S10: 23.05 | T10: 27.9 | U10: 0 | V10: 0 | W10: 0 | X10: 0 | Y10: 0 | Z10: 0 | AA10: 0 | AB10: 27.9 | AD10: 0 | AE10: 0 | AF10: 0
A11: CZ60738677 | B11: RAPO BRNO, s.r.o. | C11: 96 | D11: BALADA - Březinky | E11: Pokladna SCO2 | F11: profikasa | G11: 46132 | H11: 0.60625 | I11: 163000339 | J11: 29.3 | K11: =N11+O11+P11 -> 25.4 | L11: =Q11+R11 -> 3.9 | M11: =IF(J11=K11+L11,0,Y11) -> 0 | N11: 9.42 | O11: 15.98 | P11: 0 | Q11: 1.98 | R11: 1.92 | S11: 25.4 | T11: 29.3 | U11: 0 | V11: 0 | W11: 0 | X11: 0 | Y11: 0 | Z11: 0 | AA11: 0 | AB11: 29.3 | AD11: 0 | AE11: 0 | AF11: 0
A12: CZ60738677 | B12: RAPO BRNO, s.r.o. | C12: 96 | D12: BALADA - Březinky | E12: Pokladna SCO2 | F12: profikasa | G12: 46132 | H12: 0.60913194 | I12: 163000340 | J12: 34.9 | K12: =N12+O12+P12 -> 31.16 | L12: =Q12+R12 -> 3.74 | M12: =IF(J12=K12+L12,0,Y12) -> 0 | N12: 0 | O12: 31.16 | P12: 0 | Q12: 0 | R12: 3.74 | S12: 31.16 | T12: 34.9 | U12: 0 | V12: 0 | W12: 0 | X12: 0 | Y12: 0 | Z12: 0 | AA12: 0 | AB12: 34.9 | AD12: 0 | AE12: 0 | AF12: 0
A13: CZ60738677 | B13: RAPO BRNO, s.r.o. | C13: 96 | D13: BALADA - Březinky | E13: Pokladna SCO2 | F13: profikasa | G13: 46132 | H13: 0.60954861 | I13: 163000341 | J13: 95.8 | K13: =N13+O13+P13 -> 85.53 | L13: =Q13+R13 -> 10.27 | M13: =IF(J13=K13+L13,0,Y13) -> 0 | N13: 0 | O13: 85.53 | P13: 0 | Q13: 0 | R13: 10.27 | S13: 85.53 | T13: 95.8 | U13: 0 | V13: 0 | W13: 0 | X13: 0 | Y13: 0 | Z13: 0 | AA13: 0 | AB13: 95.8 | AD13: 0 | AE13: 0 | AF13: 0
A14: CZ60738677 | B14: RAPO BRNO, s.r.o. | C14: 96 | D14: BALADA - Březinky | E14: Pokladna SCO2 | F14: profikasa | G14: 46132 | H14: 0.61166667 | I14: 163000342 | J14: 54.8 | K14: =N14+O14+P14 -> 48.91 | L14: =Q14+R14 -> 5.89 | M14: =IF(J14=K14+L14,0,Y14) -> 0 | N14: 0 | O14: 48.91 | P14: 0 | Q14: 0 | R14: 5.89 | S14: 48.91 | T14: 54.8 | U14: 0 | V14: 0 | W14: 0 | X14: 0 | Y14: 0 | Z14: 0 | AA14: 0 | AB14: 54.8 | AD14: 0 | AE14: 0 | AF14: 0
A15: CZ60738677 | B15: RAPO BRNO, s.r.o. | C15: 96 | D15: BALADA - Březinky | E15: Pokladna SCO2 | F15: profikasa | G15: 46132 | H15: 0.62326389 | I15: 163000343 | J15: 93 | K15: =N15+O15+P15 -> 83.01 | L15: =Q15+R15 -> 9.99 | M15: =IF(J15=K15+L15,0,Y15) -> 0 | N15: 0 | O15: 83.01 | P15: 0 | Q15: 0 | R15: 9.99 | S15: 83.01 | T15: 93 | U15: 0 | V15: 0 | W15: 0 | X15: 0 | Y15: 0 | Z15: 0 | AA15: 0 | AB15: 93 | AD15: 0 | AE15: 0 | AF15: 0
A16: CZ60738677 | B16: RAPO BRNO, s.r.o. | C16: 96 | D16: BALADA - Březinky | E16: Pokladna SCO2 | F16: profikasa | G16: 46132 | H16: 0.62793981 | I16: 163000344 | J16: 31.8 | K16: =N16+O16+P16 -> 26.28 | L16: =Q16+R16 -> 5.52 | M16: =IF(J16=K16+L16,0,Y16) -> 0 | N16: 26.28 | O16: 0 | P16: 0 | Q16: 5.52 | R16: 0 | S16: 26.28 | T16: 31.8 | U16: 0 | V16: 0 | W16: 0 | X16: 0 | Y16: 0 | Z16: 0 | AA16: 0 | AB16: 31.8 | AD16: 0 | AE16: 0 | AF16: 0
... A28: CZ60738677 | B28: RAPO BRNO, s.r.o. | C28: 96 | D28: BALADA - Březinky | E28: Pokladna 1 | F28: Teclová | G28: 46132 | H28: 0.42050926 | I28: 166004612 | J28: 39 | K28: =N28+O28+P28 -> 34.625 | L28: =Q28+R28 -> 4.155 | M28: =IF(J28=K28+L28,0,Y28) -> 0.22 | N28: 0 | O28: 34.625 | P28: 0 | Q28: 0 | R28: 4.155 | S28: 34.625 | T28: 38.78 | U28: 0 | V28: 0 | W28: 0 | X28: 0 | Y28: 0.22 | Z28: 200 | AA28: 0 | AB28: 0 | AD28: 0 | AE28: -161 | AF28: 0
A29: CZ60738677 | B29: RAPO BRNO, s.r.o. | C29: 96 | D29: BALADA - Březinky | E29: Pokladna 1 | F29: Teclová | G29: 46132 | H29: 0.42090278 | I29: 166004613 | J29: 22.9 | K29: =N29+O29+P29 -> 18.9256 | L29: =Q29+R29 -> 3.9744 | M29: =IF(J29=K29+L29,0,Y29) -> 0 | N29: 18.9256 | O29: 0 | P29: 0 | Q29: 3.9744 | R29: 0 | S29: 18.9256 | T29: 22.9 | U29: 0 | V29: 0 | W29: 0 | X29: 0 | Y29: 0 | Z29: 0 | AA29: 0 | AB29: 22.9 | AC29: 0 | AD29: 0 | AE29: 0 | AF29: 0
A30: CZ60738677 | B30: RAPO BRNO, s.r.o. | C30: 96 | D30: BALADA - Březinky | E30: Pokladna 1 | F30: Teclová | G30: 46132 | H30: 0.42236111 | I30: 166004614 | J30: 39 | K30: =N30+O30+P30 -> 34.7232 | L30: =Q30+R30 -> 4.1668 | M30: =IF(J30=K30+L30,0,Y30) -> 0.11 | N30: 0 | O30: 34.7232 | P30: 0 | Q30: 0 | R30: 4.1668 | S30: 34.7232 | T30: 38.89 | U30: 0 | V30: 0 | W30: 0 | X30: 0 | Y30: 0.11 | Z30: 39 | AA30: 0 | AB30: 0 | AD30: 0 | AE30: 0 | AF30: 0
A31: CZ60738677 | B31: RAPO BRNO, s.r.o. | C31: 96 | D31: BALADA - Březinky | E31: Pokladna 1 | F31: Teclová | G31: 46132 | H31: 0.42359954 | I31: 166004615 | J31: 473.68 | K31: =N31+O31+P31 -> 422.9289 | L31: =Q31+R31 -> 50.7511 | M31: =IF(J31=K31+L31,0,Y31) -> 0 | N31: 0 | O31: 422.9289 | P31: 0 | Q31: 0 | R31: 50.7511 | S31: 422.9289 | T31: 473.68 | U31: 0 | V31: 0 | W31: 0 | X31: 0 | Y31: 0 | Z31: 0 | AA31: 0 | AB31: 473.68 | AC31: 0 | AD31: 0 | AE31: 0 | AF31: 0
A32: CZ60738677 | B32: RAPO BRNO, s.r.o. | C32: 96 | D32: BALADA - Březinky | E32: Pokladna 1 | F32: Teclová | G32: 46132 | H32: 0.42488426 | I32: 166004616 | J32: 121 | K32: =N32+O32+P32 -> 104.5868 | L32: =Q32+R32 -> 16.1132 | M32: =IF(J32=K32+L32,0,Y32) -> 0.3 | N32: 39.5868 | O32: 65 | P32: 0 | Q32: 8.3132 | R32: 7.8 | S32: 104.5868 | T32: 120.7 | U32: 0 | V32: 0 | W32: 0 | X32: 0 | Y32: 0.3 | Z32: 200 | AA32: 0 | AB32: 0 | AD32: 0 | AE32: -79 | AF32: 0
A33: CZ60738677 | B33: RAPO BRNO, s.r.o. | C33: 96 | D33: BALADA - Březinky | E33: Pokladna 1 | F33: Teclová | G33: 46132 | H33: 0.42532407 | I33: 166004617 | J33: 43 | K33: =N33+O33+P33 -> 38.3929 | L33: =Q33+R33 -> 4.6071 | M33: =IF(J33=K33+L33,0,Y33) -> 0 | N33: 0 | O33: 38.3929 | P33: 0 | Q33: 0 | R33: 4.6071 | S33: 38.3929 | T33: 43 | U33: 0 | V33: 0 | W33: 0 | X33: 0 | Y33: 0 | Z33: 0 | AA33: 0 | AB33: 43 | AC33: 0 | AD33: 0 | AE33: 0 | AF33: 0
A34: CZ60738677 | B34: RAPO BRNO, s.r.o. | C34: 96 | D34: BALADA - Březinky | E34: Pokladna 1 | F34: Teclová | G34: 46132 | H34: 0.42546296 | I34: 166004618 | J34: 48 | K34: =N34+O34+P34 -> 42.6786 | L34: =Q34+R34 -> 5.1214 | M34: =IF(J34=K34+L34,0,Y34) -> 0.2 | N34: 0 | O34: 42.6786 | P34: 0 | Q34: 0 | R34: 5.1214 | S34: 42.6786 | T34: 47.8 | U34: 0 | V34: 0 | W34: 0 | X34: 0 | Y34: 0.2 | Z34: 50 | AA34: 0 | AB34: 0 | AD34: 0 | AE34: -2 | AF34: 0
A35: CZ60738677 | B35: RAPO BRNO, s.r.o. | C35: 96 | D35: BALADA - Březinky | E35: Pokladna 1 | F35: Teclová | G35: 46132 | H35: 0.42611111 | I35: 166004619 | J35: 226.9 | K35: =N35+O35+P35 -> 202.5895 | L35: =Q35+R35 -> 24.3105 | M35: =IF(J35=K35+L35,0,Y35) -> 0 | N35: 0 | O35: 202.5895 | P35: 0 | Q35: 0 | R35: 24.3105 | S35: 202.5895 | T35: 226.9 | U35: 0 | V35: 0 | W35: 0 | X35: 0 | Y35: 0 | Z35: 0 | AA35: 0 | AB35: 226.9 | AC35: 0 | AD35: 0 | AE35: 0 | AF35: 0
A36: CZ60738677 | B36: RAPO BRNO, s.r.o. | C36: 96 | D36: BALADA - Březinky | E36: Pokladna 1 | F36: Teclová | G36: 46132 | H36: 0.4262037 | I36: 166004620 | J36: 68 | K36: =N36+O36+P36 -> 60.3482 | L36: =Q36+R36 -> 7.2418 | M36: =IF(J36=K36+L36,0,Y36) -> 0.41 | N36: 0 | O36: 60.3482 | P36: 0 | Q36: 0 | R36: 7.2418 | S36: 60.3482 | T36: 67.59 | U36: 0 | V36: 0 | W36: 0 | X36: 0 | Y36: 0.41 | Z36: 100 | AA36: 0 | AB36: 0 | AD36: 0 | AE36: -32 | AF36: 0
A37: CZ60738677 | B37: RAPO BRNO, s.r.o. | C37: 96 | D37: BALADA - Březinky | E37: Pokladna 1 | F37: Teclová | G37: 46132 | H37: 0.42648148 | I37: 166004621 | J37: 92 | K37: =N37+O37+P37 -> 79.1817 | L37: =Q37+R37 -> 12.6183 | M37: =IF(J37=K37+L37,0,Y37) -> 0.2 | N37: 34.6281 | O37: 44.5536 | P37: 0 | Q37: 7.2719 | R37: 5.3464 | S37: 79.1817 | T37: 91.8 | U37: 0 | V37: 0 | W37: 0 | X37: 0 | Y37: 0.2 | Z37: 102 | AA37: 0 | AB37: 0 | AD37: 0 | AE37: -10 | AF37: 0
A38: CZ60738677 | B38: RAPO BRNO, s.r.o. | C38: 96 | D38: BALADA - Březinky | E38: Pokladna 1 | F38: Teclová | G38: 46132 | H38: 0.43123843 | I38: 166004622 | J38: 53.8 | K38: =N38+O38+P38 -> 46.7142 | L38: =Q38+R38 -> 7.0858 | M38: =IF(J38=K38+L38,0,Y38) -> 0 | N38: 16.4463 | O38: 30.2679 | P38: 0 | Q38: 3.4537 | R38: 3.6321 | S38: 46.7142 | T38: 53.8 | U38: 0 | V38: 0 | W38: 0 | X38: 0 | Y38: 0 | Z38: 0 | AA38: 0 | AB38: 53.8 | AC38: 0 | AD38: 0 | AE38: 0 | AF38: 0
A39: CZ60738677 | B39: RAPO BRNO, s.r.o. | C39: 96 | D39: BALADA - Březinky | E39: Pokladna 1 | F39: Teclová | G39: 46132 | H39: 0.43149306 | I39: 166004623 | J39: 19.9 | K39: =N39+O39+P39 -> 16.4463 | L39: =Q39+R39 -> 3.4537 | M39: =IF(J39=K39+L39,0,Y39) -> 0 | N39: 16.4463 | O39: 0 | P39: 0 | Q39: 3.4537 | R39: 0 | S39: 16.4463 | T39: 19.9 | U39: 0 | V39: 0 | W39: 0 | X39: 0 | Y39: 0 | Z39: 0 | AA39: 0 | AB39: 19.9 | AC39: 0 | AD39: 0 | AE39: 0 | AF39: 0
A40: CZ60738677 | B40: RAPO BRNO, s.r.o. | C40: 96 | D40: BALADA - Březinky | E40: Pokladna 1 | F40: Teclová | G40: 46132 | H40: 0.4322338 | I40: 166004624 | J40: 88 | K40: =N40+O40+P40 -> 78.875 | L40: =Q40+R40 -> 9.465 | M40: =IF(J40=K40+L40,0,Y40) -> -0.34 | N40: 0 | O40: 78.875 | P40: 0 | Q40: 0 | R40: 9.465 | S40: 78.875 | T40: 88.34 | U40: 0 | V40: 0 | W40: 0 | X40: 0 | Y40: -0.34 | Z40: 200 | AA40: 0 | AB40: 0 | AD40: 0 | AE40: -112 | AF40: 0
A41: CZ60738677 | B41: RAPO BRNO, s.r.o. | C41: 96 | D41: BALADA - Březinky | E41: Pokladna 1 | F41: Teclová | G41: 46132 | H41: 0.43269676 | I41: 166004625 | J41: 75 | K41: =N41+O41+P41 -> 66.4318 | L41: =Q41+R41 -> 8.7082 | M41: =IF(J41=K41+L41,0,Y41) -> -0.14 | N41: 8.1818 | O41: 58.25 | P41: 0 | Q41: 1.7182 | R41: 6.99 | S41: 66.4318 | T41: 75.14 | U41: 0 | V41: 0 | W41: 0 | X41: 0 | Y41: -0.14 | Z41: 75 | AA41: 0 | AB41: 0 | AD41: 0 | AE41: 0 | AF41: 0
A42: CZ60738677 | B42: RAPO BRNO, s.r.o. | C42: 96 | D42: BALADA - Březinky | E42: Pokladna 1 | F42: Teclová | G42: 46132 | H42: 0.43283565 | I42: 166004626 | J42: 38 | K42: =N42+O42+P42 -> 33.8393 | L42: =Q42+R42 -> 4.0607 | M42: =IF(J42=K42+L42,0,Y42) -> 0.1 | N42: 0 | O42: 33.8393 | P42: 0 | Q42: 0 | R42: 4.0607 | S42: 33.8393 | T42: 37.9 | U42: 0 | V42: 0 | W42: 0 | X42: 0 | Y42: 0.1 | Z42: 50 | AA42: 0 | AB42: 0 | AD42: 0 | AE42: -12 | AF42: 0
A43: CZ60738677 | B43: RAPO BRNO, s.r.o. | C43: 96 | D43: BALADA - Březinky | E43: Pokladna 1 | F43: Teclová | G43: 46132 | H43: 0.43332176 | I43: 166004627 | J43: 254 | K43: =N43+O43+P43 -> 220.0454 | L43: =Q43+R43 -> 33.6646 | M43: =IF(J43=K43+L43,0,Y43) -> 0.29 | N43: 80.6613 | O43: 139.3841 | P43: 0 | Q43: 16.9387 | R43: 16.7259 | S43: 220.0454 | T43: 253.71 | U43: 0 | V43: 0 | W43: 0 | X43: 0 | Y43: 0.29 | Z43: 500 | AA43: 0 | AB43: 0 | AD43: 0 | AE43: -246 | AF43: 0
A44: CZ60738677 | B44: RAPO BRNO, s.r.o. | C44: 96 | D44: BALADA - Březinky | E44: Pokladna 1 | F44: Teclová | G44: 46132 | H44: 0.43450231 | I44: 166004628 | J44: 181 | K44: =N44+O44+P44 -> 161.9285 | L44: =Q44+R44 -> 19.4315 | M44: =IF(J44=K44+L44,0,Y44) -> -0.36 | N44: 0 | O44: 161.9285 | P44: 0 | Q44: 0 | R44: 19.4315 | S44: 161.9285 | T44: 181.36 | U44: 0 | V44: 0 | W44: 0 | X44: 0 | Y44: -0.36 | Z44: 200 | AA44: 0 | AB44: 0 | AD44: 0 | AE44: -19 | AF44: 0
A45: CZ60738677 | B45: RAPO BRNO, s.r.o. | C45: 96 | D45: BALADA - Březinky | E45: Pokladna 1 | F45: Teclová | G45: 46132 | H45: 0.43509259 | I45: 166004629 | J45: 222.3 | K45: =N45+O45+P45 -> 190.8516 | L45: =Q45+R45 -> 31.4484 | M45: =IF(J45=K45+L45,0,Y45) -> 0 | N45: 94.9587 | O45: 95.8929 | P45: 0 | Q45: 19.9413 | R45: 11.5071 | S45: 190.8516 | T45: 222.3 | U45: 0 | V45: 0 | W45: 0 | X45: 0 | Y45: 0 | Z45: 0 | AA45: 0 | AB45: 222.3 | AC45: 0 | AD45: 0 | AE45: 0 | AF45: 0
A46: CZ60738677 | B46: RAPO BRNO, s.r.o. | C46: 96 | D46: BALADA - Březinky | E46: Pokladna 1 | F46: Teclová | G46: 46132 | H46: 0.43631944 | I46: 166004630 | J46: 352.94 | K46: =N46+O46+P46 -> 315.1253 | L46: =Q46+R46 -> 37.8147 | M46: =IF(J46=K46+L46,0,Y46) -> 0 | N46: 0 | O46: 315.1253 | P46: 0 | Q46: 0 | R46: 37.8147 | S46: 315.1253 | T46: 352.94 | U46: 0 | V46: 0 | W46: 0 | X46: 0 | Y46: 0 | Z46: 0 | AA46: 0 | AB46: 352.94 | AC46: 0 | AD46: 0 | AE46: 0 | AF46: 0
A47: CZ60738677 | B47: RAPO BRNO, s.r.o. | C47: 96 | D47: BALADA - Březinky | E47: Pokladna 1 | F47: Teclová | G47: 46132 | H47: 0.43739583 | I47: 166004631 | J47: 255.55 | K47: =N47+O47+P47 -> 223.7338 | L47: =Q47+R47 -> 31.8162 | M47: =IF(J47=K47+L47,0,Y47) -> 0 | N47: 55.2066 | O47: 168.5272 | P47: 0 | Q47: 11.5934 | R47: 20.2228 | S47: 223.7338 | T47: 255.55 | U47: 0 | V47: 0 | W47: 0 | X47: 0 | Y47: 0 | Z47: 0 | AA47: 0 | AB47: 255.55 | AC47: 0 | AD47: 0 | AE47: 0 | AF47: 8.7431
A48: CZ60738677 | B48: RAPO BRNO, s.r.o. | C48: 96 | D48: BALADA - Březinky | E48: Pokladna 1 | F48: Teclová | G48: 46132 | H48: 0.43763889 | I48: 166004632 | J48: 21.9 | K48: =N48+O48+P48 -> 19.5536 | L48: =Q48+R48 -> 2.3464 | M48: =IF(J48=K48+L48,0,Y48) -> 0 | N48: 0 | O48: 19.5536 | P48: 0 | Q48: 0 | R48: 2.3464 | S48: 19.5536 | T48: 21.9 | U48: 0 | V48: 0 | W48: 0 | X48: 0 | Y48: 0 | Z48: 0 | AA48: 0 | AB48: 21.9 | AC48: 0 | AD48: 0 | AE48: 0 | AF48: 0
A49: CZ60738677 | B49: RAPO BRNO, s.r.o. | C49: 96 | D49: BALADA - Březinky | E49: Pokladna 1 | F49: Teclová | G49: 46132 | H49: 0.43792824 | I49: 166004633 | J49: 161 | K49: =N49+O49+P49 -> 133.0579 | L49: =Q49+R49 -> 27.9421 | M49: =IF(J49=K49+L49,0,Y49) -> 0 | N49: 133.0579 | O49: 0 | P49: 0 | Q49: 27.9421 | R49: 0 | S49: 133.0579 | T49: 161 | U49: 0 | V49: 0 | W49: 0 | X49: 0 | Y49: 0 | Z49: 0 | AA49: 0 | AB49: 161 | AC49: 0 | AD49: 0 | AE49: 0 | AF49: 0
A50: CZ60738677 | B50: RAPO BRNO, s.r.o. | C50: 96 | D50: BALADA - Březinky | E50: Pokladna 1 | F50: Teclová | G50: 46132 | H50: 0.43881944 | I50: 166004634 | J50: 421 | K50: =N50+O50+P50 -> 376.2768 | L50: =Q50+R50 -> 45.1532 | M50: =IF(J50=K50+L50,0,Y50) -> -0.43 | N50: 0 | O50: 376.2768 | P50: 0 | Q50: 0 | R50: 45.1532 | S50: 376.2768 | T50: 421.43 | U50: 0 | V50: 0 | W50: 0 | X50: 0 | Y50: -0.43 | Z50: 421 | AA50: 0 | AB50: 0 | AD50: 0 | AE50: 0 | AF50: 0
A51: CZ60738677 | B51: RAPO BRNO, s.r.o. | C51: 96 | D51: BALADA - Březinky | E51: Pokladna 1 | F51: Teclová | G51: 46132 | H51: 0.43925926 | I51: 166004635 | J51: 80.21 | K51: =N51+O51+P51 -> 71.6161 | L51: =Q51+R51 -> 8.5939 | M51: =IF(J51=K51+L51,0,Y51) -> 0 | N51: 0 | O51: 71.6161 | P51: 0 | Q51: 0 | R51: 8.5939 | S51: 71.6161 | T51: 80.21 | U51: 0 | V51: 0 | W51: 0 | X51: 0 | Y51: 0 | Z51: 0 | AA51: 0 | AB51: 80.21 | AC51: 0 | AD51: 0 | AE51: 0 | AF51: 13.974
A52: CZ60738677 | B52: RAPO BRNO, s.r.o. | C52: 96 | D52: BALADA - Březinky | E52: Pokladna 1 | F52: Teclová | G52: 46132 | H52: 0.43960648 | I52: 166004636 | J52: 43 | K52: =N52+O52+P52 -> 37.9732 | L52: =Q52+R52 -> 4.5568 | M52: =IF(J52=K52+L52,0,Y52) -> 0.47 | N52: 0 | O52: 37.9732 | P52: 0 | Q52: 0 | R52: 4.5568 | S52: 37.9732 | T52: 42.53 | U52: 0 | V52: 0 | W52: 0 | X52: 0 | Y52: 0.47 | Z52: 103 | AA52: 0 | AB52: 0 | AD52: 0 | AE52: -60 | AF52: 7.1267
A53: CZ60738677 | B53: RAPO BRNO, s.r.o. | C53: 96 | D53: BALADA - Březinky | E53: Pokladna 1 | F53: Teclová | G53: 46132 | H53: 0.44049769 | I53: 166004637 | J53: 42.8 | K53: =N53+O53+P53 -> 36.5606 | L53: =Q53+R53 -> 6.2394 | M53: =IF(J53=K53+L53,0,Y53) -> 0 | N53: 20.5785 | O53: 15.9821 | P53: 0 | Q53: 4.3215 | R53: 1.9179 | S53: 36.5606 | T53: 42.8 | U53: 0 | V53: 0 | W53: 0 | X53: 0 | Y53: 0 | Z53: 0 | AA53: 0 | AB53: 42.8 | AC53: 0 | AD53: 0 | AE53: 0 | AF53: 0
A54: CZ60738677 | B54: RAPO BRNO, s.r.o. | C54: 96 | D54: BALADA - Březinky | E54: Pokladna 1 | F54: Teclová | G54: 46132 | H54: 0.44150463 | I54: 166004638 | J54: 179 | K54: =N54+O54+P54 -> 157.9774 | L54: =Q54+R54 -> 21.3226 | M54: =IF(J54=K54+L54,0,Y54) -> -0.3 | N54: 26.281 | O54: 131.6964 | P54: 0 | Q54: 5.519 | R54: 15.8036 | S54: 157.9774 | T54: 179.3 | U54: 0 | V54: 0 | W54: 0 | X54: 0 | Y54: -0.3 | Z54: 200 | AA54: 0 | AB54: 0 | AD54: 0 | AE54: -21 | AF54: 0
A55: CZ60738677 | B55: RAPO BRNO, s.r.o. | C55: 96 | D55: BALADA - Březinky | E55: Pokladna 1 | F55: Teclová | G55: 46132 | H55: 0.44228009 | I55: 166004639 | J55: 93.8 | K55: =N55+O55+P55 -> 77.5207 | L55: =Q55+R55 -> 16.2793 | M55: =IF(J55=K55+L55,0,Y55) -> 0 | N55: 77.5207 | O55: 0 | P55: 0 | Q55: 16.2793 | R55: 0 | S55: 77.5207 | T55: 93.8 | U55: 0 | V55: 0 | W55: 0 | X55: 0 | Y55: 0 | Z55: 0 | AA55: 0 | AB55: 93.8 | AC55: 0 | AD55: 0 | AE55: 0 | AF55: 0
A56: CZ60738677 | B56: RAPO BRNO, s.r.o. | C56: 96 | D56: BALADA - Březinky | E56: Pokladna 1 | F56: Teclová | G56: 46132 | H56: 0.44289352 | I56: 166004640 | J56: 134.5 | K56: =N56+O56+P56 -> 119.9634 | L56: =Q56+R56 -> 14.5366 | M56: =IF(J56=K56+L56,0,Y56) -> 0 | N56: 1.5702 | O56: 118.3932 | P56: 0 | Q56: 0.3298 | R56: 14.2068 | S56: 119.9634 | T56: 134.5 | U56: 0 | V56: 0 | W56: 0 | X56: 0 | Y56: 0 | Z56: 0 | AA56: 0 | AB56: 134.5 | AC56: 0 | AD56: 0 | AE56: 0 | AF56: 0
A57: CZ60738677 | B57: RAPO BRNO, s.r.o. | C57: 96 | D57: BALADA - Březinky | E57: Pokladna 1 | F57: Teclová | G57: 46132 | H57: 0.4434375 | I57: 166004641 | J57: 275 | K57: =N57+O57+P57 -> 245.3122 | L57: =Q57+R57 -> 29.4378 | M57: =IF(J57=K57+L57,0,Y57) -> 0.25 | N57: 0 | O57: 245.3122 | P57: 0 | Q57: 0 | R57: 29.4378 | S57: 245.3122 | T57: 274.75 | U57: 0 | V57: 0 | W57: 0 | X57: 0 | Y57: 0.25 | Z57: 275 | AA57: 0 | AB57: 0 | AD57: 0 | AE57: 0 | AF57: 0
A58: CZ60738677 | B58: RAPO BRNO, s.r.o. | C58: 96 | D58: BALADA - Březinky | E58: Pokladna 1 | F58: Teclová | G58: 46132 | H58: 0.44439815 | I58: 166004642 | J58: 255.01 | K58: =N58+O58+P58 -> 225.1705 | L58: =Q58+R58 -> 29.8395 | M58: =IF(J58=K58+L58,0,Y58) -> 0 | N58: 31.3223 | O58: 193.8482 | P58: 0 | Q58: 6.5777 | R58: 23.2618 | S58: 225.1705 | T58: 255.01 | U58: 0 | V58: 0 | W58: 0 | X58: 0 | Y58: 0 | Z58: 0 | AA58: 0 | AB58: 255.01 | AC58: 0 | AD58: 0 | AE58: 0 | AF58: 0
A59: CZ60738677 | B59: RAPO BRNO, s.r.o. | C59: 96 | D59: BALADA - Březinky | E59: Pokladna 1 | F59: Teclová | G59: 46132 | H59: 0.44476852 | I59: 166004643 | J59: 212.5 | K59: =N59+O59+P59 -> 180.1226 | L59: =Q59+R59 -> 32.3774 | M59: =IF(J59=K59+L59,0,Y59) -> 0 | N59: 119.5868 | O59: 60.5358 | P59: 0 | Q59: 25.1132 | R59: 7.2642 | S59: 180.1226 | T59: 212.5 | U59: 0 | V59: 0 | W59: 0 | X59: 0 | Y59: 0 | Z59: 0 | AA59: 0 | AB59: 212.5 | AC59: 0 | AD59: 0 | AE59: 0 | AF59: 0
A60: CZ60738677 | B60: RAPO BRNO, s.r.o. | C60: 96 | D60: BALADA - Březinky | E60: Pokladna 1 | F60: Teclová | G60: 46132 | H60: 0.445 | I60: 166004644 | J60: 62 | K60: =N60+O60+P60 -> 55.1786 | L60: =Q60+R60 -> 6.6214 | M60: =IF(J60=K60+L60,0,Y60) -> 0.2 | N60: 0 | O60: 55.1786 | P60: 0 | Q60: 0 | R60: 6.6214 | S60: 55.1786 | T60: 61.8 | U60: 0 | V60: 0 | W60: 0 | X60: 0 | Y60: 0.2 | Z60: 62 | AA60: 0 | AB60: 0 | AD60: 0 | AE60: 0 | AF60: 0
A61: CZ60738677 | B61: RAPO BRNO, s.r.o. | C61: 96 | D61: BALADA - Březinky | E61: Pokladna 1 | F61: Teclová | G61: 46132 | H61: 0.4456713 | I61: 166004645 | J61: 226 | K61: =N61+O61+P61 -> 191.0936 | L61: =Q61+R61 -> 34.9064 | M61: =IF(J61=K61+L61,0,Y61) -> 0 | N61: 133.0579 | O61: 58.0357 | P61: 0 | Q61: 27.9421 | R61: 6.9643 | S61: 191.0936 | T61: 226 | U61: 0 | V61: 0 | W61: 0 | X61: 0 | Y61: 0 | Z61: 0 | AA61: 0 | AB61: 226 | AC61: 0 | AD61: 0 | AE61: 0 | AF61: 0
A62: CZ60738677 | B62: RAPO BRNO, s.r.o. | C62: 96 | D62: BALADA - Březinky | E62: Pokladna 1 | F62: Teclová | G62: 46132 | H62: 0.44590278 | I62: 166004646 | J62: 24 | K62: =N62+O62+P62 -> 21.4196 | L62: =Q62+R62 -> 2.5704 | M62: =IF(J62=K62+L62,0,Y62) -> 0.01 | N62: 0 | O62: 21.4196 | P62: 0 | Q62: 0 | R62: 2.5704 | S62: 21.4196 | T62: 23.99 | U62: 0 | V62: 0 | W62: 0 | X62: 0 | Y62: 0.01 | Z62: 204 | AA62: 0 | AB62: 0 | AD62: 0 | AE62: -180 | AF62: 0
A63: CZ60738677 | B63: RAPO BRNO, s.r.o. | C63: 96 | D63: BALADA - Březinky | E63: Pokladna 1 | F63: Teclová | G63: 46132 | H63: 0.44640046 | I63: 166004647 | J63: 174.56 | K63: =N63+O63+P63 -> 155.8572 | L63: =Q63+R63 -> 18.7028 | M63: =IF(J63=K63+L63,0,Y63) -> 0 | N63: 0 | O63: 155.8572 | P63: 0 | Q63: 0 | R63: 18.7028 | S63: 155.8572 | T63: 174.56 | U63: 0 | V63: 0 | W63: 0 | X63: 0 | Y63: 0 | Z63: 0 | AA63: 0 | AB63: 174.56 | AC63: 0 | AD63: 0 | AE63: 0 | AF63: 0
A64: CZ60738677 | B64: RAPO BRNO, s.r.o. | C64: 96 | D64: BALADA - Březinky | E64: Pokladna 1 | F64: Teclová | G64: 46132 | H64: 0.44670139 | I64: 166004648 | J64: 228 | K64: =N64+O64+P64 -> 203.8393 | L64: =Q64+R64 -> 24.4607 | M64: =IF(J64=K64+L64,0,Y64) -> -0.3 | N64: 0 | O64: 203.8393 | P64: 0 | Q64: 0 | R64: 24.4607 | S64: 203.8393 | T64: 228.3 | U64: 0 | V64: 0 | W64: 0 | X64: 0 | Y64: -0.3 | Z64: 1000 | AA64: 0 | AB64: 0 | AD64: 0 | AE64: -772 | AF64: 0
A65: CZ60738677 | B65: RAPO BRNO, s.r.o. | C65: 96 | D65: BALADA - Březinky | E65: Pokladna 1 | F65: Teclová | G65: 46132 | H65: 0.44849537 | I65: 166004649 | J65: 162 | K65: =N65+O65+P65 -> 133.8843 | L65: =Q65+R65 -> 28.1157 | M65: =IF(J65=K65+L65,0,Y65) -> 0 | N65: 133.8843 | O65: 0 | P65: 0 | Q65: 28.1157 | R65: 0 | S65: 133.8843 | T65: 162 | U65: 0 | V65: 0 | W65: 0 | X65: 0 | Y65: 0 | Z65: 162 | AA65: 0 | AB65: 0 | AD65: 0 | AE65: 0 | AF65: 0
A66: CZ60738677 | B66: RAPO BRNO, s.r.o. | C66: 96 | D66: BALADA - Březinky | E66: Pokladna 1 | F66: Teclová | G66: 46132 | H66: 0.44871528 | I66: 166004650 | J66: 42 | K66: =N66+O66+P66 -> 37.3214 | L66: =Q66+R66 -> 4.4786 | M66: =IF(J66=K66+L66,0,Y66) -> 0.2 | N66: 0 | O66: 37.3214 | P66: 0 | Q66: 0 | R66: 4.4786 | S66: 37.3214 | T66: 41.8 | U66: 0 | V66: 0 | W66: 0 | X66: 0 | Y66: 0.2 | Z66: 50 | AA66: 0 | AB66: 0 | AD66: 0 | AE66: -8 | AF66: 0
A67: CZ60738677 | B67: RAPO BRNO, s.r.o. | C67: 96 | D67: BALADA - Březinky | E67: Pokladna 1 | F67: Teclová | G67: 46132 | H67: 0.45081019 | I67: 166004651 | J67: 245.21 | K67: =N67+O67+P67 -> 218.9375 | L67: =Q67+R67 -> 26.2725 | M67: =IF(J67=K67+L67,0,Y67) -> 0 | N67: 0 | O67: 218.9375 | P67: 0 | Q67: 0 | R67: 26.2725 | S67: 218.9375 | T67: 245.21 | U67: 0 | V67: 0 | W67: 0 | X67: 0 | Y67: 0 | Z67: 0 | AA67: 0 | AB67: 245.21 | AC67: 0 | AD67: 0 | AE67: 0 | AF67: 0
A68: CZ60738677 | B68: RAPO BRNO, s.r.o. | C68: 96 | D68: BALADA - Březinky | E68: Pokladna 1 | F68: Teclová | G68: 46132 | H68: 0.45100694 | I68: 166004652 | J68: 48 | K68: =N68+O68+P68 -> 42.5894 | L68: =Q68+R68 -> 5.1106 | M68: =IF(J68=K68+L68,0,Y68) -> 0.3 | N68: 0 | O68: 42.5894 | P68: 0 | Q68: 0 | R68: 5.1106 | S68: 42.5894 | T68: 47.7 | U68: 0 | V68: 0 | W68: 0 | X68: 0 | Y68: 0.3 | Z68: 200 | AA68: 0 | AB68: 0 | AD68: 0 | AE68: -152 | AF68: 0
A69: CZ60738677 | B69: RAPO BRNO, s.r.o. | C69: 96 | D69: BALADA - Březinky | E69: Pokladna 1 | F69: Teclová | G69: 46132 | H69: 0.45144676 | I69: 166004653 | J69: 111 | K69: =N69+O69+P69 -> 95.5254 | L69: =Q69+R69 -> 15.1746 | M69: =IF(J69=K69+L69,0,Y69) -> 0.3 | N69: 41.2397 | O69: 54.2857 | P69: 0 | Q69: 8.6603 | R69: 6.5143 | S69: 95.5254 | T69: 110.7 | U69: 0 | V69: 0 | W69: 0 | X69: 0 | Y69: 0.3 | Z69: 121 | AA69: 0 | AB69: 0 | AD69: 0 | AE69: -10 | AF69: 0
A70: CZ60738677 | B70: RAPO BRNO, s.r.o. | C70: 96 | D70: BALADA - Březinky | E70: Pokladna 1 | F70: Teclová | G70: 46132 | H70: 0.45199074 | I70: 166004654 | J70: 105 | K70: =N70+O70+P70 -> 94.0356 | L70: =Q70+R70 -> 11.2844 | M70: =IF(J70=K70+L70,0,Y70) -> -0.32 | N70: 0 | O70: 94.0356 | P70: 0 | Q70: 0 | R70: 11.2844 | S70: 94.0356 | T70: 105.32 | U70: 0 | V70: 0 | W70: 0 | X70: 0 | Y70: -0.32 | Z70: 105 | AA70: 0 | AB70: 0 | AD70: 0 | AE70: 0 | AF70: 23.8794
A71: CZ60738677 | B71: RAPO BRNO, s.r.o. | C71: 96 | D71: BALADA - Březinky | E71: Pokladna 1 | F71: Teclová | G71: 46132 | H71: 0.45233796 | I71: 166004655 | J71: 33.97 | K71: =N71+O71+P71 -> 30.3304 | L71: =Q71+R71 -> 3.6396 | M71: =IF(J71=K71+L71,0,Y71) -> 0 | N71: 0 | O71: 30.3304 | P71: 0 | Q71: 0 | R71: 3.6396 | S71: 30.3304 | T71: 33.97 | U71: 0 | V71: 0 | W71: 0 | X71: 0 | Y71: 0 | Z71: 0 | AA71: 0 | AB71: 33.97 | AC71: 0 | AD71: 0 | AE71: 0 | AF71: 0
A72: CZ60738677 | B72: RAPO BRNO, s.r.o. | C72: 96 | D72: BALADA - Březinky | E72: Pokladna 1 | F72: Teclová | G72: 46132 | H72: 0.45262731 | I72: 166004656 | J72: 38.8 | K72: =N72+O72+P72 -> 33.5869 | L72: =Q72+R72 -> 5.2131 | M72: =IF(J72=K72+L72,0,Y72) -> 0 | N72: 13.1405 | O72: 20.4464 | P72: 0 | Q72: 2.7595 | R72: 2.4536 | S72: 33.5869 | T72: 38.8 | U72: 0 | V72: 0 | W72: 0 | X72: 0 | Y72: 0 | Z72: 0 | AA72: 0 | AB72: 38.8 | AC72: 0 | AD72: 0 | AE72: 0 | AF72: 0
A73: CZ60738677 | B73: RAPO BRNO, s.r.o. | C73: 96 | D73: BALADA - Březinky | E73: Pokladna 1 | F73: Teclová | G73: 46132 | H73: 0.45646991 | I73: 166004657 | J73: 232.3 | K73: =N73+O73+P73 -> 206.5274 | L73: =Q73+R73 -> 25.7726 | M73: =IF(J73=K73+L73,0,Y73) -> 0 | N73: 10.9917 | O73: 195.5357 | P73: 0 | Q73: 2.3083 | R73: 23.4643 | S73: 206.5274 | T73: 232.3 | U73: 0 | V73: 0 | W73: 0 | X73: 0 | Y73: 0 | Z73: 0 | AA73: 0 | AB73: 232.3 | AC73: 0 | AD73: 0 | AE73: 0 | AF73: 0
A74: CZ60738677 | B74: RAPO BRNO, s.r.o. | C74: 96 | D74: BALADA - Březinky | E74: Pokladna 1 | F74: Teclová | G74: 46132 | H74: 0.45684028 | I74: 166004658 | J74: 63.6 | K74: =N74+O74+P74 -> 56.7857 | L74: =Q74+R74 -> 6.8143 | M74: =IF(J74=K74+L74,0,Y74) -> 0 | N74: 0 | O74: 56.7857 | P74: 0 | Q74: 0 | R74: 6.8143 | S74: 56.7857 | T74: 63.6 | U74: 0 | V74: 0 | W74: 0 | X74: 0 | Y74: 0 | Z74: 0 | AA74: 0 | AB74: 63.6 | AC74: 0 | AD74: 0 | AE74: 0 | AF74: 0
A75: CZ60738677 | B75: RAPO BRNO, s.r.o. | C75: 96 | D75: BALADA - Březinky | E75: Pokladna 1 | F75: Teclová | G75: 46132 | H75: 0.45768519 | I75: 166004659 | J75: 437.85 | K75: =N75+O75+P75 -> 390.9375 | L75: =Q75+R75 -> 46.9125 | M75: =IF(J75=K75+L75,0,Y75) -> 0 | N75: 0 | O75: 390.9375 | P75: 0 | Q75: 0 | R75: 46.9125 | S75: 390.9375 | T75: 437.85 | U75: 0 | V75: 0 | W75: 0 | X75: 0 | Y75: 0 | Z75: 0 | AA75: 0 | AB75: 437.85 | AC75: 0 | AD75: 0 | AE75: 0 | AF75: 0
A76: CZ60738677 | B76: RAPO BRNO, s.r.o. | C76: 96 | D76: BALADA - Březinky | E76: Pokladna 1 | F76: Teclová | G76: 46132 | H76: 0.45835648 | I76: 166004660 | J76: 209 | K76: =N76+O76+P76 -> 186.3392 | L76: =Q76+R76 -> 22.3608 | M76: =IF(J76=K76+L76,0,Y76) -> 0.3 | N76: 0 | O76: 186.3392 | P76: 0 | Q76: 0 | R76: 22.3608 | S76: 186.3392 | T76: 208.7 | U76: 0 | V76: 0 | W76: 0 | X76: 0 | Y76: 0.3 | Z76: 209 | AA76: 0 | AB76: 0 | AD76: 0 | AE76: 0 | AF76: 0
A77: CZ60738677 | B77: RAPO BRNO, s.r.o. | C77: 96 | D77: BALADA - Březinky | E77: Pokladna 1 | F77: Teclová | G77: 46132 | H77: 0.45913194 | I77: 166004661 | J77: 248.06 | K77: =N77+O77+P77 -> 217.7079 | L77: =Q77+R77 -> 30.3521 | M77: =IF(J77=K77+L77,0,Y77) -> 0 | N77: 46.9669 | O77: 170.741 | P77: 0 | Q77: 9.8631 | R77: 20.489 | S77: 217.7079 | T77: 248.06 | U77: 0 | V77: 0 | W77: 0 | X77: 0 | Y77: 0 | Z77: 0 | AA77: 0 | AB77: 248.06 | AC77: 0 | AD77: 0 | AE77: 0 | AF77: 20.94
A78: CZ60738677 | B78: RAPO BRNO, s.r.o. | C78: 96 | D78: BALADA - Březinky | E78: Pokladna 1 | F78: Teclová | G78: 46132 | H78: 0.45931713 | I78: 166004662 | J78: 149 | K78: =N78+O78+P78 -> 123.1405 | L78: =Q78+R78 -> 25.8595 | M78: =IF(J78=K78+L78,0,Y78) -> 0 | N78: 123.1405 | O78: 0 | P78: 0 | Q78: 25.8595 | R78: 0 | S78: 123.1405 | T78: 149 | U78: 0 | V78: 0 | W78: 0 | X78: 0 | Y78: 0 | Z78: 200 | AA78: 0 | AB78: 0 | AD78: 0 | AE78: -51 | AF78: 0
A79: CZ60738677 | B79: RAPO BRNO, s.r.o. | C79: 96 | D79: BALADA - Březinky | E79: Pokladna 1 | F79: Teclová | G79: 46132 | H79: 0.46368056 | I79: 166004663 | J79: 12 | K79: =N79+O79+P79 -> 10.3571 | L79: =Q79+R79 -> 1.2429 | M79: =IF(J79=K79+L79,0,Y79) -> 0.4 | N79: 0 | O79: 10.3571 | P79: 0 | Q79: 0 | R79: 1.2429 | S79: 10.3571 | T79: 11.6 | U79: 0 | V79: 0 | W79: 0 | X79: 0 | Y79: 0.4 | Z79: 100 | AA79: 0 | AB79: 0 | AD79: 0 | AE79: -88 | AF79: 0
A80: CZ60738677 | B80: RAPO BRNO, s.r.o. | C80: 96 | D80: BALADA - Březinky | E80: Pokladna 1 | F80: Teclová | G80: 46132 | H80: 0.46449074 | I80: 166004664 | J80: 222 | K80: =N80+O80+P80 -> 195.484 | L80: =Q80+R80 -> 27.006 | M80: =IF(J80=K80+L80,0,Y80) -> -0.49 | N80: 39.4215 | O80: 156.0625 | P80: 0 | Q80: 8.2785 | R80: 18.7275 | S80: 195.484 | T80: 222.49 | U80: 0 | V80: 0 | W80: 0 | X80: 0 | Y80: -0.49 | Z80: 502 | AA80: 0 | AB80: 0 | AD80: 0 | AE80: -280 | AF80: 0
A81: CZ60738677 | B81: RAPO BRNO, s.r.o. | C81: 96 | D81: BALADA - Březinky | E81: Pokladna 1 | F81: Teclová | G81: 46132 | H81: 0.46689815 | I81: 166004665 | J81: 51 | K81: =N81+O81+P81 -> 45.3392 | L81: =Q81+R81 -> 5.4408 | M81: =IF(J81=K81+L81,0,Y81) -> 0.22 | N81: 0 | O81: 45.3392 | P81: 0 | Q81: 0 | R81: 5.4408 | S81: 45.3392 | T81: 50.78 | U81: 0 | V81: 0 | W81: 0 | X81: 0 | Y81: 0.22 | Z81: 51 | AA81: 0 | AB81: 0 | AD81: 0 | AE81: 0 | AF81: 0
A82: CZ60738677 | B82: RAPO BRNO, s.r.o. | C82: 96 | D82: BALADA - Březinky | E82: Pokladna 1 | F82: Teclová | G82: 46132 | H82: 0.46759259 | I82: 166004666 | J82: 50 | K82: =N82+O82+P82 -> 41.2397 | L82: =Q82+R82 -> 8.6603 | M82: =IF(J82=K82+L82,0,Y82) -> 0.1 | N82: 41.2397 | O82: 0 | P82: 0 | Q82: 8.6603 | R82: 0 | S82: 41.2397 | T82: 49.9 | U82: 0 | V82: 0 | W82: 0 | X82: 0 | Y82: 0.1 | Z82: 50 | AA82: 0 | AB82: 0 | AD82: 0 | AE82: 0 | AF82: 0
A83: CZ60738677 | B83: RAPO BRNO, s.r.o. | C83: 96 | D83: BALADA - Březinky | E83: Pokladna 1 | F83: Teclová | G83: 46132 | H83: 0.4687037 | I83: 166004667 | J83: 653 | K83: =N83+O83+P83 -> 561.4099 | L83: =Q83+R83 -> 91.8401 | M83: =IF(J83=K83+L83,0,Y83) -> -0.25 | N83: 271.9008 | O83: 289.5091 | P83: 0 | Q83: 57.0992 | R83: 34.7409 | S83: 561.4099 | T83: 653.25 | U83: 0 | V83: 0 | W83: 0 | X83: 0 | Y83: -0.25 | Z83: 1000 | AA83: 0 | AB83: 0 | AD83: 0 | AE83: -347 | AF83: 10.4805
A84: CZ60738677 | B84: RAPO BRNO, s.r.o. | C84: 96 | D84: BALADA - Březinky | E84: Pokladna 1 | F84: Teclová | G84: 46132 | H84: 0.4690625 | I84: 166004668 | J84: 15 | K84: =N84+O84+P84 -> 12.314 | L84: =Q84+R84 -> 2.586 | M84: =IF(J84=K84+L84,0,Y84) -> 0.1 | N84: 12.314 | O84: 0 | P84: 0 | Q84: 2.586 | R84: 0 | S84: 12.314 | T84: 14.9 | U84: 0 | V84: 0 | W84: 0 | X84: 0 | Y84: 0.1 | Z84: 20 | AA84: 0 | AB84: 0 | AD84: 0 | AE84: -5 | AF84: 0
A85: CZ60738677 | B85: RAPO BRNO, s.r.o. | C85: 96 | D85: BALADA - Březinky | E85: Pokladna 1 | F85: Teclová | G85: 46132 | H85: 0.46952546 | I85: 166004669 | J85: 148.6 | K85: =N85+O85+P85 -> 131.0249 | L85: =Q85+R85 -> 17.5751 | M85: =IF(J85=K85+L85,0,Y85) -> 0 | N85: 20.5785 | O85: 110.4464 | P85: 0 | Q85: 4.3215 | R85: 13.2536 | S85: 131.0249 | T85: 148.6 | U85: 0 | V85: 0 | W85: 0 | X85: 0 | Y85: 0 | Z85: 0 | AA85: 0 | AB85: 148.6 | AC85: 0 | AD85: 0 | AE85: 0 | AF85: 0
A86: CZ60738677 | B86: RAPO BRNO, s.r.o. | C86: 96 | D86: BALADA - Březinky | E86: Pokladna 1 | F86: Teclová | G86: 46132 | H86: 0.4699537 | I86: 166004670 | J86: 481 | K86: =N86+O86+P86 -> 415.4146 | L86: =Q86+R86 -> 65.6854 | M86: =IF(J86=K86+L86,0,Y86) -> -0.1 | N86: 175.9504 | O86: 239.4642 | P86: 0 | Q86: 36.9496 | R86: 28.7358 | S86: 415.4146 | T86: 481.1 | U86: 0 | V86: 0 | W86: 0 | X86: 0 | Y86: -0.1 | Z86: 2000 | AA86: 0 | AB86: 0 | AD86: 0 | AE86: -1519 | AF86: 0
A87: CZ60738677 | B87: RAPO BRNO, s.r.o. | C87: 96 | D87: BALADA - Březinky | E87: Pokladna 1 | F87: Teclová | G87: 46132 | H87: 0.47050926 | I87: 166004671 | J87: 94 | K87: =N87+O87+P87 -> 83.5714 | L87: =Q87+R87 -> 10.0286 | M87: =IF(J87=K87+L87,0,Y87) -> 0.4 | N87: 0 | O87: 83.5714 | P87: 0 | Q87: 0 | R87: 10.0286 | S87: 83.5714 | T87: 93.6 | U87: 0 | V87: 0 | W87: 0 | X87: 0 | Y87: 0.4 | Z87: 94 | AA87: 0 | AB87: 0 | AD87: 0 | AE87: 0 | AF87: 0
A88: CZ60738677 | B88: RAPO BRNO, s.r.o. | C88: 96 | D88: BALADA - Březinky | E88: Pokladna 1 | F88: Teclová | G88: 46132 | H88: 0.47078704 | I88: 166004672 | J88: 123 | K88: =N88+O88+P88 -> 109.5536 | L88: =Q88+R88 -> 13.1464 | M88: =IF(J88=K88+L88,0,Y88) -> 0.3 | N88: 0 | O88: 109.5536 | P88: 0 | Q88: 0 | R88: 13.1464 | S88: 109.5536 | T88: 122.7 | U88: 0 | V88: 0 | W88: 0 | X88: 0 | Y88: 0.3 | Z88: 200 | AA88: 0 | AB88: 0 | AD88: 0 | AE88: -77 | AF88: 0
A89: CZ60738677 | B89: RAPO BRNO, s.r.o. | C89: 96 | D89: BALADA - Březinky | E89: Pokladna 1 | F89: Teclová | G89: 46132 | H89: 0.47130787 | I89: 166004673 | J89: 30 | K89: =N89+O89+P89 -> 26.9274 | L89: =Q89+R89 -> 3.3726 | M89: =IF(J89=K89+L89,0,Y89) -> -0.3 | N89: 1.5702 | O89: 25.3572 | P89: 0 | Q89: 0.3298 | R89: 3.0428 | S89: 26.9274 | T89: 30.3 | U89: 0 | V89: 0 | W89: 0 | X89: 0 | Y89: -0.3 | Z89: 30 | AA89: 0 | AB89: 0 | AD89: 0 | AE89: 0 | AF89: 0
A90: CZ60738677 | B90: RAPO BRNO, s.r.o. | C90: 96 | D90: BALADA - Březinky | E90: Pokladna 1 | F90: Teclová | G90: 46132 | H90: 0.47166667 | I90: 166004674 | J90: 5.77 | K90: =N90+O90+P90 -> 5.1518 | L90: =Q90+R90 -> 0.6182 | M90: =IF(J90=K90+L90,0,Y90) -> 0 | N90: 0 | O90: 5.1518 | P90: 0 | Q90: 0 | R90: 0.6182 | S90: 5.1518 | T90: 5.77 | U90: 0 | V90: 0 | W90: 0 | X90: 0 | Y90: 0 | Z90: 0 | AA90: 0 | AB90: 5.77 | AC90: 0 | AD90: 0 | AE90: 0 | AF90: 0
A91: CZ60738677 | B91: RAPO BRNO, s.r.o. | C91: 96 | D91: BALADA - Březinky | E91: Pokladna 1 | F91: Teclová | G91: 46132 | H91: 0.47203704 | I91: 166004675 | J91: 15.9 | K91: =N91+O91+P91 -> 14.1964 | L91: =Q91+R91 -> 1.7036 | M91: =IF(J91=K91+L91,0,Y91) -> 0 | N91: 0 | O91: 14.1964 | P91: 0 | Q91: 0 | R91: 1.7036 | S91: 14.1964 | T91: 15.9 | U91: 0 | V91: 0 | W91: 0 | X91: 0 | Y91: 0 | Z91: 0 | AA91: 0 | AB91: 15.9 | AC91: 0 | AD91: 0 | AE91: 0 | AF91: 0
A92: CZ60738677 | B92: RAPO BRNO, s.r.o. | C92: 96 | D92: BALADA - Březinky | E92: Pokladna 1 | F92: Teclová | G92: 46132 | H92: 0.47388889 | I92: 166004676 | J92: 137 | K92: =N92+O92+P92 -> 117.6446 | L92: =Q92+R92 -> 19.7554 | M92: =IF(J92=K92+L92,0,Y92) -> -0.4 | N92: 62.6446 | O92: 55 | P92: 0 | Q92: 13.1554 | R92: 6.6 | S92: 117.6446 | T92: 137.4 | U92: 0 | V92: 0 | W92: 0 | X92: 0 | Y92: -0.4 | Z92: 237 | AA92: 0 | AB92: 0 | AD92: 0 | AE92: -100 | AF92: 0
A93: CZ60738677 | B93: RAPO BRNO, s.r.o. | C93: 96 | D93: BALADA - Březinky | E93: Pokladna 1 | F93: Teclová | G93: 46132 | H93: 0.47467593 | I93: 166004677 | J93: 105.16 | K93: =N93+O93+P93 -> 92.5713 | L93: =Q93+R93 -> 12.5887 | M93: =IF(J93=K93+L93,0,Y93) -> 0 | N93: 16.4463 | O93: 76.125 | P93: 0 | Q93: 3.4537 | R93: 9.135 | S93: 92.5713 | T93: 105.16 | U93: 0 | V93: 0 | W93: 0 | X93: 0 | Y93: 0 | Z93: 0 | AA93: 0 | AB93: 105.16 | AC93: 0 | AD93: 0 | AE93: 0 | AF93: 13.11
A94: CZ60738677 | B94: RAPO BRNO, s.r.o. | C94: 96 | D94: BALADA - Březinky | E94: Pokladna 1 | F94: Teclová | G94: 46132 | H94: 0.4750463 | I94: 166004678 | J94: 30 | K94: =N94+O94+P94 -> 26.5267 | L94: =Q94+R94 -> 3.1833 | M94: =IF(J94=K94+L94,0,Y94) -> 0.29 | N94: 0 | O94: 26.5267 | P94: 0 | Q94: 0 | R94: 3.1833 | S94: 26.5267 | T94: 29.71 | U94: 0 | V94: 0 | W94: 0 | X94: 0 | Y94: 0.29 | Z94: 1000 | AA94: 0 | AB94: 0 | AD94: 0 | AE94: -970 | AF94: 0
A95: CZ60738677 | B95: RAPO BRNO, s.r.o. | C95: 96 | D95: BALADA - Březinky | E95: Pokladna 1 | F95: Teclová | G95: 46132 | H95: 0.47530093 | I95: 166004679 | J95: 12 | K95: =N95+O95+P95 -> 10.5358 | L95: =Q95+R95 -> 1.2642 | M95: =IF(J95=K95+L95,0,Y95) -> 0.2 | N95: 0 | O95: 10.5358 | P95: 0 | Q95: 0 | R95: 1.2642 | S95: 10.5358 | T95: 11.8 | U95: 0 | V95: 0 | W95: 0 | X95: 0 | Y95: 0.2 | Z95: 50 | AA95: 0 | AB95: 0 | AD95: 0 | AE95: -38 | AF95: 0
A96: CZ60738677 | B96: RAPO BRNO, s.r.o. | C96: 96 | D96: BALADA - Březinky | E96: Pokladna 1 | F96: Teclová | G96: 46132 | H96: 0.47579861 | I96: 166004680 | J96: 146 | K96: =N96+O96+P96 -> 130.2053 | L96: =Q96+R96 -> 15.6247 | M96: =IF(J96=K96+L96,0,Y96) -> 0.17 | N96: 0 | O96: 130.2053 | P96: 0 | Q96: 0 | R96: 15.6247 | S96: 130.2053 | T96: 145.83 | U96: 0 | V96: 0 | W96: 0 | X96: 0 | Y96: 0.17 | Z96: 200 | AA96: 0 | AB96: 0 | AD96: 0 | AE96: -54 | AF96: 7.7711
A97: CZ60738677 | B97: RAPO BRNO, s.r.o. | C97: 96 | D97: BALADA - Březinky | E97: Pokladna 1 | F97: Teclová | G97: 46132 | H97: 0.47657407 | I97: 166004681 | J97: 63.6 | K97: =N97+O97+P97 -> 56.7857 | L97: =Q97+R97 -> 6.8143 | M97: =IF(J97=K97+L97,0,Y97) -> 0 | N97: 0 | O97: 56.7857 | P97: 0 | Q97: 0 | R97: 6.8143 | S97: 56.7857 | T97: 63.6 | U97: 0 | V97: 0 | W97: 0 | X97: 0 | Y97: 0 | Z97: 0 | AA97: 0 | AB97: 63.6 | AC97: 0 | AD97: 0 | AE97: 0 | AF97: 0
A98: CZ60738677 | B98: RAPO BRNO, s.r.o. | C98: 96 | D98: BALADA - Březinky | E98: Pokladna 1 | F98: Teclová | G98: 46132 | H98: 0.47824074 | I98: 166004682 | J98: 322 | K98: =N98+O98+P98 -> 266.1158 | L98: =Q98+R98 -> 55.8842 | M98: =IF(J98=K98+L98,0,Y98) -> 0 | N98: 266.1158 | O98: 0 | P98: 0 | Q98: 55.8842 | R98: 0 | S98: 266.1158 | T98: 322 | U98: 0 | V98: 0 | W98: 0 | X98: 0 | Y98: 0 | Z98: 0 | AA98: 0 | AB98: 322 | AC98: 0 | AD98: 0 | AE98: 0 | AF98: 0
A99: CZ60738677 | B99: RAPO BRNO, s.r.o. | C99: 96 | D99: BALADA - Březinky | E99: Pokladna 1 | F99: Teclová | G99: 46132 | H99: 0.47878472 | I99: 166004683 | J99: 20 | K99: =N99+O99+P99 -> 17.7143 | L99: =Q99+R99 -> 2.4857 | M99: =IF(J99=K99+L99,0,Y99) -> -0.2 | N99: 0 | O99: 20.7143 | P99: -3 | Q99: 0 | R99: 2.4857 | S99: 20.7143 | T99: 23.2 | U99: 0 | V99: 0 | W99: 0 | X99: -3 | Y99: -0.2 | Z99: 20 | AA99: 0 | AB99: 0 | AD99: 0 | AE99: 0 | AF99: 0
A100: CZ60738677 | B100: RAPO BRNO, s.r.o. | C100: 96 | D100: BALADA - Březinky | E100: Pokladna 1 | F100: Teclová | G100: 46132 | H100: 0.48077546 | I100: 166004684 | J100: 261.91 | K100: =N100+O100+P100 -> 221.0443 | L100: =Q100+R100 -> 40.8657 | M100: =IF(J100=K100+L100,0,Y100) -> 0 | N100: 159.3389 | O100: 61.7054 | P100: 0 | Q100: 33.4611 | R100: 7.4046 | S100: 221.0443 | T100: 261.91 | U100: 0 | V100: 0 | W100: 0 | X100: 0 | Y100: 0 | Z100: 0 | AA100: 0 | AB100: 261.91 | AC100: 0 | AD100: 0 | AE100: 0 | AF100: 0
A101: CZ60738677 | B101: RAPO BRNO, s.r.o. | C101: 96 | D101: BALADA - Březinky | E101: Pokladna 1 | F101: Teclová | G101: 46132 | H101: 0.48173611 | I101: 166004685 | J101: 116 | K101: =N101+O101+P101 -> 100.2619 | L101: =Q101+R101 -> 15.4381 | M101: =IF(J101=K101+L101,0,Y101) -> 0.3 | N101: 37.8512 | O101: 62.4107 | P101: 0 | Q101: 7.9488 | R101: 7.4893 | S101: 100.2619 | T101: 115.7 | U101: 0 | V101: 0 | W101: 0 | X101: 0 | Y101: 0.3 | Z101: 116 | AA101: 0 | AB101: 0 | AD101: 0 | AE101: 0 | AF101: 0
A102: CZ60738677 | B102: RAPO BRNO, s.r.o. | C102: 96 | D102: BALADA - Březinky | E102: Pokladna 1 | F102: Teclová | G102: 46132 | H102: 0.48313657 | I102: 166004686 | J102: 63 | K102: =N102+O102+P102 -> 52.8078 | L102: =Q102+R102 -> 9.8922 | M102: =IF(J102=K102+L102,0,Y102) -> 0.3 | N102: 39.5042 | O102: 13.3036 | P102: 0 | Q102: 8.2958 | R102: 1.5964 | S102: 52.8078 | T102: 62.7 | U102: 0 | V102: 0 | W102: 0 | X102: 0 | Y102: 0.3 | Z102: 200 | AA102: 0 | AB102: 0 | AD102: 0 | AE102: -137 | AF102: 0
A103: CZ60738677 | B103: RAPO BRNO, s.r.o. | C103: 96 | D103: BALADA - Březinky | E103: Pokladna 1 | F103: Teclová | G103: 46132 | H103: 0.4837037 | I103: 166004687 | J103: 173 | K103: =N103+O103+P103 -> 142.9752 | L103: =Q103+R103 -> 30.0248 | M103: =IF(J103=K103+L103,0,Y103) -> 0 | N103: 142.9752 | O103: 0 | P103: 0 | Q103: 30.0248 | R103: 0 | S103: 142.9752 | T103: 173 | U103: 0 | V103: 0 | W103: 0 | X103: 0 | Y103: 0 | Z103: 0 | AA103: 0 | AB103: 173 | AC103: 0 | AD103: 0 | AE103: 0 | AF103: 0
A104: CZ60738677 | B104: RAPO BRNO, s.r.o. | C104: 96 | D104: BALADA - Březinky | E104: Pokladna 1 | F104: Teclová | G104: 46132 | H104: 0.4843287 | I104: 166004688 | J104: 51 | K104: =N104+O104+P104 -> 45.1608 | L104: =Q104+R104 -> 5.4192 | M104: =IF(J104=K104+L104,0,Y104) -> 0.42 | N104: 0 | O104: 45.1608 | P104: 0 | Q104: 0 | R104: 5.4192 | S104: 45.1608 | T104: 50.58 | U104: 0 | V104: 0 | W104: 0 | X104: 0 | Y104: 0.42 | Z104: 102 | AA104: 0 | AB104: 0 | AD104: 0 | AE104: -51 | AF104: 10.6202
A105: CZ60738677 | B105: RAPO BRNO, s.r.o. | C105: 96 | D105: BALADA - Březinky | E105: Pokladna 1 | F105: Teclová | G105: 46132 | H105: 0.48508102 | I105: 166004689 | J105: 160.07 | K105: =N105+O105+P105 -> 142.9197 | L105: =Q105+R105 -> 17.1503 | M105: =IF(J105=K105+L105,0,Y105) -> 0 | N105: 0 | O105: 142.9197 | P105: 0 | Q105: 0 | R105: 17.1503 | S105: 142.9197 | T105: 160.07 | U105: 0 | V105: 0 | W105: 0 | X105: 0 | Y105: 0 | Z105: 0 | AA105: 0 | AB105: 160.07 | AC105: 0 | AD105: 0 | AE105: 0 | AF105: 0
A106: CZ60738677 | B106: RAPO BRNO, s.r.o. | C106: 96 | D106: BALADA - Březinky | E106: Pokladna 1 | F106: Teclová | G106: 46132 | H106: 0.48591435 | I106: 166004690 | J106: 39.9 | K106: =N106+O106+P106 -> 35.625 | L106: =Q106+R106 -> 4.275 | M106: =IF(J106=K106+L106,0,Y106) -> 0 | N106: 0 | O106: 35.625 | P106: 0 | Q106: 0 | R106: 4.275 | S106: 35.625 | T106: 39.9 | U106: 0 | V106: 0 | W106: 0 | X106: 0 | Y106: 0 | Z106: 0 | AA106: 0 | AB106: 39.9 | AC106: 0 | AD106: 0 | AE106: 0 | AF106: 0
A107: CZ60738677 | B107: RAPO BRNO, s.r.o. | C107: 96 | D107: BALADA - Březinky | E107: Pokladna 1 | F107: Teclová | G107: 46132 | H107: 0.48641204 | I107: 166004691 | J107: 194 | K107: =N107+O107+P107 -> 173.5715 | L107: =Q107+R107 -> 20.8285 | M107: =IF(J107=K107+L107,0,Y107) -> -0.4 | N107: 0 | O107: 173.5715 | P107: 0 | Q107: 0 | R107: 20.8285 | S107: 173.5715 | T107: 194.4 | U107: 0 | V107: 0 | W107: 0 | X107: 0 | Y107: -0.4 | Z107: 200 | AA107: 0 | AB107: 0 | AD107: 0 | AE107: -6 | AF107: 0
A108: CZ60738677 | B108: RAPO BRNO, s.r.o. | C108: 96 | D108: BALADA - Březinky | E108: Pokladna 1 | F108: Teclová | G108: 46132 | H108: 0.48916667 | I108: 166004692 | J108: 19.9 | K108: =N108+O108+P108 -> 16.4463 | L108: =Q108+R108 -> 3.4537 | M108: =IF(J108=K108+L108,0,Y108) -> 0 | N108: 16.4463 | O108: 0 | P108: 0 | Q108: 3.4537 | R108: 0 | S108: 16.4463 | T108: 19.9 | U108: 0 | V108: 0 | W108: 0 | X108: 0 | Y108: 0 | Z108: 0 | AA108: 0 | AB108: 19.9 | AC108: 0 | AD108: 0 | AE108: 0 | AF108: 0
A109: CZ60738677 | B109: RAPO BRNO, s.r.o. | C109: 96 | D109: BALADA - Březinky | E109: Pokladna 1 | F109: Teclová | G109: 46132 | H109: 0.48987269 | I109: 166004693 | J109: 149.3 | K109: =N109+O109+P109 -> 131.982 | L109: =Q109+R109 -> 17.318 | M109: =IF(J109=K109+L109,0,Y109) -> 0 | N109: 16.4463 | O109: 115.5357 | P109: 0 | Q109: 3.4537 | R109: 13.8643 | S109: 131.982 | T109: 149.3 | U109: 0 | V109: 0 | W109: 0 | X109: 0 | Y109: 0 | Z109: 0 | AA109: 0 | AB109: 149.3 | AC109: 0 | AD109: 0 | AE109: 0 | AF109: 0
A110: CZ60738677 | B110: RAPO BRNO, s.r.o. | C110: 96 | D110: BALADA - Březinky | E110: Pokladna 1 | F110: Teclová | G110: 46132 | H110: 0.49054398 | I110: 166004694 | J110: 81 | K110: =N110+O110+P110 -> 72.4631 | L110: =Q110+R110 -> 8.8369 | M110: =IF(J110=K110+L110,0,Y110) -> -0.3 | N110: 1.5702 | O110: 70.8929 | P110: 0 | Q110: 0.3298 | R110: 8.5071 | S110: 72.4631 | T110: 81.3 | U110: 0 | V110: 0 | W110: 0 | X110: 0 | Y110: -0.3 | Z110: 100 | AA110: 0 | AB110: 0 | AD110: 0 | AE110: -19 | AF110: 0
A111: CZ60738677 | B111: RAPO BRNO, s.r.o. | C111: 96 | D111: BALADA - Březinky | E111: Pokladna 1 | F111: Teclová | G111: 46132 | H111: 0.49288194 | I111: 166004695 | J111: 91.36 | K111: =N111+O111+P111 -> 81.5714 | L111: =Q111+R111 -> 9.7886 | M111: =IF(J111=K111+L111,0,Y111) -> 0 | N111: 0 | O111: 81.5714 | P111: 0 | Q111: 0 | R111: 9.7886 | S111: 81.5714 | T111: 91.36 | U111: 0 | V111: 0 | W111: 0 | X111: 0 | Y111: 0 | Z111: 0 | AA111: 0 | AB111: 91.36 | AC111: 0 | AD111: 0 | AE111: 0 | AF111: 8.1049
...

Sheet Položky dokladů
A1: Identifikace | G1: Datum a doklad | K1: Zboží | P1: Akce | R1: Jednotková cena zboží a obalu | W1: Množství | Y1: Celkem za položku zboží a obalu | AD1: Sleva na pokladně
A2: DIČ | B2: Název firmy | C2: ID provozovny | D2: Název provozovny | E2: ID pokladny | F2: Uživatel | G2: Datum | H2: Čas | I2: Číslo dokladu | J2: Fiskalizace | K2: Číslo zboží | L2: EAN kód | M2: Výrobce | N2: Třídící strom | O2: Název zboží | P2: Příznak akce | Q2: Kód akce | R2: Zboží | V2: Obal | W2: Množství | X2: Jednotka | Y2: =SUBTOTAL(109,Y4:Y999225) -> 92256.226 | Z2: =SUBTOTAL(109,Z4:Z999225) -> 80410.622 | AA2: =SUBTOTAL(109,AA4:AA999225) -> 11845.604 | AB2: =SUBTOTAL(109,AB4:AB999225) -> 6 | AC2: =SUBTOTAL(109,AC4:AC999225) -> 92295.126 | AD2: =SUBTOTAL(109,AD4:AD999225) -> 117438.25 | AE2: =SUBTOTAL(109,AE4:AE999225) -> 3356.43 | AF2: =SUBTOTAL(109,AF4:AF999225) -> 1083.0861
R3: Cena s DPH | S3: Základ DPH | T3: DPH | U3: Sazba DPH | V3: Cena | Y3: Celkem zboží s DPH | Z3: Celkem zboží základ DPH | AA3: Celkem zboží DPH | AB3: Celkem obaly | AC3: Celkem zboží a obaly s DPH | AD3: Původní jednotková Cena s DPH | AE3: Jednotková Sleva | AF3: Sleva celkem za položku zboží
A4: CZ60738677 | B4: RAPO BRNO, s.r.o. | C4: 96 | D4: BALADA - Březinky | E4: Pokladna SCO1 | F4: profikasa | G4: 46132 | H4: 0.3162963 | I4: 161000330 | J4: NE | K4: 13336602 | L4: 8595019696884 | M4: CARLA spol. s r.o. | N4: 51102 | O4: Laguna Mořské plody mléčná | P4: NE | R4: 32.9 | S4: ==R4-T4 -> FALSE | T4: ==R4*U4/(U4+100) -> FALSE | U4: 12 | V4: 0 | W4: 1 | X4: KS | Y4: ==R4*W4 -> FALSE | Z4: ==S4*W4 -> FALSE | AA4: ==T4*W4 -> FALSE | AB4: ==V4*W4 -> FALSE | AC4: =(R4+V4)*W4 -> 32.9 | AD4: 32.9 | AE4: 0 | AF4: 0
A5: CZ60738677 | B5: RAPO BRNO, s.r.o. | C5: 96 | D5: BALADA - Březinky | E5: Pokladna SCO1 | F5: profikasa | G5: 46132 | H5: 0.31802083 | I5: 161000331 | J5: NE | K5: 48119602 | L5: 8594057637859 | M5: MASPEX CZECH, s.r.o. | N5: 52209 | O5: Tiger energy drink 1l | P5: NE | R5: 23.9 | S5: =R5-T5 -> 19.752066 | T5: =R5*U5/(U5+100) -> 4.1479339 | U5: 21 | V5: 0 | W5: 1 | X5: KS | Y5: =R5*W5 -> 23.9 | Z5: =S5*W5 -> 19.752066 | AA5: =T5*W5 -> 4.1479339 | AB5: =V5*W5 -> 0 | AC5: =(R5+V5)*W5 -> 23.9 | AD5: 23.9 | AE5: 0 | AF5: 0
A6: CZ60738677 | B6: RAPO BRNO, s.r.o. | C6: 96 | D6: BALADA - Březinky | E6: Pokladna SCO1 | F6: profikasa | G6: 46132 | H6: 0.3306713 | I6: 161000332 | J6: NE | K6: 21153380 | L6: 5900749624961 | M6: FS IMPORT- EXPORT s.r.o. | N6: 50201 | O6: BA! Energy Bar 5 forest fr | P6: NE | R6: 10.9 | S6: =R6-T6 -> 9.7321429 | T6: =R6*U6/(U6+100) -> 1.1678571 | U6: 12 | V6: 0 | W6: 1 | X6: KS | Y6: =R6*W6 -> 10.9 | Z6: =S6*W6 -> 9.7321429 | AA6: =T6*W6 -> 1.1678571 | AB6: =V6*W6 -> 0 | AC6: =(R6+V6)*W6 -> 10.9 | AD6: 10.9 | AE6: 0 | AF6: 0
A7: CZ60738677 | B7: RAPO BRNO, s.r.o. | C7: 96 | D7: BALADA - Březinky | E7: Pokladna SCO1 | F7: profikasa | G7: 46132 | H7: 0.3306713 | I7: 161000332 | J7: NE | K7: 21153398 | L7: 5900749618991 | M7: FS IMPORT- EXPORT s.r.o. | N7: 50201 | O7: BA! Energetická mysli tyči | P7: NE | R7: 11.4 | S7: =R7-T7 -> 10.178571 | T7: =R7*U7/(U7+100) -> 1.2214286 | U7: 12 | V7: 0 | W7: 1 | X7: KS | Y7: =R7*W7 -> 11.4 | Z7: =S7*W7 -> 10.178571 | AA7: =T7*W7 -> 1.2214286 | AB7: =V7*W7 -> 0 | AC7: =(R7+V7)*W7 -> 11.4 | AD7: 11.4 | AE7: 0 | AF7: 0
A8: CZ60738677 | B8: RAPO BRNO, s.r.o. | C8: 96 | D8: BALADA - Březinky | E8: Pokladna SCO1 | F8: profikasa | G8: 46132 | H8: 0.3306713 | I8: 161000332 | J8: NE | K8: 21153400 | L8: 5900749618984 | M8: FS IMPORT- EXPORT s.r.o. | N8: 50201 | O8: BA! Energy Bar brusinka 40 | P8: NE | R8: 11.4 | S8: =R8-T8 -> 10.178571 | T8: =R8*U8/(U8+100) -> 1.2214286 | U8: 12 | V8: 0 | W8: 1 | X8: KS | Y8: =R8*W8 -> 11.4 | Z8: =S8*W8 -> 10.178571 | AA8: =T8*W8 -> 1.2214286 | AB8: =V8*W8 -> 0 | AC8: =(R8+V8)*W8 -> 11.4 | AD8: 11.4 | AE8: 0 | AF8: 0
A9: CZ60738677 | B9: RAPO BRNO, s.r.o. | C9: 96 | D9: BALADA - Březinky | E9: Pokladna SCO1 | F9: profikasa | G9: 46132 | H9: 0.3306713 | I9: 161000332 | J9: NE | K9: 21153425 | L9: 5900749618939 | M9: FS IMPORT- EXPORT s.r.o. | N9: 50201 | O9: BA! 5 Dries fruits and nut | P9: NE | R9: 11.4 | S9: =R9-T9 -> 10.178571 | T9: =R9*U9/(U9+100) -> 1.2214286 | U9: 12 | V9: 0 | W9: 1 | X9: KS | Y9: =R9*W9 -> 11.4 | Z9: =S9*W9 -> 10.178571 | AA9: =T9*W9 -> 1.2214286 | AB9: =V9*W9 -> 0 | AC9: =(R9+V9)*W9 -> 11.4 | AD9: 11.4 | AE9: 0 | AF9: 0
A10: CZ60738677 | B10: RAPO BRNO, s.r.o. | C10: 96 | D10: BALADA - Březinky | E10: Pokladna SCO1 | F10: profikasa | G10: 46132 | H10: 0.3306713 | I10: 161000332 | J10: NE | K10: 60532961 | L10: 8596140001721 | M10: ČEPOS-Česká potravinářská obchodní a.s. | N10: 80306 | O10: Košilka ČC 50ks | P10: NE | R10: 1.9 | S10: =R10-T10 -> 1.5702479 | T10: =R10*U10/(U10+100) -> 0.32975207 | U10: 21 | V10: 0 | W10: 1 | X10: KS | Y10: =R10*W10 -> 1.9 | Z10: =S10*W10 -> 1.5702479 | AA10: =T10*W10 -> 0.32975207 | AB10: =V10*W10 -> 0 | AC10: =(R10+V10)*W10 -> 1.9 | AD10: 1.9 | AE10: 0 | AF10: 0
A11: CZ60738677 | B11: RAPO BRNO, s.r.o. | C11: 96 | D11: BALADA - Březinky | E11: Pokladna SCO1 | F11: profikasa | G11: 46132 | H11: 0.3306713 | I11: 161000332 | J11: NE | K11: 68356200 | L11: 287531 | M11: ČEROZFRUCHT České Budějovice | N11: 70202 | O11: Okurka hadovka | P11: NE | R11: 33.9 | S11: =R11-T11 -> 30.267857 | T11: =R11*U11/(U11+100) -> 3.6321429 | U11: 12 | V11: 0 | W11: 0.294 | X11: KG | Y11: =R11*W11 -> 9.9666 | Z11: =S11*W11 -> 8.89875 | AA11: =T11*W11 -> 1.06785 | AB11: =V11*W11 -> 0 | AC11: =(R11+V11)*W11 -> 9.9666 | AD11: 33.9 | AE11: 0 | AF11: 0
A12: CZ60738677 | B12: RAPO BRNO, s.r.o. | C12: 96 | D12: BALADA - Březinky | E12: Pokladna SCO1 | F12: profikasa | G12: 46132 | H12: 0.3306713 | I12: 161000332 | J12: NE | K12: 68356200 | L12: 287531 | M12: ČEROZFRUCHT České Budějovice | N12: 70202 | O12: Okurka hadovka | P12: NE | R12: 33.9 | S12: =R12-T12 -> 30.267857 | T12: =R12*U12/(U12+100) -> 3.6321429 | U12: 12 | V12: 0 | W12: 0.264 | X12: KG | Y12: =R12*W12 -> 8.9496 | Z12: =S12*W12 -> 7.9907143 | AA12: =T12*W12 -> 0.95888571 | AB12: =V12*W12 -> 0 | AC12: =(R12+V12)*W12 -> 8.9496 | AD12: 33.9 | AE12: 0 | AF12: 0
A13: CZ60738677 | B13: RAPO BRNO, s.r.o. | C13: 96 | D13: BALADA - Březinky | E13: Pokladna SCO1 | F13: profikasa | G13: 46132 | H13: 0.3306713 | I13: 161000332 | J13: NE | K13: 68356200 | L13: 287531 | M13: ČEROZFRUCHT České Budějovice | N13: 70202 | O13: Okurka hadovka | P13: NE | R13: 33.9 | S13: =R13-T13 -> 30.267857 | T13: =R13*U13/(U13+100) -> 3.6321429 | U13: 12 | V13: 0 | W13: 0.284 | X13: KG | Y13: =R13*W13 -> 9.6276 | Z13: =S13*W13 -> 8.5960714 | AA13: =T13*W13 -> 1.0315286 | AB13: =V13*W13 -> 0 | AC13: =(R13+V13)*W13 -> 9.6276 | AD13: 33.9 | AE13: 0 | AF13: 0
A14: CZ60738677 | B14: RAPO BRNO, s.r.o. | C14: 96 | D14: BALADA - Březinky | E14: Pokladna SCO1 | F14: profikasa | G14: 46132 | H14: 0.3580787 | I14: 161000333 | J14: NE | K14: 10103125 | L14: 8584004030000 | M14: I.D.C. Praha, a.s. | N14: 51001 | O14: Mila řezy 50g | P14: NE | R14: 18.9 | S14: =R14-T14 -> 16.875 | T14: =R14*U14/(U14+100) -> 2.025 | U14: 12 | V14: 0 | W14: 2 | X14: KS | Y14: =R14*W14 -> 37.8 | Z14: =S14*W14 -> 33.75 | AA14: =T14*W14 -> 4.05 | AB14: =V14*W14 -> 0 | AC14: =(R14+V14)*W14 -> 37.8 | AD14: 18.9 | AE14: 0 | AF14: 0
A15: CZ60738677 | B15: RAPO BRNO, s.r.o. | C15: 96 | D15: BALADA - Březinky | E15: Pokladna SCO1 | F15: profikasa | G15: 46132 | H15: 0.3580787 | I15: 161000333 | J15: NE | K15: 31775740 | L15: 4014500515083 | M15: Zott s.r.o. | N15: 20112 | O15: Zott Monte Snack 29g | P15: NE | R15: 11.9 | S15: =R15-T15 -> 10.625 | T15: =R15*U15/(U15+100) -> 1.275 | U15: 12 | V15: 0 | W15: 1 | X15: KS | Y15: =R15*W15 -> 11.9 | Z15: =S15*W15 -> 10.625 | AA15: =T15*W15 -> 1.275 | AB15: =V15*W15 -> 0 | AC15: =(R15+V15)*W15 -> 11.9 | AD15: 11.9 | AE15: 0 | AF15: 0
A16: CZ60738677 | B16: RAPO BRNO, s.r.o. | C16: 96 | D16: BALADA - Březinky | E16: Pokladna SCO1 | F16: profikasa | G16: 46132 | H16: 0.3580787 | I16: 161000333 | J16: NE | K16: 31775740 | L16: 4014500515083 | M16: Zott s.r.o. | N16: 20112 | O16: Zott Monte Snack 29g | P16: NE | R16: 11.9 | S16: =R16-T16 -> 10.625 | T16: =R16*U16/(U16+100) -> 1.275 | U16: 12 | V16: 0 | W16: 1 | X16: KS | Y16: =R16*W16 -> 11.9 | Z16: =S16*W16 -> 10.625 | AA16: =T16*W16 -> 1.275 | AB16: =V16*W16 -> 0 | AC16: =(R16+V16)*W16 -> 11.9 | AD16: 11.9 | AE16: 0 | AF16: 0
... A24: CZ60738677 | B24: RAPO BRNO, s.r.o. | C24: 96 | D24: BALADA - Březinky | E24: Pokladna SCO1 | F24: profikasa | G24: 46132 | H24: 0.38399306 | I24: 161000336 | J24: NE | K24: 31775791 | L24: 4014500520773 | M24: Zott s.r.o. | N24: 20101 | O24: Zott Protein Drink a přích | P24: NE | R24: 29.9 | S24: =R24-T24 -> 26.696429 | T24: =R24*U24/(U24+100) -> 3.2035714 | U24: 12 | V24: 0 | W24: 1 | X24: KS | Y24: =R24*W24 -> 29.9 | Z24: =S24*W24 -> 26.696429 | AA24: =T24*W24 -> 3.2035714 | AB24: =V24*W24 -> 0 | AC24: =(R24+V24)*W24 -> 29.9 | AD24: 29.9 | AE24: 0 | AF24: 0
A25: CZ60738677 | B25: RAPO BRNO, s.r.o. | C25: 96 | D25: BALADA - Březinky | E25: Pokladna SCO1 | F25: profikasa | G25: 46132 | H25: 0.38399306 | I25: 161000336 | J25: NE | K25: 45116303 | L25: 8594001026357 | M25: Mattoni 1873 a.s. | N25: 52202 | O25: Magnesia Plus Boost mandar | P25: ANO | Q25: BALADA 26_9A | R25: 24.9 | S25: =R25-T25 -> 20.578512 | T25: =R25*U25/(U25+100) -> 4.3214876 | U25: 21 | V25: 0 | W25: 1 | X25: KS | Y25: =R25*W25 -> 24.9 | Z25: =S25*W25 -> 20.578512 | AA25: =T25*W25 -> 4.3214876 | AB25: =V25*W25 -> 0 | AC25: =(R25+V25)*W25 -> 24.9 | AD25: 24.9 | AE25: 0 | AF25: 0
A26: CZ60738677 | B26: RAPO BRNO, s.r.o. | C26: 96 | D26: BALADA - Březinky | E26: Pokladna SCO1 | F26: profikasa | G26: 46132 | H26: 0.40315972 | I26: 161000337 | J26: NE | K26: 12103849 | L26: 8584004803307 | M26: I.D.C. Praha, a.s. | N26: 51101 | O26: Lina celomáčená tyčinka ch | P26: NE | R26: 27.9 | S26: =R26-T26 -> 24.910714 | T26: =R26*U26/(U26+100) -> 2.9892857 | U26: 12 | V26: 0 | W26: 1 | X26: KS | Y26: =R26*W26 -> 27.9 | Z26: =S26*W26 -> 24.910714 | AA26: =T26*W26 -> 2.9892857 | AB26: =V26*W26 -> 0 | AC26: =(R26+V26)*W26 -> 27.9 | AD26: 27.9 | AE26: 0 | AF26: 0
A27: CZ60738677 | B27: RAPO BRNO, s.r.o. | C27: 96 | D27: BALADA - Březinky | E27: Pokladna SCO1 | F27: profikasa | G27: 46132 | H27: 0.40315972 | I27: 161000337 | J27: NE | K27: 21153400 | L27: 5900749618984 | M27: FS IMPORT- EXPORT s.r.o. | N27: 50201 | O27: BA! Energy Bar brusinka 40 | P27: NE | R27: 11.4 | S27: =R27-T27 -> 10.178571 | T27: =R27*U27/(U27+100) -> 1.2214286 | U27: 12 | V27: 0 | W27: 1 | X27: KS | Y27: =R27*W27 -> 11.4 | Z27: =S27*W27 -> 10.178571 | AA27: =T27*W27 -> 1.2214286 | AB27: =V27*W27 -> 0 | AC27: =(R27+V27)*W27 -> 11.4 | AD27: 11.4 | AE27: 0 | AF27: 0
A28: CZ60738677 | B28: RAPO BRNO, s.r.o. | C28: 96 | D28: BALADA - Březinky | E28: Pokladna SCO1 | F28: profikasa | G28: 46132 | H28: 0.42946759 | I28: 161000338 | J28: NE | K28: 11309154 | L28: 8595606210059 | M28: INTERSNACK a.s. | N28: 50101 | O28: Bohemia chips slanina 60g | P28: NE | R28: 27.9 | S28: =R28-T28 -> 24.910714 | T28: =R28*U28/(U28+100) -> 2.9892857 | U28: 12 | V28: 0 | W28: 1 | X28: KS | Y28: =R28*W28 -> 27.9 | Z28: =S28*W28 -> 24.910714 | AA28: =T28*W28 -> 2.9892857 | AB28: =V28*W28 -> 0 | AC28: =(R28+V28)*W28 -> 27.9 | AD28: 27.9 | AE28: 0 | AF28: 0
A29: CZ60738677 | B29: RAPO BRNO, s.r.o. | C29: 96 | D29: BALADA - Březinky | E29: Pokladna SCO1 | F29: profikasa | G29: 46132 | H29: 0.42946759 | I29: 161000338 | J29: NE | K29: 11980030 | L29: 8594004160003 | M29: SECALO a.s. | N29: 50101 | O29: Křupky arašídové 60g | P29: NE | R29: 13.9 | S29: =R29-T29 -> 12.410714 | T29: =R29*U29/(U29+100) -> 1.4892857 | U29: 12 | V29: 0 | W29: 1 | X29: KS | Y29: =R29*W29 -> 13.9 | Z29: =S29*W29 -> 12.410714 | AA29: =T29*W29 -> 1.4892857 | AB29: =V29*W29 -> 0 | AC29: =(R29+V29)*W29 -> 13.9 | AD29: 13.9 | AE29: 0 | AF29: 0
A30: CZ60738677 | B30: RAPO BRNO, s.r.o. | C30: 96 | D30: BALADA - Březinky | E30: Pokladna SCO1 | F30: profikasa | G30: 46132 | H30: 0.42946759 | I30: 161000338 | J30: NE | K30: 31704300 | L30: 8594006320122 | M30: Moravia Lacto a.s. | N30: 20101 | O30: Mléko polotučné 1,5% Morav | P30: NE | R30: 27.9 | S30: =R30-T30 -> 24.910714 | T30: =R30*U30/(U30+100) -> 2.9892857 | U30: 12 | V30: 0 | W30: 1 | X30: KS | Y30: =R30*W30 -> 27.9 | Z30: =S30*W30 -> 24.910714 | AA30: =T30*W30 -> 2.9892857 | AB30: =V30*W30 -> 0 | AC30: =(R30+V30)*W30 -> 27.9 | AD30: 27.9 | AE30: 0 | AF30: 0
A31: CZ60738677 | B31: RAPO BRNO, s.r.o. | C31: 96 | D31: BALADA - Březinky | E31: Pokladna SCO1 | F31: profikasa | G31: 46132 | H31: 0.42946759 | I31: 161000338 | J31: NE | K31: 53121264 | L31: 8594404026428 | M31: Plzeňský Prazdroj, a.s. | N31: 52101 | O31: Birell příchuť Polotmavý C | P31: NE | R31: 23.9 | S31: =R31-T31 -> 19.752066 | T31: =R31*U31/(U31+100) -> 4.1479339 | U31: 21 | V31: 0 | W31: 1 | X31: KS | Y31: =R31*W31 -> 23.9 | Z31: =S31*W31 -> 19.752066 | AA31: =T31*W31 -> 4.1479339 | AB31: =V31*W31 -> 0 | AC31: =(R31+V31)*W31 -> 23.9 | AD31: 23.9 | AE31: 0 | AF31: 0
A32: CZ60738677 | B32: RAPO BRNO, s.r.o. | C32: 96 | D32: BALADA - Březinky | E32: Pokladna SCO1 | F32: profikasa | G32: 46132 | H32: 0.42946759 | I32: 161000338 | J32: NE | K32: 60532985 | L32: 8594066791986 | M32: ČEPOS-Česká potravinářská obchodní a.s. | N32: 80306 | O32: Pytel na odpad 60l ČC 20ks | P32: NE | R32: 19.9 | S32: =R32-T32 -> 16.446281 | T32: =R32*U32/(U32+100) -> 3.453719 | U32: 21 | V32: 0 | W32: 1 | X32: KS | Y32: =R32*W32 -> 19.9 | Z32: =S32*W32 -> 16.446281 | AA32: =T32*W32 -> 3.453719 | AB32: =V32*W32 -> 0 | AC32: =(R32+V32)*W32 -> 19.9 | AD32: 19.9 | AE32: 0 | AF32: 0
A33: CZ60738677 | B33: RAPO BRNO, s.r.o. | C33: 96 | D33: BALADA - Březinky | E33: Pokladna SCO1 | F33: profikasa | G33: 46132 | H33: 0.43596065 | I33: 161000339 | J33: NE | K33: 10163951 | L33: 8588010163035 | M33: SWEETEX s.r.o | N33: 10204 | O33: Prima rolky s příchutí mer | P33: NE | R33: 37.9 | S33: =R33-T33 -> 33.839286 | T33: =R33*U33/(U33+100) -> 4.0607143 | U33: 12 | V33: 0 | W33: 1 | X33: KS | Y33: =R33*W33 -> 37.9 | Z33: =S33*W33 -> 33.839286 | AA33: =T33*W33 -> 4.0607143 | AB33: =V33*W33 -> 0 | AC33: =(R33+V33)*W33 -> 37.9 | AD33: 37.9 | AE33: 0 | AF33: 0
A34: CZ60738677 | B34: RAPO BRNO, s.r.o. | C34: 96 | D34: BALADA - Březinky | E34: Pokladna SCO1 | F34: profikasa | G34: 46132 | H34: 0.445625 | I34: 161000340 | J34: NE | K34: 90125206 | L34: 8590077430616 | M34: PENAM, a.s. | N34: 10203 | O34: Krémka 80g | P34: ANO | Q34: BALADA 26_9A | R34: 11.9 | S34: =R34-T34 -> 10.625 | T34: =R34*U34/(U34+100) -> 1.275 | U34: 12 | V34: 0 | W34: 1 | X34: KS | Y34: =R34*W34 -> 11.9 | Z34: =S34*W34 -> 10.625 | AA34: =T34*W34 -> 1.275 | AB34: =V34*W34 -> 0 | AC34: =(R34+V34)*W34 -> 11.9 | AD34: 11.9 | AE34: 0 | AF34: 0
A35: CZ60738677 | B35: RAPO BRNO, s.r.o. | C35: 96 | D35: BALADA - Březinky | E35: Pokladna SCO1 | F35: profikasa | G35: 46132 | H35: 0.445625 | I35: 161000340 | J35: NE | K35: 90385963 | L35: 8594162858866 | M35: Bidfood Czech Republic s.r.o. | N35: 10104 | O35: Kobliha s meruňkovou nápln | P35: NE | R35: 13.9 | S35: =R35-T35 -> 12.410714 | T35: =R35*U35/(U35+100) -> 1.4892857 | U35: 12 | V35: 0 | W35: 1 | X35: KS | Y35: =R35*W35 -> 13.9 | Z35: =S35*W35 -> 12.410714 | AA35: =T35*W35 -> 1.4892857 | AB35: =V35*W35 -> 0 | AC35: =(R35+V35)*W35 -> 13.9 | AD35: 13.9 | AE35: 0 | AF35: 0
A36: CZ60738677 | B36: RAPO BRNO, s.r.o. | C36: 96 | D36: BALADA - Březinky | E36: Pokladna SCO1 | F36: profikasa | G36: 46132 | H36: 0.445625 | I36: 161000340 | J36: NE | K36: 90979203 | L36: 283355 | M36: Uzenářství a lahůdky Sláma s.r.o. | N36: 30202 | O36: Bítešská klobása TOP | P36: ANO | Q36: BALADA 26_9A | R36: 169 | S36: =R36-T36 -> 150.89286 | T36: =R36*U36/(U36+100) -> 18.107143 | U36: 12 | V36: 0 | W36: 0.374 | X36: KG | Y36: =R36*W36 -> 63.206 | Z36: =S36*W36 -> 56.433929 | AA36: =T36*W36 -> 6.7720714 | AB36: =V36*W36 -> 0 | AC36: =(R36+V36)*W36 -> 63.206 | AD36: 169 | AE36: 0 | AF36: 0
A37: CZ60738677 | B37: RAPO BRNO, s.r.o. | C37: 96 | D37: BALADA - Březinky | E37: Pokladna SCO1 | F37: profikasa | G37: 46132 | H37: 0.4469213 | I37: 161000341 | J37: NE | K37: 31704300 | L37: 8594006320122 | M37: Moravia Lacto a.s. | N37: 20101 | O37: Mléko polotučné 1,5% Morav | P37: NE | R37: 27.9 | S37: =R37-T37 -> 24.910714 | T37: =R37*U37/(U37+100) -> 2.9892857 | U37: 12 | V37: 0 | W37: 1 | X37: KS | Y37: =R37*W37 -> 27.9 | Z37: =S37*W37 -> 24.910714 | AA37: =T37*W37 -> 2.9892857 | AB37: =V37*W37 -> 0 | AC37: =(R37+V37)*W37 -> 27.9 | AD37: 27.9 | AE37: 0 | AF37: 0
A38: CZ60738677 | B38: RAPO BRNO, s.r.o. | C38: 96 | D38: BALADA - Březinky | E38: Pokladna SCO1 | F38: profikasa | G38: 46132 | H38: 0.4469213 | I38: 161000341 | J38: NE | K38: 31708524 | L38: 8594003024139 | M38: Mlékárna Valašské Meziříčí, spol. s r.o. | N38: 20106 | O38: Kefírové mléko 1,1% 1l | P38: NE | R38: 21.9 | S38: =R38-T38 -> 19.553571 | T38: =R38*U38/(U38+100) -> 2.3464286 | U38: 12 | V38: 0 | W38: 1 | X38: KS | Y38: =R38*W38 -> 21.9 | Z38: =S38*W38 -> 19.553571 | AA38: =T38*W38 -> 2.3464286 | AB38: =V38*W38 -> 0 | AC38: =(R38+V38)*W38 -> 21.9 | AD38: 21.9 | AE38: 0 | AF38: 0
A39: CZ60738677 | B39: RAPO BRNO, s.r.o. | C39: 96 | D39: BALADA - Březinky | E39: Pokladna SCO1 | F39: profikasa | G39: 46132 | H39: 0.4469213 | I39: 161000341 | J39: NE | K39: 57134830 | L39: 8594042232182 | M39: ČEPOS-Česká potravinářská obchodní a.s. | N39: 80505 | O39: Ubrousky kosmetické ČC 100 | P39: NE | R39: 25.9 | S39: =R39-T39 -> 21.404959 | T39: =R39*U39/(U39+100) -> 4.4950413 | U39: 21 | V39: 0 | W39: 1 | X39: KS | Y39: =R39*W39 -> 25.9 | Z39: =S39*W39 -> 21.404959 | AA39: =T39*W39 -> 4.4950413 | AB39: =V39*W39 -> 0 | AC39: =(R39+V39)*W39 -> 25.9 | AD39: 25.9 | AE39: 0 | AF39: 0
A40: CZ60738677 | B40: RAPO BRNO, s.r.o. | C40: 96 | D40: BALADA - Březinky | E40: Pokladna SCO1 | F40: profikasa | G40: 46132 | H40: 0.44766204 | I40: 161000342 | J40: NE | K40: 31793801 | L40: 8594033405182 | M40: EKOMILK a.s. | N40: 20102 | O40: Smetana zakysaná 14% 200g | P40: NE | R40: 16.9 | S40: =R40-T40 -> 15.089286 | T40: =R40*U40/(U40+100) -> 1.8107143 | U40: 12 | V40: 0 | W40: 1 | X40: KS | Y40: =R40*W40 -> 16.9 | Z40: =S40*W40 -> 15.089286 | AA40: =T40*W40 -> 1.8107143 | AB40: =V40*W40 -> 0 | AC40: =(R40+V40)*W40 -> 16.9 | AD40: 16.9 | AE40: 0 | AF40: 0
A41: CZ60738677 | B41: RAPO BRNO, s.r.o. | C41: 96 | D41: BALADA - Březinky | E41: Pokladna SCO1 | F41: profikasa | G41: 46132 | H41: 0.44766204 | I41: 161000342 | J41: NE | K41: 90A51816 | L41: 8594015842011 | M41: ADW FOOD s.r.o. | N41: 10101 | O41: Rohlík 43g | P41: NE | R41: 2.9 | S41: =R41-T41 -> 2.5892857 | T41: =R41*U41/(U41+100) -> 0.31071429 | U41: 12 | V41: 0 | W41: 2 | X41: KS | Y41: =R41*W41 -> 5.8 | Z41: =S41*W41 -> 5.1785714 | AA41: =T41*W41 -> 0.62142857 | AB41: =V41*W41 -> 0 | AC41: =(R41+V41)*W41 -> 5.8 | AD41: 2.9 | AE41: 0 | AF41: 0
A42: CZ60738677 | B42: RAPO BRNO, s.r.o. | C42: 96 | D42: BALADA - Březinky | E42: Pokladna SCO1 | F42: profikasa | G42: 46132 | H42: 0.45103009 | I42: 161000343 | J42: NE | K42: 22105116 | L42: 8593837270521 | M42: Orkla Foods Česko a Slovensko a.s. | N42: 52502 | O42: Kuře pečené 25g | P42: NE | R42: 29.9 | S42: =R42-T42 -> 26.696429 | T42: =R42*U42/(U42+100) -> 3.2035714 | U42: 12 | V42: 0 | W42: 1 | X42: KS | Y42: =R42*W42 -> 29.9 | Z42: =S42*W42 -> 26.696429 | AA42: =T42*W42 -> 3.2035714 | AB42: =V42*W42 -> 0 | AC42: =(R42+V42)*W42 -> 29.9 | AD42: 29.9 | AE42: 0 | AF42: 0
A43: CZ60738677 | B43: RAPO BRNO, s.r.o. | C43: 96 | D43: BALADA - Březinky | E43: Pokladna SCO1 | F43: profikasa | G43: 46132 | H43: 0.45103009 | I43: 161000343 | J43: NE | K43: 90385924 | L43: 8594162852291 | M43: Bidfood Czech Republic s.r.o. | N43: 10101 | O43: Rohlík císařský 95g | P43: NE | R43: 11.9 | S43: =R43-T43 -> 10.625 | T43: =R43*U43/(U43+100) -> 1.275 | U43: 12 | V43: 0 | W43: 2 | X43: KS | Y43: =R43*W43 -> 23.8 | Z43: =S43*W43 -> 21.25 | AA43: =T43*W43 -> 2.55 | AB43: =V43*W43 -> 0 | AC43: =(R43+V43)*W43 -> 23.8 | AD43: 11.9 | AE43: 0 | AF43: 0
A44: CZ60738677 | B44: RAPO BRNO, s.r.o. | C44: 96 | D44: BALADA - Březinky | E44: Pokladna SCO1 | F44: profikasa | G44: 46132 | H44: 0.45368056 | I44: 161000344 | J44: NE | K44: 24732539 | L44: 8594060910192 | M44: GoodMills Česko s.r.o. | N44: 52001 | O44: Mouka hrubá Babiččina volb | P44: NE | R44: 29.9 | S44: =R44-T44 -> 26.696429 | T44: =R44*U44/(U44+100) -> 3.2035714 | U44: 12 | V44: 0 | W44: 1 | X44: KS | Y44: =R44*W44 -> 29.9 | Z44: =S44*W44 -> 26.696429 | AA44: =T44*W44 -> 3.2035714 | AB44: =V44*W44 -> 0 | AC44: =(R44+V44)*W44 -> 29.9 | AD44: 29.9 | AE44: 0 | AF44: 0
A45: CZ60738677 | B45: RAPO BRNO, s.r.o. | C45: 96 | D45: BALADA - Březinky | E45: Pokladna SCO1 | F45: profikasa | G45: 46132 | H45: 0.45368056 | I45: 161000344 | J45: NE | K45: 90125206 | L45: 8590077430616 | M45: PENAM, a.s. | N45: 10203 | O45: Krémka 80g | P45: ANO | Q45: BALADA 26_9A | R45: 11.9 | S45: =R45-T45 -> 10.625 | T45: =R45*U45/(U45+100) -> 1.275 | U45: 12 | V45: 0 | W45: 1 | X45: KS | Y45: =R45*W45 -> 11.9 | Z45: =S45*W45 -> 10.625 | AA45: =T45*W45 -> 1.275 | AB45: =V45*W45 -> 0 | AC45: =(R45+V45)*W45 -> 11.9 | AD45: 11.9 | AE45: 0 | AF45: 0
A46: CZ60738677 | B46: RAPO BRNO, s.r.o. | C46: 96 | D46: BALADA - Březinky | E46: Pokladna SCO1 | F46: profikasa | G46: 46132 | H46: 0.45368056 | I46: 161000344 | J46: NE | K46: 90A51816 | L46: 8594015842011 | M46: ADW FOOD s.r.o. | N46: 10101 | O46: Rohlík 43g | P46: NE | R46: 2.9 | S46: =R46-T46 -> 2.5892857 | T46: =R46*U46/(U46+100) -> 0.31071429 | U46: 12 | V46: 0 | W46: 2 | X46: KS | Y46: =R46*W46 -> 5.8 | Z46: =S46*W46 -> 5.1785714 | AA46: =T46*W46 -> 0.62142857 | AB46: =V46*W46 -> 0 | AC46: =(R46+V46)*W46 -> 5.8 | AD46: 2.9 | AE46: 0 | AF46: 0
A47: CZ60738677 | B47: RAPO BRNO, s.r.o. | C47: 96 | D47: BALADA - Březinky | E47: Pokladna SCO1 | F47: profikasa | G47: 46132 | H47: 0.4602662 | I47: 161000345 | J47: NE | K47: 15107331 | L47: 4006067868474 | M47: Tchibo Praha, spol. s.r.o. | N47: 50302 | O47: Jihlavanka Staročeská směs | P47: NE | R47: 45.9 | S47: =R47-T47 -> 40.982143 | T47: =R47*U47/(U47+100) -> 4.9178571 | U47: 12 | V47: 0 | W47: 1 | X47: KS | Y47: =R47*W47 -> 45.9 | Z47: =S47*W47 -> 40.982143 | AA47: =T47*W47 -> 4.9178571 | AB47: =V47*W47 -> 0 | AC47: =(R47+V47)*W47 -> 45.9 | AD47: 45.9 | AE47: 0 | AF47: 0
A48: CZ60738677 | B48: RAPO BRNO, s.r.o. | C48: 96 | D48: BALADA - Březinky | E48: Pokladna SCO1 | F48: profikasa | G48: 46132 | H48: 0.4602662 | I48: 161000345 | J48: NE | K48: 31699561 | L48: 8594008270012 | M48: Savencia Fromage & Dairy Czech Republic, a.s. | N48: 20108 | O48: Sedlčanský Hermelín 100g | P48: NE | R48: 39.9 | S48: =R48-T48 -> 35.625 | T48: =R48*U48/(U48+100) -> 4.275 | U48: 12 | V48: 0 | W48: 1 | X48: KS | Y48: =R48*W48 -> 39.9 | Z48: =S48*W48 -> 35.625 | AA48: =T48*W48 -> 4.275 | AB48: =V48*W48 -> 0 | AC48: =(R48+V48)*W48 -> 39.9 | AD48: 39.9 | AE48: 0 | AF48: 0
A49: CZ60738677 | B49: RAPO BRNO, s.r.o. | C49: 96 | D49: BALADA - Březinky | E49: Pokladna SCO1 | F49: profikasa | G49: 46132 | H49: 0.4602662 | I49: 161000345 | J49: NE | K49: 45116338 | L49: 8595723202296 | M49: Mattoni 1873 a.s. | N49: 52202 | O49: Mattoni Imuno hruška&marak | P49: NE | R49: 24.9 | S49: =R49-T49 -> 20.578512 | T49: =R49*U49/(U49+100) -> 4.3214876 | U49: 21 | V49: 0 | W49: 1 | X49: KS | Y49: =R49*W49 -> 24.9 | Z49: =S49*W49 -> 20.578512 | AA49: =T49*W49 -> 4.3214876 | AB49: =V49*W49 -> 0 | AC49: =(R49+V49)*W49 -> 24.9 | AD49: 24.9 | AE49: 0 | AF49: 0
A50: CZ60738677 | B50: RAPO BRNO, s.r.o. | C50: 96 | D50: BALADA - Březinky | E50: Pokladna SCO1 | F50: profikasa | G50: 46132 | H50: 0.48071759 | I50: 161000346 | J50: NE | K50: 34114115 | L50: 8594000770039 | M50: KAUMY Czechia s.r.o. | N50: 51802 | O50: Hořčice kremžská ČC 200g | P50: NE | R50: 8.4 | S50: =R50-T50 -> 7.5 | T50: =R50*U50/(U50+100) -> 0.9 | U50: 12 | V50: 0 | W50: 1 | X50: KS | Y50: =R50*W50 -> 8.4 | Z50: =S50*W50 -> 7.5 | AA50: =T50*W50 -> 0.9 | AB50: =V50*W50 -> 0 | AC50: =(R50+V50)*W50 -> 8.4 | AD50: 8.4 | AE50: 0 | AF50: 0
A51: CZ60738677 | B51: RAPO BRNO, s.r.o. | C51: 96 | D51: BALADA - Březinky | E51: Pokladna SCO1 | F51: profikasa | G51: 46132 | H51: 0.49940972 | I51: 161000347 | J51: NE | K51: 32397900 | L51: 8590047900026 | M51: ČEPOS-Česká potravinářská obchodní a.s. | N51: 20206 | O51: Pohodová Vejce M 10ks ČC 1 | P51: NE | R51: 49.9 | S51: =R51-T51 -> 44.553571 | T51: =R51*U51/(U51+100) -> 5.3464286 | U51: 12 | V51: 0 | W51: 1 | X51: KS | Y51: =R51*W51 -> 49.9 | Z51: =S51*W51 -> 44.553571 | AA51: =T51*W51 -> 5.3464286 | AB51: =V51*W51 -> 0 | AC51: =(R51+V51)*W51 -> 49.9 | AD51: 49.9 | AE51: 0 | AF51: 0
A52: CZ60738677 | B52: RAPO BRNO, s.r.o. | C52: 96 | D52: BALADA - Březinky | E52: Pokladna SCO1 | F52: profikasa | G52: 46132 | H52: 0.49940972 | I52: 161000347 | J52: NE | K52: 34114160 | L52: 8594000771838 | M52: KAUMY Czechia s.r.o. | N52: 51802 | O52: Hořčice plnotučná ČC 200g | P52: NE | R52: 6.9 | S52: =R52-T52 -> 6.1607143 | T52: =R52*U52/(U52+100) -> 0.73928571 | U52: 12 | V52: 0 | W52: 1 | X52: KS | Y52: =R52*W52 -> 6.9 | Z52: =S52*W52 -> 6.1607143 | AA52: =T52*W52 -> 0.73928571 | AB52: =V52*W52 -> 0 | AC52: =(R52+V52)*W52 -> 6.9 | AD52: 6.9 | AE52: 0 | AF52: 0
A53: CZ60738677 | B53: RAPO BRNO, s.r.o. | C53: 96 | D53: BALADA - Březinky | E53: Pokladna SCO1 | F53: profikasa | G53: 46132 | H53: 0.49940972 | I53: 161000347 | J53: NE | K53: 68356072 | L53: 287508 | M53: ČEROZFRUCHT České Budějovice | N53: 70202 | O53: Cibule | P53: NE | R53: 11.9 | S53: =R53-T53 -> 10.625 | T53: =R53*U53/(U53+100) -> 1.275 | U53: 12 | V53: 0 | W53: 0.924 | X53: KG | Y53: =R53*W53 -> 10.9956 | Z53: =S53*W53 -> 9.8175 | AA53: =T53*W53 -> 1.1781 | AB53: =V53*W53 -> 0 | AC53: =(R53+V53)*W53 -> 10.9956 | AD53: 11.9 | AE53: 0 | AF53: 0
A54: CZ60738677 | B54: RAPO BRNO, s.r.o. | C54: 96 | D54: BALADA - Březinky | E54: Pokladna SCO1 | F54: profikasa | G54: 46132 | H54: 0.50226852 | I54: 161000348 | J54: NE | K54: 45115942 | L54: 8595231219458 | M54: Kofola a.s. | N54: 52202 | O54: Jupík Aqua příchuť malina | P54: NE | R54: 18.9 | S54: =R54-T54 -> 15.619835 | T54: =R54*U54/(U54+100) -> 3.2801653 | U54: 21 | V54: 0 | W54: 1 | X54: KS | Y54: =R54*W54 -> 18.9 | Z54: =S54*W54 -> 15.619835 | AA54: =T54*W54 -> 3.2801653 | AB54: =V54*W54 -> 0 | AC54: =(R54+V54)*W54 -> 18.9 | AD54: 18.9 | AE54: 0 | AF54: 0
A55: CZ60738677 | B55: RAPO BRNO, s.r.o. | C55: 96 | D55: BALADA - Březinky | E55: Pokladna SCO1 | F55: profikasa | G55: 46132 | H55: 0.50226852 | I55: 161000348 | J55: NE | K55: 45116304 | L55: 8594001026364 | M55: Mattoni 1873 a.s. | N55: 52202 | O55: Magnesia Plus Revital hroz | P55: ANO | Q55: BALADA 26_9A | R55: 24.9 | S55: =R55-T55 -> 20.578512 | T55: =R55*U55/(U55+100) -> 4.3214876 | U55: 21 | V55: 0 | W55: 1 | X55: KS | Y55: =R55*W55 -> 24.9 | Z55: =S55*W55 -> 20.578512 | AA55: =T55*W55 -> 4.3214876 | AB55: =V55*W55 -> 0 | AC55: =(R55+V55)*W55 -> 24.9 | AD55: 24.9 | AE55: 0 | AF55: 0
A56: CZ60738677 | B56: RAPO BRNO, s.r.o. | C56: 96 | D56: BALADA - Březinky | E56: Pokladna SCO1 | F56: profikasa | G56: 46132 | H56: 0.51219907 | I56: 161000349 | J56: NE | K56: 14153660 | L56: 5903839701825 | M56: FS IMPORT- EXPORT s.r.o. | N56: 51003 | O56: Pat Mat želé kyselé 70g | P56: NE | R56: 14.9 | S56: =R56-T56 -> 13.303571 | T56: =R56*U56/(U56+100) -> 1.5964286 | U56: 12 | V56: 0 | W56: 1 | X56: KS | Y56: =R56*W56 -> 14.9 | Z56: =S56*W56 -> 13.303571 | AA56: =T56*W56 -> 1.5964286 | AB56: =V56*W56 -> 0 | AC56: =(R56+V56)*W56 -> 14.9 | AD56: 14.9 | AE56: 0 | AF56: 0
A57: CZ60738677 | B57: RAPO BRNO, s.r.o. | C57: 96 | D57: BALADA - Březinky | E57: Pokladna SCO1 | F57: profikasa | G57: 46132 | H57: 0.51219907 | I57: 161000349 | J57: NE | K57: 48141253 | L57: 4003490069089 | M57: ALIMPEX FOOD a.s. | N57: 50306 | O57: Eiskaffee Ledová káva 1,1% | P57: NE | R57: 27.9 | S57: =R57-T57 -> 23.057851 | T57: =R57*U57/(U57+100) -> 4.8421488 | U57: 21 | V57: 0 | W57: 1 | X57: KS | Y57: =R57*W57 -> 27.9 | Z57: =S57*W57 -> 23.057851 | AA57: =T57*W57 -> 4.8421488 | AB57: =V57*W57 -> 0 | AC57: =(R57+V57)*W57 -> 27.9 | AD57: 27.9 | AE57: 0 | AF57: 0
A58: CZ60738677 | B58: RAPO BRNO, s.r.o. | C58: 96 | D58: BALADA - Březinky | E58: Pokladna SCO1 | F58: profikasa | G58: 46132 | H58: 0.51840278 | I58: 161000350 | J58: NE | K58: 10153420 | L58: 8588005524049 | M58: FS IMPORT- EXPORT s.r.o. | N58: 10204 | O58: Alaska bezlepková trubička | P58: NE | R58: 4.5 | S58: =R58-T58 -> 4.0178571 | T58: =R58*U58/(U58+100) -> 0.48214286 | U58: 12 | V58: 0 | W58: 1 | X58: KS | Y58: =R58*W58 -> 4.5 | Z58: =S58*W58 -> 4.0178571 | AA58: =T58*W58 -> 0.48214286 | AB58: =V58*W58 -> 0 | AC58: =(R58+V58)*W58 -> 4.5 | AD58: 4.5 | AE58: 0 | AF58: 0
A59: CZ60738677 | B59: RAPO BRNO, s.r.o. | C59: 96 | D59: BALADA - Březinky | E59: Pokladna SCO1 | F59: profikasa | G59: 46132 | H59: 0.51840278 | I59: 161000350 | J59: NE | K59: 48115103 | L59: 4000177408100 | M59: VITAR, s.r.o. | N59: 52204 | O59: Capri Sonne Mystic dragon | P59: NE | R59: 11.4 | S59: =R59-T59 -> 9.4214876 | T59: =R59*U59/(U59+100) -> 1.9785124 | U59: 21 | V59: 0 | W59: 1 | X59: KS | Y59: =R59*W59 -> 11.4 | Z59: =S59*W59 -> 9.4214876 | AA59: =T59*W59 -> 1.9785124 | AB59: =V59*W59 -> 0 | AC59: =(R59+V59)*W59 -> 11.4 | AD59: 11.4 | AE59: 0 | AF59: 0
A60: CZ60738677 | B60: RAPO BRNO, s.r.o. | C60: 96 | D60: BALADA - Březinky | E60: Pokladna SCO1 | F60: profikasa | G60: 46132 | H60: 0.54243056 | I60: 161000351 | J60: NE | K60: 34225116 | L60: 8595003415514 | M60: Spak Foods s.r.o. | N60: 51801 | O60: Gourmet Ketchup jemný 500g | P60: NE | R60: 44.9 | S60: =R60-T60 -> 40.089286 | T60: =R60*U60/(U60+100) -> 4.8107143 | U60: 12 | V60: 0 | W60: 1 | X60: KS | Y60: =R60*W60 -> 44.9 | Z60: =S60*W60 -> 40.089286 | AA60: =T60*W60 -> 4.8107143 | AB60: =V60*W60 -> 0 | AC60: =(R60+V60)*W60 -> 44.9 | AD60: 44.9 | AE60: 0 | AF60: 0
A61: CZ60738677 | B61: RAPO BRNO, s.r.o. | C61: 96 | D61: BALADA - Březinky | E61: Pokladna SCO1 | F61: profikasa | G61: 46132 | H61: 0.54243056 | I61: 161000351 | J61: NE | K61: 90862288 | L61: 283374 | M61: MP Krásno, a.s. | N61: 30202 | O61: Klobása Maďarka | P61: NE | R61: 344.9 | S61: =R61-T61 -> 307.94643 | T61: =R61*U61/(U61+100) -> 36.953571 | U61: 12 | V61: 0 | W61: 0.106 | X61: KG | Y61: =R61*W61 -> 36.5594 | Z61: =S61*W61 -> 32.642321 | AA61: =T61*W61 -> 3.9170786 | AB61: =V61*W61 -> 0 | AC61: =(R61+V61)*W61 -> 36.5594 | AD61: 344.9 | AE61: 0 | AF61: 0
A62: CZ60738677 | B62: RAPO BRNO, s.r.o. | C62: 96 | D62: BALADA - Březinky | E62: Pokladna SCO1 | F62: profikasa | G62: 46132 | H62: 0.54243056 | I62: 161000351 | J62: NE | K62: 90979400 | L62: 283345 | M62: Uzenářství a lahůdky Sláma s.r.o. | N62: 30201 | O62: Bítešské párky | P62: NE | R62: 208.9 | S62: =R62-T62 -> 186.51786 | T62: =R62*U62/(U62+100) -> 22.382143 | U62: 12 | V62: 0 | W62: 0.306 | X62: KG | Y62: =R62*W62 -> 63.9234 | Z62: =S62*W62 -> 57.074464 | AA62: =T62*W62 -> 6.8489357 | AB62: =V62*W62 -> 0 | AC62: =(R62+V62)*W62 -> 63.9234 | AD62: 208.9 | AE62: 0 | AF62: 0
A63: CZ60738677 | B63: RAPO BRNO, s.r.o. | C63: 96 | D63: BALADA - Březinky | E63: Pokladna SCO1 | F63: profikasa | G63: 46132 | H63: 0.54577546 | I63: 161000352 | J63: NE | K63: 45116312 | L63: 8594001022434 | M63: Mattoni 1873 a.s. | N63: 52202 | O63: Magnesia Red jahoda 2l | P63: NE | R63: 29.9 | S63: =R63-T63 -> 24.710744 | T63: =R63*U63/(U63+100) -> 5.1892562 | U63: 21 | V63: 0 | W63: 1 | X63: KS | Y63: =R63*W63 -> 29.9 | Z63: =S63*W63 -> 24.710744 | AA63: =T63*W63 -> 5.1892562 | AB63: =V63*W63 -> 0 | AC63: =(R63+V63)*W63 -> 29.9 | AD63: 29.9 | AE63: 0 | AF63: 0
A64: CZ60738677 | B64: RAPO BRNO, s.r.o. | C64: 96 | D64: BALADA - Březinky | E64: Pokladna SCO1 | F64: profikasa | G64: 46132 | H64: 0.54741898 | I64: 161000353 | J64: NE | K64: 10153400 | L64: 8588005524018 | M64: FS IMPORT- EXPORT s.r.o. | N64: 10204 | O64: Alaska bezlepková trubička | P64: NE | R64: 4.5 | S64: =R64-T64 -> 4.0178571 | T64: =R64*U64/(U64+100) -> 0.48214286 | U64: 12 | V64: 0 | W64: 1 | X64: KS | Y64: =R64*W64 -> 4.5 | Z64: =S64*W64 -> 4.0178571 | AA64: =T64*W64 -> 0.48214286 | AB64: =V64*W64 -> 0 | AC64: =(R64+V64)*W64 -> 4.5 | AD64: 4.5 | AE64: 0 | AF64: 0
A65: CZ60738677 | B65: RAPO BRNO, s.r.o. | C65: 96 | D65: BALADA - Březinky | E65: Pokladna SCO1 | F65: profikasa | G65: 46132 | H65: 0.54741898 | I65: 161000353 | J65: NE | K65: 10153430 | L65: 8588005524100 | M65: FS IMPORT- EXPORT s.r.o. | N65: 10204 | O65: Alaska bezlepková trubička | P65: NE | R65: 4.5 | S65: =R65-T65 -> 4.0178571 | T65: =R65*U65/(U65+100) -> 0.48214286 | U65: 12 | V65: 0 | W65: 1 | X65: KS | Y65: =R65*W65 -> 4.5 | Z65: =S65*W65 -> 4.0178571 | AA65: =T65*W65 -> 0.48214286 | AB65: =V65*W65 -> 0 | AC65: =(R65+V65)*W65 -> 4.5 | AD65: 4.5 | AE65: 0 | AF65: 0
A66: CZ60738677 | B66: RAPO BRNO, s.r.o. | C66: 96 | D66: BALADA - Březinky | E66: Pokladna SCO1 | F66: profikasa | G66: 46132 | H66: 0.54741898 | I66: 161000353 | J66: NE | K66: 10C77193 | L66: 8001585010783 | M66: SILISAN, spol. s r.o. | N66: 10204 | O66: Balconi Mix Milk Buonissim | P66: NE | R66: 6.9 | S66: =R66-T66 -> 6.1607143 | T66: =R66*U66/(U66+100) -> 0.73928571 | U66: 12 | V66: 0 | W66: 1 | X66: KS | Y66: =R66*W66 -> 6.9 | Z66: =S66*W66 -> 6.1607143 | AA66: =T66*W66 -> 0.73928571 | AB66: =V66*W66 -> 0 | AC66: =(R66+V66)*W66 -> 6.9 | AD66: 6.9 | AE66: 0 | AF66: 0
A67: CZ60738677 | B67: RAPO BRNO, s.r.o. | C67: 96 | D67: BALADA - Březinky | E67: Pokladna SCO1 | F67: profikasa | G67: 46132 | H67: 0.54741898 | I67: 161000353 | J67: NE | K67: 45170321 | L67: 8594008040509 | M67: KMV BEV CZ s.r.o. | N67: 52206 | O67: Pepsi 500ml | P67: NE | R67: 29.9 | S67: =R67-T67 -> 24.710744 | T67: =R67*U67/(U67+100) -> 5.1892562 | U67: 21 | V67: 0 | W67: 1 | X67: KS | Y67: =R67*W67 -> 29.9 | Z67: =S67*W67 -> 24.710744 | AA67: =T67*W67 -> 5.1892562 | AB67: =V67*W67 -> 0 | AC67: =(R67+V67)*W67 -> 29.9 | AD67: 29.9 | AE67: 0 | AF67: 0
... A69: CZ60738677 | B69: RAPO BRNO, s.r.o. | C69: 96 | D69: BALADA - Březinky | E69: Pokladna SCO1 | F69: profikasa | G69: 46132 | H69: 0.56099537 | I69: 161000354 | J69: NE | K69: 48248102 | L69: 9002490200077 | M69: RED BULL Česká republika, s.r.o. | N69: 52209 | O69: Red Bull Energy drink 250m | P69: NE | R69: 41.9 | S69: =R69-T69 -> 34.628099 | T69: =R69*U69/(U69+100) -> 7.2719008 | U69: 21 | V69: 0 | W69: 1 | X69: KS | Y69: =R69*W69 -> 41.9 | Z69: =S69*W69 -> 34.628099 | AA69: =T69*W69 -> 7.2719008 | AB69: =V69*W69 -> 0 | AC69: =(R69+V69)*W69 -> 41.9 | AD69: 41.9 | AE69: 0 | AF69: 0
A70: CZ60738677 | B70: RAPO BRNO, s.r.o. | C70: 96 | D70: BALADA - Březinky | E70: Pokladna SCO1 | F70: profikasa | G70: 46132 | H70: 0.5630787 | I70: 161000355 | J70: NE | K70: 48B40150 | L70: 5999860497073 | M70: Hell Energy Drinks Czech s.r.o. | N70: 50306 | O70: Ice Coffee Latte 250ml | P70: ANO | Q70: BALADA 26_9A | R70: 26.9 | S70: =R70-T70 -> 22.231405 | T70: =R70*U70/(U70+100) -> 4.668595 | U70: 21 | V70: 0 | W70: 1 | X70: KS | Y70: =R70*W70 -> 26.9 | Z70: =S70*W70 -> 22.231405 | AA70: =T70*W70 -> 4.668595 | AB70: =V70*W70 -> 0 | AC70: =(R70+V70)*W70 -> 26.9 | AD70: 26.9 | AE70: 0 | AF70: 0
A71: CZ60738677 | B71: RAPO BRNO, s.r.o. | C71: 96 | D71: BALADA - Březinky | E71: Pokladna SCO1 | F71: profikasa | G71: 46132 | H71: 0.5630787 | I71: 161000355 | J71: NE | K71: 66864300 | L71: 283022 | M71: Krahulík-MASOZÁVOD Krahulčí, a.s. | N71: 51005 | O71: Játrová cihla česká cena | P71: NE | R71: 169.9 | S71: =R71-T71 -> 151.69643 | T71: =R71*U71/(U71+100) -> 18.203571 | U71: 12 | V71: 0 | W71: 0.118 | X71: KG | Y71: =R71*W71 -> 20.0482 | Z71: =S71*W71 -> 17.900179 | AA71: =T71*W71 -> 2.1480214 | AB71: =V71*W71 -> 0 | AC71: =(R71+V71)*W71 -> 20.0482 | AD71: 169.9 | AE71: 0 | AF71: 0
A72: CZ60738677 | B72: RAPO BRNO, s.r.o. | C72: 96 | D72: BALADA - Březinky | E72: Pokladna SCO1 | F72: profikasa | G72: 46132 | H72: 0.5630787 | I72: 161000355 | J72: NE | K72: 90385924 | L72: 8594162852291 | M72: Bidfood Czech Republic s.r.o. | N72: 10101 | O72: Rohlík císařský 95g | P72: NE | R72: 11.9 | S72: =R72-T72 -> 10.625 | T72: =R72*U72/(U72+100) -> 1.275 | U72: 12 | V72: 0 | W72: 2 | X72: KS | Y72: =R72*W72 -> 23.8 | Z72: =S72*W72 -> 21.25 | AA72: =T72*W72 -> 2.55 | AB72: =V72*W72 -> 0 | AC72: =(R72+V72)*W72 -> 23.8 | AD72: 11.9 | AE72: 0 | AF72: 0
A73: CZ60738677 | B73: RAPO BRNO, s.r.o. | C73: 96 | D73: BALADA - Březinky | E73: Pokladna SCO1 | F73: profikasa | G73: 46132 | H73: 0.5630787 | I73: 161000355 | J73: NE | K73: C000038 | L73: 284017 | M73: Uzenářství a lahůdky Sláma s.r.o. | N73: 30502 | O73: Tuňáková pomazánka | P73: NE | R73: 259.9 | S73: =R73-T73 -> 232.05357 | T73: =R73*U73/(U73+100) -> 27.846429 | U73: 12 | V73: 0 | W73: 0.126 | X73: kg | Y73: =R73*W73 -> 32.7474 | Z73: =S73*W73 -> 29.23875 | AA73: =T73*W73 -> 3.50865 | AB73: =V73*W73 -> 0 | AC73: =(R73+V73)*W73 -> 32.7474 | AD73: 259.9 | AE73: 0 | AF73: 0
A74: CZ60738677 | B74: RAPO BRNO, s.r.o. | C74: 96 | D74: BALADA - Březinky | E74: Pokladna SCO1 | F74: profikasa | G74: 46132 | H74: 0.56574074 | I74: 161000356 | J74: NE | K74: 28962432 | L74: 8594174210089 | M74: HOKA TRADE s.r.o. | N74: 52402 | O74: Instantní nudlová polévka | P74: NE | R74: 12.4 | S74: =R74-T74 -> 11.071429 | T74: =R74*U74/(U74+100) -> 1.3285714 | U74: 12 | V74: 0 | W74: 1 | X74: KS | Y74: =R74*W74 -> 12.4 | Z74: =S74*W74 -> 11.071429 | AA74: =T74*W74 -> 1.3285714 | AB74: =V74*W74 -> 0 | AC74: =(R74+V74)*W74 -> 12.4 | AD74: 12.4 | AE74: 0 | AF74: 0
A75: CZ60738677 | B75: RAPO BRNO, s.r.o. | C75: 96 | D75: BALADA - Březinky | E75: Pokladna SCO1 | F75: profikasa | G75: 46132 | H75: 0.56956019 | I75: 161000357 | J75: NE | K75: 90385037 | L75: 5902054001024 | M75: Bidfood Czech Republic s.r.o. | N75: 10106 | O75: Kornbageta fitness 28 cm 1 | P75: NE | R75: 19.9 | S75: =R75-T75 -> 17.767857 | T75: =R75*U75/(U75+100) -> 2.1321429 | U75: 12 | V75: 0 | W75: 1 | X75: KS | Y75: =R75*W75 -> 19.9 | Z75: =S75*W75 -> 17.767857 | AA75: =T75*W75 -> 2.1321429 | AB75: =V75*W75 -> 0 | AC75: =(R75+V75)*W75 -> 19.9 | AD75: 19.9 | AE75: 0 | AF75: 0
A76: CZ60738677 | B76: RAPO BRNO, s.r.o. | C76: 96 | D76: BALADA - Březinky | E76: Pokladna SCO1 | F76: profikasa | G76: 46132 | H76: 0.57478009 | I76: 161000358 | J76: NE | K76: 45116302 | L76: 8594001021758 | M76: Mattoni 1873 a.s. | N76: 52202 | O76: Magnesia neperlivá 2l | P76: NE | R76: 19.9 | S76: =R76-T76 -> 16.446281 | T76: =R76*U76/(U76+100) -> 3.453719 | U76: 21 | V76: 0 | W76: 1 | X76: KS | Y76: =R76*W76 -> 19.9 | Z76: =S76*W76 -> 16.446281 | AA76: =T76*W76 -> 3.453719 | AB76: =V76*W76 -> 0 | AC76: =(R76+V76)*W76 -> 19.9 | AD76: 19.9 | AE76: 0 | AF76: 0
A77: CZ60738677 | B77: RAPO BRNO, s.r.o. | C77: 96 | D77: BALADA - Březinky | E77: Pokladna SCO1 | F77: profikasa | G77: 46132 | H77: 0.58325231 | I77: 161000359 | J77: NE | K77: 21C10904 | L77: 4820200894959 | M77: Charlock s.r.o. | N77: 50201 | O77: Proteline tyčinka s čokolá | P77: NE | R77: 15.9 | S77: =R77-T77 -> 14.196429 | T77: =R77*U77/(U77+100) -> 1.7035714 | U77: 12 | V77: 0 | W77: 1 | X77: KS | Y77: =R77*W77 -> 15.9 | Z77: =S77*W77 -> 14.196429 | AA77: =T77*W77 -> 1.7035714 | AB77: =V77*W77 -> 0 | AC77: =(R77+V77)*W77 -> 15.9 | AD77: 15.9 | AE77: 0 | AF77: 0
A78: CZ60738677 | B78: RAPO BRNO, s.r.o. | C78: 96 | D78: BALADA - Březinky | E78: Pokladna SCO1 | F78: profikasa | G78: 46132 | H78: 0.59230324 | I78: 161000360 | J78: NE | K78: 12101442 | L78: 3800020418772 | M78: Nestlé Česko | N78: 51101 | O78: Kit Kat Chunky Peanut butt | P78: NE | R78: 19.9 | S78: =R78-T78 -> 17.767857 | T78: =R78*U78/(U78+100) -> 2.1321429 | U78: 12 | V78: 0 | W78: 1 | X78: KS | Y78: =R78*W78 -> 19.9 | Z78: =S78*W78 -> 17.767857 | AA78: =T78*W78 -> 2.1321429 | AB78: =V78*W78 -> 0 | AC78: =(R78+V78)*W78 -> 19.9 | AD78: 19.9 | AE78: 0 | AF78: 0
A79: CZ60738677 | B79: RAPO BRNO, s.r.o. | C79: 96 | D79: BALADA - Březinky | E79: Pokladna SCO1 | F79: profikasa | G79: 46132 | H79: 0.59230324 | I79: 161000360 | J79: NE | K79: 90125252 | L79: 8590077322409 | M79: PENAM, a.s. | N79: 10102 | O79: Chléb Beskyd BK 500g | P79: NE | R79: 37.9 | S79: =R79-T79 -> 33.839286 | T79: =R79*U79/(U79+100) -> 4.0607143 | U79: 12 | V79: 0 | W79: 1 | X79: KS | Y79: =R79*W79 -> 37.9 | Z79: =S79*W79 -> 33.839286 | AA79: =T79*W79 -> 4.0607143 | AB79: =V79*W79 -> 0 | AC79: =(R79+V79)*W79 -> 37.9 | AD79: 37.9 | AE79: 0 | AF79: 0
A80: CZ60738677 | B80: RAPO BRNO, s.r.o. | C80: 96 | D80: BALADA - Březinky | E80: Pokladna SCO1 | F80: profikasa | G80: 46132 | H80: 0.60278935 | I80: 161000361 | J80: NE | K80: 11170384 | L80: 5900259128515 | M80: KMV BEV CZ s.r.o. | N80: 50101 | O80: Lays Stix s příchutí Ketch | P80: NE | R80: 49.9 | S80: =R80-T80 -> 44.553571 | T80: =R80*U80/(U80+100) -> 5.3464286 | U80: 12 | V80: 0 | W80: 1 | X80: KS | Y80: =R80*W80 -> 49.9 | Z80: =S80*W80 -> 44.553571 | AA80: =T80*W80 -> 5.3464286 | AB80: =V80*W80 -> 0 | AC80: =(R80+V80)*W80 -> 49.9 | AD80: 49.9 | AE80: 0 | AF80: 0
A81: CZ60738677 | B81: RAPO BRNO, s.r.o. | C81: 96 | D81: BALADA - Březinky | E81: Pokladna SCO1 | F81: profikasa | G81: 46132 | H81: 0.60278935 | I81: 161000361 | J81: NE | K81: 90933875 | L81: 8594005320574 | M81: ČEPOS-Česká potravinářská obchodní a.s. | N81: 30101 | O81: Šunka dušená standard ČC 1 | P81: NE | R81: 27.9 | S81: =R81-T81 -> 24.910714 | T81: =R81*U81/(U81+100) -> 2.9892857 | U81: 12 | V81: 0 | W81: 1 | X81: KS | Y81: =R81*W81 -> 27.9 | Z81: =S81*W81 -> 24.910714 | AA81: =T81*W81 -> 2.9892857 | AB81: =V81*W81 -> 0 | AC81: =(R81+V81)*W81 -> 27.9 | AD81: 27.9 | AE81: 0 | AF81: 0
A82: CZ60738677 | B82: RAPO BRNO, s.r.o. | C82: 96 | D82: BALADA - Březinky | E82: Pokladna SCO1 | F82: profikasa | G82: 46132 | H82: 0.60641204 | I82: 161000362 | J82: NE | K82: 31122117 | L82: 8594006845380 | M82: Mlékárna Hlinsko, a.s. | N82: 50404 | O82: Tatra mléko 1,5% 500ml | P82: NE | R82: 19.9 | S82: =R82-T82 -> 17.767857 | T82: =R82*U82/(U82+100) -> 2.1321429 | U82: 12 | V82: 0 | W82: 1 | X82: KS | Y82: =R82*W82 -> 19.9 | Z82: =S82*W82 -> 17.767857 | AA82: =T82*W82 -> 2.1321429 | AB82: =V82*W82 -> 0 | AC82: =(R82+V82)*W82 -> 19.9 | AD82: 19.9 | AE82: 0 | AF82: 0
A83: CZ60738677 | B83: RAPO BRNO, s.r.o. | C83: 96 | D83: BALADA - Březinky | E83: Pokladna SCO1 | F83: profikasa | G83: 46132 | H83: 0.60641204 | I83: 161000362 | J83: NE | K83: 31775598 | L83: 4014500515571 | M83: Zott s.r.o. | N83: 20112 | O83: Zott Monte White 150g | P83: ANO | Q83: BALADA 26_9A | R83: 19.9 | S83: =R83-T83 -> 17.767857 | T83: =R83*U83/(U83+100) -> 2.1321429 | U83: 12 | V83: 0 | W83: 2 | X83: KS | Y83: =R83*W83 -> 39.8 | Z83: =S83*W83 -> 35.535714 | AA83: =T83*W83 -> 4.2642857 | AB83: =V83*W83 -> 0 | AC83: =(R83+V83)*W83 -> 39.8 | AD83: 19.9 | AE83: 0 | AF83: 0
A84: CZ60738677 | B84: RAPO BRNO, s.r.o. | C84: 96 | D84: BALADA - Březinky | E84: Pokladna SCO1 | F84: profikasa | G84: 46132 | H84: 0.60641204 | I84: 161000362 | J84: NE | K84: 34112181 | L84: 8595139720483 | M84: Orkla Foods Česko a Slovensko a.s. | N84: 51801 | O84: Kečup sladký Česká cena 30 | P84: NE | R84: 24.9 | S84: =R84-T84 -> 22.232143 | T84: =R84*U84/(U84+100) -> 2.6678571 | U84: 12 | V84: 0 | W84: 1 | X84: KS | Y84: =R84*W84 -> 24.9 | Z84: =S84*W84 -> 22.232143 | AA84: =T84*W84 -> 2.6678571 | AB84: =V84*W84 -> 0 | AC84: =(R84+V84)*W84 -> 24.9 | AD84: 24.9 | AE84: 0 | AF84: 0
A85: CZ60738677 | B85: RAPO BRNO, s.r.o. | C85: 96 | D85: BALADA - Březinky | E85: Pokladna SCO1 | F85: profikasa | G85: 46132 | H85: 0.60641204 | I85: 161000362 | J85: NE | K85: 68356049 | L85: 287501 | M85: ČEROZFRUCHT České Budějovice | N85: 70202 | O85: Batáty | P85: NE | R85: 49.9 | S85: =R85-T85 -> 44.553571 | T85: =R85*U85/(U85+100) -> 5.3464286 | U85: 12 | V85: 0 | W85: 0.778 | X85: KG | Y85: =R85*W85 -> 38.8222 | Z85: =S85*W85 -> 34.662679 | AA85: =T85*W85 -> 4.1595214 | AB85: =V85*W85 -> 0 | AC85: =(R85+V85)*W85 -> 38.8222 | AD85: 49.9 | AE85: 0 | AF85: 0
A86: CZ60738677 | B86: RAPO BRNO, s.r.o. | C86: 96 | D86: BALADA - Březinky | E86: Pokladna SCO1 | F86: profikasa | G86: 46132 | H86: 0.60641204 | I86: 161000362 | J86: NE | K86: 68356051 | L86: 287502 | M86: ČEROZFRUCHT České Budějovice | N86: 70202 | O86: Brambory rané | P86: NE | R86: 22.9 | S86: =R86-T86 -> 20.446429 | T86: =R86*U86/(U86+100) -> 2.4535714 | U86: 12 | V86: 0 | W86: 0.298 | X86: KG | Y86: =R86*W86 -> 6.8242 | Z86: =S86*W86 -> 6.0930357 | AA86: =T86*W86 -> 0.73116429 | AB86: =V86*W86 -> 0 | AC86: =(R86+V86)*W86 -> 6.8242 | AD86: 22.9 | AE86: 0 | AF86: 0
A87: CZ60738677 | B87: RAPO BRNO, s.r.o. | C87: 96 | D87: BALADA - Březinky | E87: Pokladna SCO1 | F87: profikasa | G87: 46132 | H87: 0.60641204 | I87: 161000362 | J87: NE | K87: 68A66807 | L87: 8594023940389 | M87: Jiří Bareš - GIRA | N87: 70201 | O87: Směs polévkové zeleniny 40 | P87: NE | R87: 49.9 | S87: =R87-T87 -> 44.553571 | T87: =R87*U87/(U87+100) -> 5.3464286 | U87: 12 | V87: 0 | W87: 1 | X87: KS | Y87: =R87*W87 -> 49.9 | Z87: =S87*W87 -> 44.553571 | AA87: =T87*W87 -> 5.3464286 | AB87: =V87*W87 -> 0 | AC87: =(R87+V87)*W87 -> 49.9 | AD87: 49.9 | AE87: 0 | AF87: 0
A88: CZ60738677 | B88: RAPO BRNO, s.r.o. | C88: 96 | D88: BALADA - Březinky | E88: Pokladna SCO1 | F88: profikasa | G88: 46132 | H88: 0.60921296 | I88: 161000363 | J88: NE | K88: 31697585 | L88: 8593807544058 | M88: OLMA, a.s. | N88: 20106 | O88: Florian drink višeň 400g | P88: NE | R88: 22.9 | S88: =R88-T88 -> 20.446429 | T88: =R88*U88/(U88+100) -> 2.4535714 | U88: 12 | V88: 0 | W88: 1 | X88: KS | Y88: =R88*W88 -> 22.9 | Z88: =S88*W88 -> 20.446429 | AA88: =T88*W88 -> 2.4535714 | AB88: =V88*W88 -> 0 | AC88: =(R88+V88)*W88 -> 22.9 | AD88: 22.9 | AE88: 0 | AF88: 0
A89: CZ60738677 | B89: RAPO BRNO, s.r.o. | C89: 96 | D89: BALADA - Březinky | E89: Pokladna SCO1 | F89: profikasa | G89: 46132 | H89: 0.60921296 | I89: 161000363 | J89: NE | K89: 90385963 | L89: 8594162858866 | M89: Bidfood Czech Republic s.r.o. | N89: 10104 | O89: Kobliha s meruňkovou nápln | P89: NE | R89: 13.9 | S89: =R89-T89 -> 12.410714 | T89: =R89*U89/(U89+100) -> 1.4892857 | U89: 12 | V89: 0 | W89: 4 | X89: KS | Y89: =R89*W89 -> 55.6 | Z89: =S89*W89 -> 49.642857 | AA89: =T89*W89 -> 5.9571429 | AB89: =V89*W89 -> 0 | AC89: =(R89+V89)*W89 -> 55.6 | AD89: 13.9 | AE89: 0 | AF89: 0
A90: CZ60738677 | B90: RAPO BRNO, s.r.o. | C90: 96 | D90: BALADA - Březinky | E90: Pokladna SCO1 | F90: profikasa | G90: 46132 | H90: 0.61165509 | I90: 161000364 | J90: NE | K90: 28962464 | L90: 8594174210119 | M90: HOKA TRADE s.r.o. | N90: 52402 | O90: Instantní nudlová polévka | P90: NE | R90: 12.4 | S90: =R90-T90 -> 11.071429 | T90: =R90*U90/(U90+100) -> 1.3285714 | U90: 12 | V90: 0 | W90: 1 | X90: KS | Y90: =R90*W90 -> 12.4 | Z90: =S90*W90 -> 11.071429 | AA90: =T90*W90 -> 1.3285714 | AB90: =V90*W90 -> 0 | AC90: =(R90+V90)*W90 -> 12.4 | AD90: 12.4 | AE90: 0 | AF90: 0
A91: CZ60738677 | B91: RAPO BRNO, s.r.o. | C91: 96 | D91: BALADA - Březinky | E91: Pokladna SCO1 | F91: profikasa | G91: 46132 | H91: 0.61165509 | I91: 161000364 | J91: NE | K91: 31122106 | L91: 8594006845717 | M91: Mlékárna Hlinsko, a.s. | N91: 50404 | O91: Lascato na cappuccino 1l | P91: NE | R91: 47.9 | S91: =R91-T91 -> 42.767857 | T91: =R91*U91/(U91+100) -> 5.1321429 | U91: 12 | V91: 0 | W91: 1 | X91: KS | Y91: =R91*W91 -> 47.9 | Z91: =S91*W91 -> 42.767857 | AA91: =T91*W91 -> 5.1321429 | AB91: =V91*W91 -> 0 | AC91: =(R91+V91)*W91 -> 47.9 | AD91: 47.9 | AE91: 0 | AF91: 0
A92: CZ60738677 | B92: RAPO BRNO, s.r.o. | C92: 96 | D92: BALADA - Březinky | E92: Pokladna SCO1 | F92: profikasa | G92: 46132 | H92: 0.61165509 | I92: 161000364 | J92: NE | K92: 37236103 | L92: 8595241505886 | M92: GASTON, s.r.o. | N92: 51601 | O92: Olivy černé bez pecky ve s | P92: NE | R92: 54.9 | S92: =R92-T92 -> 49.017857 | T92: =R92*U92/(U92+100) -> 5.8821429 | U92: 12 | V92: 0 | W92: 1 | X92: KS | Y92: =R92*W92 -> 54.9 | Z92: =S92*W92 -> 49.017857 | AA92: =T92*W92 -> 5.8821429 | AB92: =V92*W92 -> 0 | AC92: =(R92+V92)*W92 -> 54.9 | AD92: 54.9 | AE92: 0 | AF92: 0
A93: CZ60738677 | B93: RAPO BRNO, s.r.o. | C93: 96 | D93: BALADA - Březinky | E93: Pokladna SCO1 | F93: profikasa | G93: 46132 | H93: 0.61165509 | I93: 161000364 | J93: NE | K93: 38130148 | L93: 8594008332000 | M93: Essa spol.s r.o. | N93: 51701 | O93: Hrušky půlené loupané 410g | P93: NE | R93: 29.9 | S93: =R93-T93 -> 26.696429 | T93: =R93*U93/(U93+100) -> 3.2035714 | U93: 12 | V93: 0 | W93: 1 | X93: KS | Y93: =R93*W93 -> 29.9 | Z93: =S93*W93 -> 26.696429 | AA93: =T93*W93 -> 3.2035714 | AB93: =V93*W93 -> 0 | AC93: =(R93+V93)*W93 -> 29.9 | AD93: 29.9 | AE93: 0 | AF93: 0
A94: CZ60738677 | B94: RAPO BRNO, s.r.o. | C94: 96 | D94: BALADA - Březinky | E94: Pokladna SCO1 | F94: profikasa | G94: 46132 | H94: 0.61165509 | I94: 161000364 | J94: NE | K94: 38210100 | L94: 9001466300575 | M94: VOG, s.r.o. | N94: 51702 | O94: Ovocný koktejl Happ Frucht | P94: NE | R94: 37.9 | S94: =R94-T94 -> 33.839286 | T94: =R94*U94/(U94+100) -> 4.0607143 | U94: 12 | V94: 0 | W94: 1 | X94: KS | Y94: =R94*W94 -> 37.9 | Z94: =S94*W94 -> 33.839286 | AA94: =T94*W94 -> 4.0607143 | AB94: =V94*W94 -> 0 | AC94: =(R94+V94)*W94 -> 37.9 | AD94: 37.9 | AE94: 0 | AF94: 0
A95: CZ60738677 | B95: RAPO BRNO, s.r.o. | C95: 96 | D95: BALADA - Březinky | E95: Pokladna SCO1 | F95: profikasa | G95: 46132 | H95: 0.61165509 | I95: 161000364 | J95: NE | K95: 39385494 | L95: 8595624783337 | M95: Bidfood Czech Republic s.r.o. | N95: 20201 | O95: Mrkvový salát s ananasem N | P95: NE | R95: 37.9 | S95: =R95-T95 -> 33.839286 | T95: =R95*U95/(U95+100) -> 4.0607143 | U95: 12 | V95: 0 | W95: 1 | X95: KS | Y95: =R95*W95 -> 37.9 | Z95: =S95*W95 -> 33.839286 | AA95: =T95*W95 -> 4.0607143 | AB95: =V95*W95 -> 0 | AC95: =(R95+V95)*W95 -> 37.9 | AD95: 37.9 | AE95: 0 | AF95: 0
... A100: CZ60738677 | B100: RAPO BRNO, s.r.o. | C100: 96 | D100: BALADA - Březinky | E100: Pokladna SCO1 | F100: profikasa | G100: 46132 | H100: 0.61861111 | I100: 161000367 | J100: NE | K100: 12101579 | L100: 3800020403686 | M100: Nestlé Česko | N100: 51106 | O100: Lentilky Hexatube 28g | P100: NE | R100: 18.9 | S100: =R100-T100 -> 16.875 | T100: =R100*U100/(U100+100) -> 2.025 | U100: 12 | V100: 0 | W100: 1 | X100: KS | Y100: =R100*W100 -> 18.9 | Z100: =S100*W100 -> 16.875 | AA100: =T100*W100 -> 2.025 | AB100: =V100*W100 -> 0 | AC100: =(R100+V100)*W100 -> 18.9 | AD100: 18.9 | AE100: 0 | AF100: 0
A101: CZ60738677 | B101: RAPO BRNO, s.r.o. | C101: 96 | D101: BALADA - Březinky | E101: Pokladna SCO1 | F101: profikasa | G101: 46132 | H101: 0.61861111 | I101: 161000367 | J101: NE | K101: 53725259 | L101: 8594044363433 | M101: Pivovary Lobkowicz Group, a.s. | N101: 52101 | O101: Ježek Duklák 12 světlý lež | P101: ANO | Q101: BALADA 26_9A | R101: 15.9 | S101: =R101-T101 -> 13.140496 | T101: =R101*U101/(U101+100) -> 2.7595041 | U101: 21 | V101: 0 | W101: 4 | X101: KS | Y101: =R101*W101 -> 63.6 | Z101: =S101*W101 -> 52.561983 | AA101: =T101*W101 -> 11.038017 | AB101: =V101*W101 -> 0 | AC101: =(R101+V101)*W101 -> 63.6 | AD101: 15.9 | AE101: 0 | AF101: 0
A102: CZ60738677 | B102: RAPO BRNO, s.r.o. | C102: 96 | D102: BALADA - Březinky | E102: Pokladna SCO1 | F102: profikasa | G102: 46132 | H102: 0.61861111 | I102: 161000367 | J102: NE | K102: 68356200 | L102: 287531 | M102: ČEROZFRUCHT České Budějovice | N102: 70202 | O102: Okurka hadovka | P102: NE | R102: 49.9 | S102: =R102-T102 -> 44.553571 | T102: =R102*U102/(U102+100) -> 5.3464286 | U102: 12 | V102: 0 | W102: 0.292 | X102: KG | Y102: =R102*W102 -> 14.5708 | Z102: =S102*W102 -> 13.009643 | AA102: =T102*W102 -> 1.5611571 | AB102: =V102*W102 -> 0 | AC102: =(R102+V102)*W102 -> 14.5708 | AD102: 49.9 | AE102: 0 | AF102: 0
A103: CZ60738677 | B103: RAPO BRNO, s.r.o. | C103: 96 | D103: BALADA - Březinky | E103: Pokladna SCO1 | F103: profikasa | G103: 46132 | H103: 0.61861111 | I103: 161000367 | J103: NE | K103: 90125141 | L103: 8590077341769 | M103: PENAM, a.s. | N103: 10201 | O103: Rohlík zábrdovický tmavý 6 | P103: NE | R103: 7.5 | S103: =R103-T103 -> 6.6964286 | T103: =R103*U103/(U103+100) -> 0.80357143 | U103: 12 | V103: 0 | W103: 6 | X103: KS | Y103: =R103*W103 -> 45 | Z103: =S103*W103 -> 40.178571 | AA103: =T103*W103 -> 4.8214286 | AB103: =V103*W103 -> 0 | AC103: =(R103+V103)*W103 -> 45 | AD103: 7.5 | AE103: 0 | AF103: 0
A104: CZ60738677 | B104: RAPO BRNO, s.r.o. | C104: 96 | D104: BALADA - Březinky | E104: Pokladna SCO1 | F104: profikasa | G104: 46132 | H104: 0.61861111 | I104: 161000367 | J104: NE | K104: 90385240 | M104: Bidfood Czech Republic s.r.o. | N104: 10101 | O104: Donut s barevným posypem 5 | P104: NE | R104: 15.9 | S104: =R104-T104 -> 14.196429 | T104: =R104*U104/(U104+100) -> 1.7035714 | U104: 12 | V104: 0 | W104: 2 | X104: KS | Y104: =R104*W104 -> 31.8 | Z104: =S104*W104 -> 28.392857 | AA104: =T104*W104 -> 3.4071429 | AB104: =V104*W104 -> 0 | AC104: =(R104+V104)*W104 -> 31.8 | AD104: 15.9 | AE104: 0 | AF104: 0
A105: CZ60738677 | B105: RAPO BRNO, s.r.o. | C105: 96 | D105: BALADA - Březinky | E105: Pokladna SCO1 | F105: profikasa | G105: 46132 | H105: 0.61861111 | I105: 161000367 | J105: NE | K105: 90385924 | L105: 8594162852291 | M105: Bidfood Czech Republic s.r.o. | N105: 10101 | O105: Rohlík císařský 95g | P105: NE | R105: 11.9 | S105: =R105-T105 -> 10.625 | T105: =R105*U105/(U105+100) -> 1.275 | U105: 12 | V105: 0 | W105: 1 | X105: KS | Y105: =R105*W105 -> 11.9 | Z105: =S105*W105 -> 10.625 | AA105: =T105*W105 -> 1.275 | AB105: =V105*W105 -> 0 | AC105: =(R105+V105)*W105 -> 11.9 | AD105: 11.9 | AE105: 0 | AF105: 0
A106: CZ60738677 | B106: RAPO BRNO, s.r.o. | C106: 96 | D106: BALADA - Březinky | E106: Pokladna SCO1 | F106: profikasa | G106: 46132 | H106: 0.61861111 | I106: 161000367 | J106: NE | K106: 90868262 | L106: 5907489681773 | M106: Bidfood Czech Republic s.r.o. | N106: 10104 | O106: Donut s jahodovou příchutí | P106: NE | R106: 15.9 | S106: =R106-T106 -> 14.196429 | T106: =R106*U106/(U106+100) -> 1.7035714 | U106: 12 | V106: 0 | W106: 2 | X106: KS | Y106: =R106*W106 -> 31.8 | Z106: =S106*W106 -> 28.392857 | AA106: =T106*W106 -> 3.4071429 | AB106: =V106*W106 -> 0 | AC106: =(R106+V106)*W106 -> 31.8 | AD106: 15.9 | AE106: 0 | AF106: 0
A107: CZ60738677 | B107: RAPO BRNO, s.r.o. | C107: 96 | D107: BALADA - Březinky | E107: Pokladna SCO1 | F107: profikasa | G107: 46132 | H107: 0.61861111 | I107: 161000367 | J107: NE | K107: 90933710 | L107: 283053 | M107: PRANTL Masný průmysl s.r.o. | N107: 30105 | O107: Paprikáš | P107: NE | R107: 282.9 | S107: =R107-T107 -> 252.58929 | T107: =R107*U107/(U107+100) -> 30.310714 | U107: 12 | V107: 0 | W107: 0.154 | X107: KG | Y107: =R107*W107 -> 43.5666 | Z107: =S107*W107 -> 38.89875 | AA107: =T107*W107 -> 4.66785 | AB107: =V107*W107 -> 0 | AC107: =(R107+V107)*W107 -> 43.5666 | AD107: 282.9 | AE107: 0 | AF107: 0
A108: CZ60738677 | B108: RAPO BRNO, s.r.o. | C108: 96 | D108: BALADA - Březinky | E108: Pokladna SCO1 | F108: profikasa | G108: 46132 | H108: 0.62244213 | I108: 161000368 | J108: NE | K108: 11984140 | L108: 8586018180818 | M108: ENCINGER SK, s.r.o. | N108: 50702 | O108: Arašídy v těstíčku s přích | P108: NE | R108: 15.9 | S108: =R108-T108 -> 14.196429 | T108: =R108*U108/(U108+100) -> 1.7035714 | U108: 12 | V108: 0 | W108: 1 | X108: KS | Y108: =R108*W108 -> 15.9 | Z108: =S108*W108 -> 14.196429 | AA108: =T108*W108 -> 1.7035714 | AB108: =V108*W108 -> 0 | AC108: =(R108+V108)*W108 -> 15.9 | AD108: 15.9 | AE108: 0 | AF108: 0
A109: CZ60738677 | B109: RAPO BRNO, s.r.o. | C109: 96 | D109: BALADA - Březinky | E109: Pokladna SCO1 | F109: profikasa | G109: 46132 | H109: 0.62244213 | I109: 161000368 | J109: NE | K109: 68356093 | L109: 287014 | M109: ČEROZFRUCHT České Budějovice | N109: 70102 | O109: Jablka Red Chief | P109: NE | R109: 25.9 | S109: =R109-T109 -> 23.125 | T109: =R109*U109/(U109+100) -> 2.775 | U109: 12 | V109: 0 | W109: 0.016 | X109: KG | Y109: =R109*W109 -> 0.4144 | Z109: =S109*W109 -> 0.37 | AA109: =T109*W109 -> 0.0444 | AB109: =V109*W109 -> 0 | AC109: =(R109+V109)*W109 -> 0.4144 | AD109: 25.9 | AE109: 0 | AF109: 0
A110: CZ60738677 | B110: RAPO BRNO, s.r.o. | C110: 96 | D110: BALADA - Březinky | E110: Pokladna SCO1 | F110: profikasa | G110: 46132 | H110: 0.62753472 | I110: 161000369 | J110: NE | K110: 90979407 | L110: 8594017366829 | M110: Uzenářství a lahůdky Sláma s.r.o. | N110: 30201 | O110: Debrecínské párky 220g | P110: NE | R110: 62.9 | S110: =R110-T110 -> 56.160714 | T110: =R110*U110/(U110+100) -> 6.7392857 | U110: 12 | V110: 0 | W110: 1 | X110: KS | Y110: =R110*W110 -> 62.9 | Z110: =S110*W110 -> 56.160714 | AA110: =T110*W110 -> 6.7392857 | AB110: =V110*W110 -> 0 | AC110: =(R110+V110)*W110 -> 62.9 | AD110: 62.9 | AE110: 0 | AF110: 0
A111: CZ60738677 | B111: RAPO BRNO, s.r.o. | C111: 96 | D111: BALADA - Březinky | E111: Pokladna SCO1 | F111: profikasa | G111: 46132 | H111: 0.62930556 | I111: 161000370 | J111: NE | K111: 14152159 | L111: 90444470 | M111: Ed. Haas CZ | N111: 51003 | O111: Štangličky ovocné PEZ 9g | P111: NE | R111: 5.4 | S111: =R111-T111 -> 4.8214286 | T111: =R111*U111/(U111+100) -> 0.57857143 | U111: 12 | V111: 0 | W111: 1 | X111: KS | Y111: =R111*W111 -> 5.4 | Z111: =S111*W111 -> 4.8214286 | AA111: =T111*W111 -> 0.57857143 | AB111: =V111*W111 -> 0 | AC111: =(R111+V111)*W111 -> 5.4 | AD111: 5.4 | AE111: 0 | AF111: 0
A112: CZ60738677 | B112: RAPO BRNO, s.r.o. | C112: 96 | D112: BALADA - Březinky | E112: Pokladna SCO1 | F112: profikasa | G112: 46132 | H112: 0.62930556 | I112: 161000370 | J112: NE | K112: 21727190 | L112: 8586015310492 | M112: VITAR, s.r.o. | N112: 50205 | O112: Energit Hroznový cukr pome | P112: NE | R112: 17.9 | S112: =R112-T112 -> 15.982143 | T112: =R112*U112/(U112+100) -> 1.9178571 | U112: 12 | V112: 0 | W112: 1 | X112: KS | Y112: =R112*W112 -> 17.9 | Z112: =S112*W112 -> 15.982143 | AA112: =T112*W112 -> 1.9178571 | AB112: =V112*W112 -> 0 | AC112: =(R112+V112)*W112 -> 17.9 | AD112: 17.9 | AE112: 0 | AF112: 0
...

Sheet Zrušené položky
A1: Identifikace | G1: Datum a doklad | I1: Zboží | N1: Jednotková cena zboží a obalu | S1: Množství | U1: Celkem za položku zboží a obalu
N2: Zboží | R2: Obal | U2: =SUBTOTAL(109,U4:U999225) -> 0 | V2: =SUBTOTAL(109,V4:V999225) -> 0 | W2: =SUBTOTAL(109,W4:W999225) -> 0 | X2: =SUBTOTAL(109,X4:X999225) -> 0 | Y2: =SUBTOTAL(109,Y4:Y999225) -> 0
A3: DIČ | B3: Název firmy | C3: ID provozovny | D3: Název provozovny | E3: ID pokladny | F3: Uživatel | G3: Datum | H3: Čas | I3: Číslo zboží | J3: EAN kód | K3: Výrobce | L3: Třídící strom | M3: Název zboží | N3: Cena s DPH | O3: Základ DPH | P3: DPH | Q3: Sazba DPH | R3: Cena | S3: Množství | T3: Jednotka | U3: Celkem zboží s DPH | V3: Celkem zboží základ DPH | W3: Celkem zboží DPH | X3: Celkem obaly | Y3: Celkem zboží a obaly s DPH
